Workbook

Sheet Hoja 1
A2: NOMBRE | B2: CARGO | C2: ESTADO | D2: NACIONALIDAD | E2: CUMPLEAÑOS | F2: IMAGEN | G2: PASSAPORTO | H2: SCADENZA PASSAPORTO | I2: CARTA DI IDENTITA | J2: SCADENZA CARTA IDENTITA | K2: PERMESSO DI SOGGIORNO | L2: SCADENZA SOGGIORNO | M2: PATENTE | N2: SCADENZA PATENTE | O2: TRADUZIONE PATENTE | P2: SCADENZA TRADUZIONE | Q2: C. FISCALE | R2: SCADENZA C. FISCALE | S2: CONTRATO | T2: SCADENZA CONTRATO | U2: TELEFONO | V2: CORREO ELECTRONICO | W2: DIRECCION | X2: ÁREA | Y2: Correo_Supervisor_Asignado | Z2: Id_Trabajador | AA2: PERMISO UNIVEX | AB2: CU 2024 | AC2: DIMISSIONE | AD2: RESPONSIVA
A3: CARLOS GAMONAL | B3: COO / DIRECTOR OPERACIONES | C3: ACTIVO | D3: PERU | E3: 26791 | F3: Hoja 1_Images/G001.IMAGEN.003525.png | I3: Hoja 1_Files_/CARLOS GAMONAL.CARTA DI IDENTITA.165615.pdf | J3: 48034 | M3: Hoja 1_Files_/CARLOS GAMONAL.PATENTE.165615.pdf | N3: 47245 | Q3: Hoja 1_Files_/CARLOS GAMONAL.C. FISCALE.165615.pdf | S3: Hoja 1_Files_/CARLOS GAMONAL.CONTRATO.141539.pdf | U3: 3201499727 | V3: carlos.ga@gamonaltrasporti.com | W3: Via Domenico Cimarosa, 5, 20096 Pioltello MI, Italia | X3: UNIVEX/DHL | Z3: G001 | AB3: Hoja 1_Files_/G001.CU 2024.120944.pdf
A4: EMERSON GAMONAL | B4: CEO / DIRECTOR GENERAL | C4: ACTIVO | D4: PERUANO | E4: 26926 | F4: Hoja 1_Images/G002.IMAGEN.003550.png | K4: Hoja 1_Files_/G002.PERMESSO DI SOGGIORNO.220721.pdf | L4: 46311 | M4: Hoja 1_Files_/EMERSON GAMONAL.PATENTE.112542.pdf | N4: 47500 | Q4: Hoja 1_Files_/EMERSON GAMONAL.C. FISCALE.112542.pdf | R4: 47483 | S4: Hoja 1_Files_/EMERSON GAMONAL.CONTRATO.180441.pdf | T4: 47483 | U4: 3519033631 | V4: emerson.gs@gamonaltrasporti.com | W4: Via Domenico Cimarosa, 5, 20096 Pioltello MI, Italia | X4: UNIVEX/DHL | Z4: G002 | AB4: Hoja 1_Files_/G002.CU 2024.120922.pdf
A5: YAN GAMONAL | B5: DIRECTOR DE DESARROLLO | C5: ACTIVO | D5: PERUANA | E5: 35819 | F5: Hoja 1_Images/G003.IMAGEN.003537.png | G5: Hoja 1_Files_/G003.PASSAPORTO.220031.pdf | H5: 49509 | I5: Hoja 1_Files_/YAN GAMONAL.CARTA DI IDENTITA.053659.pdf | J5: 48001 | M5: Hoja 1_Files_/YAN GAMONAL.PATENTE.053700.pdf | N5: 49039 | U5: +51965132485 | V5: yan.gs@gamonaltrasporti.com | W5: Urb. Santa Beatriz Mz M Lt8 Callao | X5: UNIVEX/DHL | Z5: G003
A6: NATALIA PLUA | B6: SUPERVISORA GENERAL | C6: ACTIVO | D6: ECUATORIANA | E6: 36491 | F6: Hoja 1_Images/G004.IMAGEN.225042.png | I6: Hoja 1_Files_/NATALIA PLUA.CARTA DI IDENTITA.181551.pdf | J6: 47449 | M6: Hoja 1_Files_/NATALIA PLUA.PATENTE.181551.pdf | N6: 47449 | Q6: Hoja 1_Files_/NATALIA PLUA.C. FISCALE.181550.pdf | R6: 46713 | S6: Hoja 1_Files_/NATALIA PLUA.CONTRATO.181552.pdf | T6: 47483 | U6: 3286071390 | V6: autista.gamonaltrasporti@gmail.com | W6: Via Magenta, 38, 20017 Rho MI, Italia | X6: UNIVEX/DHL | Z6: G004 | AA6: Hoja 1_Files_/G004.PERMISO UNIVEX.164135.pdf | AB6: Hoja 1_Files_/G004.CU 2024.180719.pdf
A7: LUIS POMA | B7: SUPERVISOR | C7: INACTIVO | D7: PERU | E7: 32389 | F7: Hoja 1_Images/G005.IMAGEN.225057.png | I7: Hoja 1_Images/G005.CARTA DI IDENTITA.164951.jpg | J7: 46999 | K7: Hoja 1_Images/G005.PERMESSO DI SOGGIORNO.164951.jpg | L7: 46563 | M7: Hoja 1_Files_/LUIS POMA.PATENTE.182132.pdf | P7: 46003 | Q7: Hoja 1_Images/G005.C. FISCALE.164952.jpg | R7: 45989 | S7: Hoja 1_Files_/LUIS POMA.CONTRATO.182133. CONTRATO LUIS IND.pdf | U7: 3343849127 | V7: luizpoma.lp@gmail.com | W7: Via Moneta Teodoro, 1, 23876 Monticello LC, Italia | X7: INACTIVO | Z7: G005 | AA7: Hoja 1_Files_/G005.PERMISO UNIVEX.164204.pdf | AB7: Hoja 1_Files_/G005.CU 2024.180737.pdf
A8: MARTIN RODRIGUEZ | B8: SUPERVISOR | C8: ACTIVO | D8: PERU | E8: 33957 | F8: Hoja 1_Images/G006.IMAGEN.202138.png | I8: Hoja 1_Files_/MARTIN RODRIGUEZ.CARTA DI IDENTITA.192726.pdf | M8: Hoja 1_Files_/MARTIN RODRIGUEZ.PATENTE.182705. Patente MARTIN.pdf | Q8: Hoja 1_Files_/MARTIN RODRIGUEZ.C. FISCALE.182705. Codice Fiscale MARTIN.pdf | S8: Hoja 1_Files_/MARTIN RODRIGUEZ.CONTRATO.182707.pdf | U8: 3519584517 | V8: gamonaltrasporti.spedizione@gmail.com | W8: Via Montebello, 26, 20121 Milano MI, Italia | X8: DHL | Y8: gamonaltrasporti.spedizione@gmail.com | Z8: G006 | AA8: Hoja 1_Files_/G006.PERMISO UNIVEX.164420.pdf | AB8: Hoja 1_Files_/G006.CU 2024.181136.pdf
A9: MARVIN CASTILLO | B9: SUPERVISOR | C9: ACTIVO | D9: PERU | E9: 33356 | F9: Hoja 1_Images/G008.IMAGEN.164019.png | I9: Hoja 1_Files_/MARVIN CASTILLO.CARTA DI IDENTITA.183321. Carta di identita MARVIN.pdf | J9: 46871 | M9: Hoja 1_Files_/MARVIN CASTILLO.PATENTE.183320. Patente MARVIN.pdf | Q9: Hoja 1_Files_/MARVIN CASTILLO.C. FISCALE.183320. Codice fiscale MARVIN.pdf | S9: Hoja 1_Files_/MARVIN CASTILLO.CONTRATO.183322. CONTRATO MARVIN.pdf | U9: 3338356449 | V9: marvin28abril@gmail.com | W9: Viale Domenico Cimarosa, 5 pioltello | X9: UNIVEX | Y9: marvin28abril@gmail.com | Z9: G008 | AA9: Hoja 1_Files_/G008.PERMISO UNIVEX.164235.pdf | AB9: Hoja 1_Files_/G008.CU 2024.180159.pdf
A10: CESAR PLUA | B10: AUTISTA | C10: ACTIVO | D10: ECUATORIANO | E10: 20942 | F10: Hoja 1_Images/G007.IMAGEN.164006.png | I10: Hoja 1_Files_/CESAR PLUA.CARTA DI IDENTITA.183020. Carta di identita CESAR.pdf | J10: 47605 | K10: Hoja 1_Files_/G007.PERMESSO DI SOGGIORNO.103700.S_CESAR.pdf | L10: 48767 | M10: Hoja 1_Files_/CESAR PLUA.PATENTE.183020. Patente CÉSAR.pdf | N10: 46318 | Q10: Hoja 1_Files_/CESAR PLUA.C. FISCALE.183020. Codice fiscale CESAR.pdf | R10: 45926 | U10: 3493471721 | W10: Viale Palmiro Togliatti, 114, 20089 Rozzano MI, Italia | X10: UNIVEX | Y10: marvin28abril@gmail.com | Z10: G007 | AA10: Hoja 1_Files_/G007.PERMISO UNIVEX.164219.pdf | AB10: Hoja 1_Files_/G007.CU 2024.180700.pdf
A11: DOMINICK LEON | B11: AUTISTA | C11: INACTIVO | D11: PERUANO | E11: 33622 | F11: Hoja 1_Images/DOMINICK LEON.IMAGEN.055121.png | I11: Hoja 1_Files_/DOMINICK LEON.CARTA DI IDENTITA.183612. Carta di identita DOMINICK.pdf | M11: Hoja 1_Files_/DOMINICK LEON.PATENTE.183612. Patente DOMINI.pdf | Q11: Hoja 1_Files_/DOMINICK LEON.C. FISCALE.183612. Tessera DOMINICK.pdf | U11: 3277908045 | W11: Via Aldo Moro, 9, 24058 Sola BG, Italia | X11: INACTIVO | Z11: G009
A12: IVAN HERRERA | B12: AUTISTA | C12: INACTIVO | D12: PERUANO | E12: 35713 | F12: Hoja 1_Images/IVAN HERRERA.IMAGEN.055145.png | I12: Hoja 1_Files_/IVAN HERRERA.CARTA DI IDENTITA.183921. Carta di identita IVAN.pdf | M12: Hoja 1_Files_/IVAN HERRERA.PATENTE.183921. Patente IVAN.pdf | Q12: Hoja 1_Files_/IVAN HERRERA.C. FISCALE.183921. Tessera IVAN.pdf | S12: Hoja 1_Files_/IVAN HERRERA.CONTRATO.183923. CONTRATO IVAN IND.pdf | U12: 3516813140 | W12: Via Milano, 7, 23871 Lomagna LC, Italia | X12: INACTIVO | Z12: G010 | AB12: Hoja 1_Files_/G010.CU 2024.180627.pdf
A13: ROMARIO QUISPE | B13: AUTISTA | C13: ACTIVO | D13: PERUANO | E13: 34943 | F13: Hoja 1_Images/G011.IMAGEN.230301.png | I13: Hoja 1_Files_/ROMARIO QUISPE.CARTA DI IDENTITA.184248. Carta di identita ROMARIO.pdf | M13: Hoja 1_Files_/ROMARIO QUISPE.PATENTE.150924.pdf | S13: Hoja 1_Files_/ROMARIO QUISPE.CONTRATO.010947.pdf | U13: 3926274483 | V13: quispehinostrozaromario1995@gmail.com | W13: Via Rogoredo, 7, 20138 Milano MI, Italia | X13: UNIVEX | Y13: marvin28abril@gmail.com | Z13: G011 | AA13: Hoja 1_Files_/G011.PERMISO UNIVEX.164432.pdf | AB13: Hoja 1_Files_/G011.CU 2024.180940.pdf | AC13: Hoja 1_Files_/G011.DIMISSIONE.171911.pdf
A14: YHEYSON ACHAICA | B14: AUTISTA | C14: INACTIVO | D14: PERUANO | E14: 36025 | F14: Hoja 1_Images/YHEYSON ACHAICA.IMAGEN.055215.png | I14: Hoja 1_Files_/YHEYSON ACHAICA.CARTA DI IDENTITA.185200. Carta di identita YHEYSON.pdf | M14: Hoja 1_Files_/YHEYSON ACHAICA.PATENTE.185200. Patente YHEYSON.pdf | Q14: Hoja 1_Files_/YHEYSON ACHAICA.C. FISCALE.185200. Codice fiscale YHEYSON.pdf | S14: Hoja 1_Files_/YHEYSON ACHAICA.CONTRATO.230832.pdf | U14: 3513498499 | W14: Via F. Cilea, 20096 Pioltello MI, Italia | X14: INACTIVO | Z14: G012 | AB14: Hoja 1_Files_/G012.CU 2024.175843.pdf
A15: ADOLFO ROSALES | B15: AUTISTA | C15: INACTIVO | D15: SALVADOREÑO | E15: 30938 | F15: Hoja 1_Images/ADOLFO ROSALES.IMAGEN.055233.png | I15: Hoja 1_Files_/ADOLFO ROSALES.CARTA DI IDENTITA.185314. Carta di identita ADOLFO.pdf | M15: Hoja 1_Files_/ADOLFO ROSALES.PATENTE.185314. Patente ADOLFO.pdf | Q15: Hoja 1_Files_/ADOLFO ROSALES.C. FISCALE.185314. Codice Fiscale ADOLFO.pdf | S15: Hoja 1_Files_/ADOLFO ROSALES.CONTRATO.185316.pdf | U15: 3505307941 | W15: Via G. Matteotti, 10, 20019 Settimo Milanese MI, Italia | X15: INACTIVO | Z15: G013 | AB15: Hoja 1_Files_/G013.CU 2024.181721.pdf
A16: ALONSO TAMARA | B16: AUTISTA | C16: ACTIVO | D16: PERU | E16: 33799 | F16: Hoja 1_Images/G014.IMAGEN.225829.png | K16: Hoja 1_Files_/G014.PERMESSO DI SOGGIORNO.150250.pdf | L16: 46227 | M16: Hoja 1_Files_/G014.PATENTE.150250.pdf | N16: 48458 | O16: Hoja 1_Files_/G014.TRADUZIONE PATENTE.150250.pdf | P16: 45944 | Q16: Hoja 1_Files_/ALONSO TAMARA.C. FISCALE.104936.pdf | S16: Hoja 1_Files_/G014.CONTRATO.155159.pdf | U16: 3312380816 | V16: 14jatg07@gmail.com | W16: Via F. Cilea, 4, 20096 Pioltello MI, Italia | X16: DHL | Y16: gamonaltrasporti.spedizione@gmail.com | Z16: G014 | AD16: Hoja 1_Files_/G014.RESPONSIVA.073454.pdf
A17: EDWARD GUERRERO | B17: AUTISTA | C17: INACTIVO | D17: PERUANO | E17: 33066 | F17: Hoja 1_Images/G015.IMAGEN.225145.png | I17: Hoja 1_Files_/EDWARD GUERRERO.CARTA DI IDENTITA.185751. Carta di identita EDWARD.pdf | M17: Hoja 1_Files_/EDWARD GUERRERO.PATENTE.185751. Patente EDWARD.pdf | Q17: Hoja 1_Files_/EDWARD GUERRERO.C. FISCALE.185752. Codice fiscale EDWARD.pdf | S17: Hoja 1_Files_/EDWARD GUERRERO.CONTRATO.150951.pdf | U17: 3514032510 | W17: Viale Fratelli Cervi, 19, 20098 San Giuliano Milanese MI, Italia | X17: INACTIVO | Z17: G015 | AA17: Hoja 1_Files_/G015.PERMISO UNIVEX.164250.pdf | AB17: Hoja 1_Files_/G015.CU 2024.180554.pdf
A18: JUAN TEJADA | B18: AUTISTA | C18: ACTIVO | D18: SALVADOREÑO | E18: 36795 | F18: Hoja 1_Images/G016.IMAGEN.193310.png | I18: Hoja 1_Files_/JUAN TEJADA.CARTA DI IDENTITA.190103. Carta di identita JUAN.pdf | M18: Hoja 1_Files_/JUAN TEJADA.PATENTE.190103. Patente JUAN_.pdf | Q18: Hoja 1_Files_/JUAN TEJADA.C. FISCALE.190103. Codice fiscale JUAN.pdf | S18: Hoja 1_Files_/G016.CONTRATO.110538.25 -file.pdf | U18: 3517498714 | W18: Viale Leonardo da Vinci, 130, 20090 Trezzano sul Naviglio MI, Italia | X18: UNIVEX | Y18: marvin28abril@gmail.com | Z18: G016 | AA18: Hoja 1_Files_/G016.PERMISO UNIVEX.164306.pdf | AB18: Hoja 1_Files_/G016.CU 2024.181746.pdf
A19: JURGEN PALIZA | B19: AUTISTA | C19: ACTIVO | D19: PERU | E19: 30079 | F19: Hoja 1_Images/G017.IMAGEN.164202.png | I19: Hoja 1_Files_/G017.CARTA DI IDENTITA.111820.pdf | J19: 46756 | K19: Hoja 1_Files_/G017.PERMESSO DI SOGGIORNO.111824.pdf | L19: 46096 | M19: Hoja 1_Files_/G017.PATENTE.111820.pdf | N19: 47534 | Q19: Hoja 1_Files_/G017.C. FISCALE.111820.pdf | R19: 47102 | S19: Hoja 1_Files_/JURGEN PALIZA.CONTRATO.192901.pdf | U19: 3533506252 | V19: jurgen2000pv@gmail.com | W19: Via Alcide de Gasperi, 1, 20900 Monza MB, Italia | X19: UNIVEX | Y19: marvin28abril@gmail.com | Z19: G017 | AA19: Hoja 1_Files_/G017.PERMISO UNIVEX.164446.pdf | AB19: Hoja 1_Files_/G017.CU 2024.180641.pdf | AD19: Hoja 1_Files_/G017.RESPONSIVA.073744.pdf
A20: DUMINDA HADUN | B20: AUTISTA | C20: INACTIVO | D20: SRI LANKA | E20: 27084 | F20: Hoja 1_Images/DUMINDA HADUN.IMAGEN.055805.png | I20: Hoja 1_Files_/DUMINDA HADUN.CARTA DI IDENTITA.190633. CARTA DI IDENTITA DUMINDA.pdf | M20: Hoja 1_Files_/DUMINDA HADUN.PATENTE.190634. PATENTE DUMINDA.pdf | Q20: Hoja 1_Files_/DUMINDA HADUN.C. FISCALE.190634. TESSERA SANITARIA DUMINDA.pdf | S20: Hoja 1_Files_/DUMINDA HADUN.CONTRATO.190635.pdf | U20: 3312025402 | W20: Via Primo Maggio, 2, 20872 Porto d'Adda MB, Italia | X20: INACTIVO | Z20: G018 | AB20: Hoja 1_Files_/G018.CU 2024.180612.pdf
A21: SHANTHA NEELAPPAGE | B21: AUTISTA | C21: INACTIVO | D21: SRI LANKA | E21: 24961 | F21: Hoja 1_Images/SHANTHA NEELAPPAGE.IMAGEN.234228.png | I21: Hoja 1_Files_/SHANTHA NEELAPPAGE.CARTA DI IDENTITA.234228.pdf | M21: Hoja 1_Files_/SHANTHA NEELAPPAGE.PATENTE.234228.pdf | Q21: Hoja 1_Files_/SHANTHA NEELAPPAGE.C. FISCALE.234229.pdf | S21: Hoja 1_Files_/SHANTHA NEELAPPAGE.CONTRATO.234229.pdf | U21: 3279807682 | W21: Cascina degli Angeli, 5, 27020 Dorno PV, Italia | X21: INACTIVO | Z21: G019
A22: DIEGO MOLINA | B22: AUTISTA | C22: ACTIVO | D22: PERU | E22: 32570 | F22: Hoja 1_Images/G020.IMAGEN.193323.png | I22: Hoja 1_Files_/DIEGO MOLINA.CARTA DI IDENTITA.160435.pdf | Q22: Hoja 1_Files_/DIEGO MOLINA.C. FISCALE.160435.pdf | S22: Hoja 1_Files_/G020.CONTRATO.044700.pdf | U22: 3382692929 | V22: Alonsomolina0389@gmail.com | W22: Via Metastasio, 20123 Milano MI, Italia | X22: UNIVEX | Y22: marvin28abril@gmail.com | Z22: G020 | AA22: Hoja 1_Files_/G020.PERMISO UNIVEX.164325.pdf
A23: ANTONIO RIVERA | B23: AUTISTA | C23: ACTIVO | D23: PERU | E23: 26901 | F23: Hoja 1_Images/G021.IMAGEN.193346.png | I23: Hoja 1_Files_/ANTONIO RIVERA.CARTA DI IDENTITA.153916.pdf | M23: Hoja 1_Files_/ANTONIO RIVERA.PATENTE.153916.pdf | Q23: Hoja 1_Files_/ANTONIO RIVERA.C. FISCALE.111357.pdf | S23: Hoja 1_Files_/G021.CONTRATO.044757.pdf | U23: 3509340221 | V23: Antonio.rivera152535@gmail.com | W23: Via Leonardo Da Vinci, 49, 20092 Cinisello Balsamo MI, Italia | X23: UNIVEX | Y23: marvin28abril@gmail.com | Z23: G021 | AA23: Hoja 1_Files_/G021.PERMISO UNIVEX.164339.pdf
A24: EDUARDO SANTA CRUZ | B24: AUTISTA | C24: INACTIVO | D24: PERU | E24: 36052 | F24: Hoja 1_Images/G022.IMAGEN.230747.png | I24: Hoja 1_Files_/EDUARDO SANTA CRUZ.CARTA DI IDENTITA.213311.pdf | M24: Hoja 1_Files_/EDUARDO SANTA CRUZ.PATENTE.213311.pdf | U24: 38061122 | X24: INACTIVO | Z24: G022
A25: ELIZANGELA CHUMBE | B25: AUTISTA | C25: ACTIVO | D25: PERU | E25: 30599 | F25: Hoja 1_Images/G023.IMAGEN.164945.png | G25: Hoja 1_Images/G023.PASSAPORTO.131858.jpg | H25: 46604 | I25: Hoja 1_Files_/G023.CARTA DI IDENTITA.131853.pdf | J25: 49227 | K25: Hoja 1_Files_/G023.PERMESSO DI SOGGIORNO.131858.pdf | L25: 46031 | M25: Hoja 1_Files_/G023.PATENTE.131853.pdf | N25: 48325 | O25: Hoja 1_Files_/G023.TRADUZIONE PATENTE.131858.pdf | P25: 46070 | Q25: Hoja 1_Files_/G023.C. FISCALE.131853.pdf | R25: 45713 | S25: Hoja 1_Files_/ELIZANGELA.CONTRATO.105641.pdf | U25: 3478500365 | V25: elizangelasantillan@gmail.com | W25: Via Dante Alighieri, 52, 20821 Meda MB, Italia | X25: DHL | Y25: gamonaltrasporti.spedizione@gmail.com | Z25: G023 | AD25: Hoja 1_Files_/G023.RESPONSIVA.075925.pdf
A26: JULIO DIOSES | B26: AUTISTA | C26: ACTIVO | D26: PERU | E26: 29344 | F26: Hoja 1_Images/G024.IMAGEN.193337.png | I26: Hoja 1_Files_/JULIO DIOSES.CARTA DI IDENTITA.111106.pdf | K26: Hoja 1_Images/G024.PERMESSO DI SOGGIORNO.155515.jpg | M26: Hoja 1_Images/G024.PATENTE.155236.jpg | N26: 47301 | O26: Hoja 1_Images/G024.TRADUZIONE PATENTE.155515.jpg | P26: 46265 | Q26: Hoja 1_Files_/JULIO DIOSES.C. FISCALE.111108.pdf | S26: Hoja 1_Files_/G024.CONTRATO.044721.pdf | U26: 3338398834 | V26: jdioses79@gmail.com | W26: Via Pietro Metastasio, 1, 20900 Monza MB, Italia | X26: UNIVEX | Y26: marvin28abril@gmail.com | Z26: G024 | AA26: Hoja 1_Files_/G024.PERMISO UNIVEX.164359.pdf
A27: JUAN CARLOS LAZARO | B27: AUTISTA | C27: ACTIVO | D27: PERU | E27: 28737 | F27: Hoja 1_Images/G025.IMAGEN.164932.png | I27: Hoja 1_Files_/JUAN CARLOS.CARTA DI IDENTITA.182326.pdf | K27: Hoja 1_Files_/G025.PERMESSO DI SOGGIORNO.081821.pdf | L27: 45995 | M27: Hoja 1_Files_/JUAN CARLOS.PATENTE.182326.pdf | S27: Hoja 1_Files_/JUAN CARLOS.CONTRATO.195001.pdf | U27: 3208078297 | V27: Juancarloslazarolozano4@gmail.com | W27: Via S. Rocco, 118, 20831 Seregno MB, Italia | X27: DHL | Y27: gamonaltrasporti.spedizione@gmail.com | Z27: G025 | AD27: Hoja 1_Files_/G025.RESPONSIVA.073958.pdf
A28: CHRISTIAN RODRIGUEZ | B28: AUTISTA | C28: ACTIVO | D28: PERU | E28: 45703 | F28: Hoja 1_Images/G026.IMAGEN.164914.png | G28: Hoja 1_Files_/G026.PASSAPORTO.140409.pdf | H28: 46203 | J28: 36892 | K28: Hoja 1_Files_/G026.PERMESSO DI SOGGIORNO.140409.pdf | L28: 47633 | M28: Hoja 1_Files_/CHRISTIAN RODRIGUEZ.PATENTE.110931.pdf | N28: 49014 | O28: Hoja 1_Files_/G026.TRADUZIONE PATENTE.140412.pdf | P28: 46155 | Q28: Hoja 1_Files_/G026.C. FISCALE.140409.pdf | R28: 47633 | S28: Hoja 1_Files_/CHRISTIAN RODRIGUEZ.CONTRATO.194939.pdf | U28: 3514929817 | V28: Christianrodriguezmarcos@gmail.com | W28: Via Eugenio Curiel, 24, 20094 Corsico MI, Italia | X28: DHL | Y28: gamonaltrasporti.spedizione@gmail.com | Z28: G026 | AD28: Hoja 1_Files_/G026.RESPONSIVA.074917.pdf
A29: ORLANDO SICCHA | B29: AUTISTA | C29: ACTIVO | D29: PERÚ | E29: 28844 | F29: Hoja 1_Images/G027.IMAGEN.164110.png | I29: Hoja 1_Files_/ORLANDO SICCHA.CARTA DI IDENTITA.172738.pdf | M29: Hoja 1_Files_/ORLANDO SICCHA.PATENTE.172738.pdf | Q29: Hoja 1_Files_/ORLANDO SICCHA.C. FISCALE.172740.pdf | S29: Hoja 1_Files_/ORLANDO SICCHA.CONTRATO.173043.pdf | U29: 3445124845 | V29: orlandosiccha50@gmail.com | X29: UNIVEX | Y29: marvin28abril@gmail.com | Z29: G027
A30: JEAN ALVARADO | B30: AUTISTA | C30: ACTIVO | D30: PERÚ | E30: 33449 | F30: Hoja 1_Images/G028.IMAGEN.164321.png | I30: Hoja 1_Files_/JEAN ALVARADO.CARTA DI IDENTITA.173003.pdf | J30: 48425 | M30: Hoja 1_Files_/JEAN ALVARADO.PATENTE.173003.pdf | N30: 49520 | Q30: Hoja 1_Files_/G028.C. FISCALE.132350.pdf | R30: 48058 | S30: Hoja 1_Files_/G028.CONTRATO.140549.pdf | U30: +39 342 148 1557 | V30: Jeanpier1108@gmail.com | W30: Via Lorenzo Perosi, 1/5 26010 Vaiano Cremasco CR, Italia | X30: DHL | Y30: gamonaltrasporti.spedizione@gmail.com | Z30: G028 | AD30: Hoja 1_Files_/G028.RESPONSIVA.075241.pdf
A31: GAMONAL TRASPORTI | B31: EMPRESA | C31: ACTIVO | D31: PERUITALIANO | E31: 45178 | F31: Hoja 1_Images/451ba90f.IMAGEN.230508.png | V31: info@gamonaltrasporti.com | Z31: 451ba90f
A32: JHON JULIAN | B32: AUTISTA | C32: ACTIVO | D32: PERU | E32: 35416 | F32: Hoja 1_Images/G029.IMAGEN.164134.png | I32: Hoja 1_Files_/G029.CARTA DI IDENTITA.204016.pdf | M32: Hoja 1_Files_/G029.PATENTE.060124.pdf | Q32: Hoja 1_Files_/G029.C. FISCALE.211542.pdf | S32: Hoja 1_Files_/G029.CONTRATO.084557.pdf | U32: 393508243731 | V32: juliandiazjohncristian@gmail.com | X32: UNIVEX | Y32: marvin28abril@gmail.com | Z32: G029
A33: MARINO ORTEGA | B33: AUTISTA | C33: INACTIVO | D33: PERÚ | E33: 24185 | F33: Hoja 1_Images/G030.IMAGEN.230820.png | I33: Hoja 1_Files_/G030.CARTA DI IDENTITA.164133.pdf | M33: Hoja 1_Files_/G030.PATENTE.164133.pdf | X33: INACTIVO | Z33: G030
A34: FELIPE BUSTAMANTE | B34: AUTISTA | C34: ACTIVO | D34: PERÚ | E34: 34963 | F34: Hoja 1_Images/G031.IMAGEN.193358.png | I34: Hoja 1_Files_/G031.CARTA DI IDENTITA.170429.pdf | M34: Hoja 1_Files_/G031.PATENTE.170429.pdf | Q34: Hoja 1_Files_/G031.C. FISCALE.062345.59.pdf | S34: Hoja 1_Files_/G031.CONTRATO.084538.pdf | U34: 3313303702 | V34: Luisfelipe_13_ba@hotmail.com | X34: UNIVEX | Y34: marvin28abril@gmail.com | Z34: G031
A35: ADRIAN ROJAS | B35: AUTISTA | C35: ACTIVO | D35: PERÚ | E35: 36970 | F35: Hoja 1_Images/G032.IMAGEN.173415.png | I35: Hoja 1_Files_/G032.CARTA DI IDENTITA.170759.pdf | M35: Hoja 1_Files_/G032.PATENTE.170759.pdf | Q35: Hoja 1_Files_/G032.C. FISCALE.213230.pdf | S35: Hoja 1_Files_/G032.CONTRATO.083853.pdf | U35: 3508197345 | V35: Rojasuyenoadrianricardo@gmail.con | X35: UNIVEX | Y35: marvin28abril@gmail.com | Z35: G032
A36: JONATHAN CECLEN | B36: AUTISTA | C36: ACTIVO | D36: PERU | E36: 35322 | F36: Hoja 1_Images/G033.IMAGEN.164900.png | I36: Hoja 1_Files_/G033.CARTA DI IDENTITA.133801.pdf | J36: 49201 | K36: Hoja 1_Files_/G033.PERMESSO DI SOGGIORNO.133801.pdf | L36: 46417 | M36: Hoja 1_Files_/G033.PATENTE.133801.pdf | N36: 46665 | O36: Hoja 1_Files_/G033.TRADUZIONE PATENTE.133805.pdf | P36: 46062 | U36: 351 390 9109 | V36: ceclenjonathan@gmail.com | W36: Via Giacomo Matteotti 5 / Cavenago | X36: DHL | Y36: gamonaltrasporti.spedizione@gmail.com | Z36: G033
A37: ANGELO VILLAREAL | B37: AUTISTA | C37: ACTIVO | D37: Italia | E37: 39018 | F37: Hoja 1_Images/G034.IMAGEN.164846.png | I37: Hoja 1_Files_/G034.CARTA DI IDENTITA.143810.pdf | J37: 49245 | M37: Hoja 1_Files_/a52f739b.PATENTE.185029.pdf | N37: 49381 | O37: Hoja 1_Files_/G034.TRADUZIONE PATENTE.143810.pdf | P37: 46164 | Q37: Hoja 1_Files_/G034.C. FISCALE.143810.pdf | R37: 47664 | U37: 3929916431 | V37: villarrealrenzo2006@gmail.com | W37: Via Perosi 1/5 | X37: DHL | Y37: gamonaltrasporti.spedizione@gmail.com | Z37: G034 | AD37: Hoja 1_Files_/G034.RESPONSIVA.080211.pdf
A38: JEAN ARTEAGA | B38: AUTISTA | C38: ACTIVO | D38: PERU | E38: 45859 | F38: Hoja 1_Images/G035.IMAGEN.164056.png | I38: Hoja 1_Files_/G035.CARTA DI IDENTITA.171251.pdf | M38: Hoja 1_Files_/G035.PATENTE.171251.pdf | S38: Hoja 1_Files_/G035.CONTRATO.084617.pdf | U38: +39 351 435 0017 | V38: chilpa61@gmail.com | W38: Via S. Gregorio, 17, 20862 Arcore MB, Italia | X38: UNIVEX | Y38: marvin28abril@gmail.com | Z38: G035
A39: MAURO AGOSTINELLLI | B39: AUTISTA | C39: ACTIVO | D39: PERÚ | E39: 37665 | F39: Hoja 1_Images/G036.IMAGEN.025714.png | G39: Hoja 1_Files_/G036.PASSAPORTO.162257.pdf | H39: 49514 | M39: Hoja 1_Files_/G036.PATENTE.025714.pdf | N39: 49438 | U39: ‪352 030 8537‬ | V39: maufabagosgam@gmail.com | X39: UNIVEX | Y39: marvin28abril@gmail.com | Z39: G036
A40: DENNIS INGLES | B40: AUTISTA | C40: INACTIVO | D40: EL SALVADOR | E40: 33168 | F40: Hoja 1_Images/G037.IMAGEN.183932.png | I40: Hoja 1_Files_/G037.CARTA DI IDENTITA.183932.pdf | M40: Hoja 1_Files_/G037.PATENTE.183932.pdf | S40: Hoja 1_Files_/G037.CONTRATO.084024.pdf | U40: 351 839 7343 | V40: Inglesdennis8@gmail.com | W40: Via Aldo Villa, 16, 20091 Bresso MI, Italia | X40: INACTIVO | Y40: marvin28abril@gmail.com | Z40: G037
A41: DIANA SEGUIL | B41: AUTISTA | C41: ACTIVO | D41: PERÚ | E41: 35213 | F41: Hoja 1_Images/G038.IMAGEN.172927.png | M41: Hoja 1_Files_/G038.PATENTE.172927.pdf | N41: 46901 | U41: +39 345 126 2989 | V41: dianaseguil7@gmail.com | X41: DHL | Y41: gamonaltrasporti.spedizione@gmail.com | Z41: G038
A42: JAVIER DIAZ | B42: AUTISTA | C42: ACTIVO | D42: JAVIER DIAZ | E42: 31048 | F42: Hoja 1_Images/G039.IMAGEN.172912.png | G42: Hoja 1_Files_/G039.PASSAPORTO.172912.pdf | H42: 49603 | M42: Hoja 1_Files_/G039.PATENTE.172912.pdf | N42: 46819 | U42: ‪+39 350 887 9495‬ | V42: jdiazcastro37@gmail.com | X42: DHL | Y42: gamonaltrasporti.spedizione@gmail.com | Z42: G039
A43: ANGEL PAEZ | B43: AUTISTA | C43: ACTIVO | D43: PERU | E43: 30309 | F43: Hoja 1_Images/G040.IMAGEN.162937.png | G43: Hoja 1_Files_/G040.PASSAPORTO.225809.pdf | H43: 49441 | O43: Hoja 1_Files_/G040.TRADUZIONE PATENTE.225809.pdf | P43: 46140 | U43: ‪+393928103478‬ | V43: paezponce12@gmail.com | X43: UNIVEX | Y43: marvin28abril@gmail.com | Z43: G040
A44: JAIRO RIVAS | B44: AUTISTA | C44: ACTIVO | D44: ECUADOR | E44: 31962 | F44: Hoja 1_Images/G041.IMAGEN.162955.png | G44: Hoja 1_Files_/G041.PASSAPORTO.232419.pdf | H44: 49428 | I44: Hoja 1_Files_/G041.CARTA DI IDENTITA.232419.pdf | J44: 49129 | M44: Hoja 1_Files_/G041.PATENTE.232422.pdf | N44: 46117 | U44: ‪+39 351 468 0713‬ | V44: josejairorivas.288@gmail.com | X44: UNIVEX | Y44: marvin28abril@gmail.com | Z44: G041
A45: JOHANN ALIAGA | B45: AUTISTA | C45: ACTIVO | D45: PERU | E45: 33310 | F45: Hoja 1_Images/G042.IMAGEN.163413.png | I45: Hoja 1_Files_/G042.CARTA DI IDENTITA.163413.pdf | J45: 46043 | M45: Hoja 1_Files_/G042.PATENTE.163413.pdf | N45: 49334 | Q45: Hoja 1_Files_/G042.C. FISCALE.163417.pdf | R45: 46240 | U45: 3319926779 | V45: aliaga1303@gmail.com | X45: DHL | Y45: gamonaltrasporti.spedizione@gmail.com | Z45: G042
A46: FABRIZIO ANCULLE | B46: AUTISTA | C46: ACTIVO | D46: PERÚ | E46: 37803 | F46: Hoja 1_Images/G043.IMAGEN.155308.png | I46: Hoja 1_Files_/G043.CARTA DI IDENTITA.155308.pdf | J46: 46367 | M46: Hoja 1_Files_/G043.PATENTE.155308.pdf | N46: 49039 | O46: Hoja 1_Files_/G043.TRADUZIONE PATENTE.155311.pdf | Q46: Hoja 1_Files_/G043.C. FISCALE.155311.pdf | R46: 46387 | U46: ‪+39 350 121 0060‬ | X46: UNIVEX | Y46: marvin28abril@gmail.com | Z46: G043

Sheet Hoja 2
A2: TARGA | B2: MODELO | C2: IMAGEN | D2: LIBRETO | E2: ASEGURAZIONE | F2: COIBENTAZIONE | G2: AÑO | H2: TIPO | I2: ESTADO | J2: ASEGURAZIONE | K2: R.TECNICA | L2: DEROGHE | M2: ID_FURGON
A3: ER643VY | B3: FIAT DOBLO | C3: Hoja 2_Images/F001.IMAGEN.195729.png | D3: Hoja 2_Files_/ER643VY.LIBRETO.023611.pdf | E3: Hoja 2_Files_/ER643VY.ASEGURAZIONE.145308.pdf | G3: 2012 | H3: DHL | I3: DISPONIBLE | J3: 46113 | K3: 46112 | L3: 46053 | M3: F001
A4: EG403NT | B4: FORD TRANSIT | C4: Hoja 2_Images/F002.IMAGEN.193507.png | D4: Hoja 2_Files_/EG403NT.LIBRETO.025232.pdf | E4: Hoja 2_Files_/EG403NT.ASEGURAZIONE.161716.pdf | G4: 2012 | H4: DHL | I4: DISPONIBLE | J4: 46099 | K4: 45930 | L4: 46295 | M4: F002
A5: FY592SE | B5: RENAULT TRAFFIC | C5: Hoja 2_Images/F004.IMAGEN.195807.png | D5: Hoja 2_Files_/FY592SE.LIBRETO.030033.pdf | E5: Hoja 2_Files_/F004.ASEGURAZIONE.124201.pdf | F5: Hoja 2_Files_/FY592SE.COIBENTAZIONE.030035.pdf | G5: 2016 | H5: FARMACIA | I5: DISPONIBLE | J5: 46076 | K5: 46752 | L5: 46022 | M5: F004
A6: FM153VE | B6: FORD TRANSIT | C6: Hoja 2_Images/F005.IMAGEN.195820.png | D6: Hoja 2_Files_/FM153VE.LIBRETO.032648.pdf | E6: Hoja 2_Files_/FM153VE.ASEGURAZIONE.032648.pdf | F6: Hoja 2_Files_/FM153VE.COIBENTAZIONE.032650.pdf | G6: 2016 | H6: FARMACIA | I6: DISPONIBLE | J6: 46038 | K6: 46022 | L6: 46295 | M6: F005
A7: EM504JT | B7: RENAULT TRAFFIC | C7: Hoja 2_Images/F006.IMAGEN.195827.png | D7: Hoja 2_Files_/EM504JT.LIBRETO.033343. Libreto EM504JT.pdf | E7: Hoja 2_Files_/F006.ASEGURAZIONE.132335.pdf | F7: Hoja 2_Files_/EM504JT.COIBENTAZIONE.033345. Coibentazione EM504JT.pdf | G7: 2012 | H7: FARMACIA | I7: DISPONIBLE | J7: 46129 | K7: 46446 | M7: F006
A8: FY032BD | B8: RENAULT TRAFFIC | C8: Hoja 2_Images/F007.IMAGEN.195848.png | D8: Hoja 2_Files_/FY032BD.LIBRETO.033605. Libreto FY302BD.pdf | E8: Hoja 2_Files_/F007.ASEGURAZIONE.132928.pdf | F8: Hoja 2_Files_/FY032BD.COIBENTAZIONE.033607. Coibentazione FY302BD.pdf | G8: 2019 | H8: FARMACIA | I8: DISPONIBLE | J8: 46153 | K8: 46629 | L8: 46295 | M8: F007
A9: GE027AM | B9: RENAULT TRAFFIC | C9: Hoja 2_Images/F008.IMAGEN.195857.png | D9: Hoja 2_Files_/GE027AM.LIBRETO.033744. Libreto GE027AM.pdf | E9: Hoja 2_Files_/F008.ASEGURAZIONE.133629.pdf | F9: Hoja 2_Files_/GE027AM.COIBENTAZIONE.033746. Coibentazione GE027AM.pdf | G9: 2021 | H9: FARMACIA | I9: DISPONIBLE | J9: 46157 | K9: 46477 | M9: F008
A10: FN505ZH | B10: MERCEDES VITO | C10: Hoja 2_Images/F009.IMAGEN.195912.png | D10: Hoja 2_Files_/FN505ZH.LIBRETO.034022. Libreto FN505ZH.pdf | E10: Hoja 2_Files_/F009.ASEGURAZIONE.133359.pdf | F10: Hoja 2_Files_/FN505ZH.COIBENTAZIONE.034024. Coibentazione FN505ZH.pdf | G10: 2021 | H10: FARMACIA | I10: DISPONIBLE | J10: 46154 | K10: 46173 | L10: 46295 | M10: F009
A11: EX030XG | B11: Audi A3 | C11: Hoja 2_Images/F010.IMAGEN.193255.png | D11: Hoja 2_Files_/EX030XG.LIBRETO.170552.pdf | E11: Hoja 2_Files_/F010.ASEGURAZIONE.103420.pdf | G11: 2014 | H11: DHL | I11: DISPONIBLE | J11: 46021 | K11: 46446 | M11: F010
A12: GT894FF | B12: Ford Puma | C12: Hoja 2_Images/F011.IMAGEN.193456.png | D12: Hoja 2_Files_/GT894FF.LIBRETO.153351.pdf | E12: Hoja 2_Files_/F011.ASEGURAZIONE.100005.pdf | G12: 2024 | H12: DHL | I12: DISPONIBLE | J12: 45952 | K12: 46843 | M12: F011
A13: DZ923BS | B13: Hyundai Santa Fe | C13: Hoja 2_Images/F012.IMAGEN.193442.png | D13: Hoja 2_Files_/DZ923BS.LIBRETO.223150.pdf | E13: Hoja 2_Files_/F012.ASEGURAZIONE.165350.pdf | G13: 2009 | H13: DHL | I13: DISPONIBLE | J13: 46046 | K13: 46081 | M13: F012
A14: CV627GV | B14: Mercedes Benz | C14: Hoja 2_Images/F013.IMAGEN.194425.png | D14: Hoja 2_Files_/CV627GV.LIBRETO.222721.pdf | E14: Hoja 2_Files_/CV627GV.ASEGURAZIONE.050430.pdf | G14: 2003 | H14: DHL | I14: DISPONIBLE | J14: 46018 | K14: 46446 | M14: F013
A15: GB502TP | B15: Fiat Panda | C15: Hoja 2_Images/F014.IMAGEN.194447.png | D15: Hoja 2_Files_/GB502TP.LIBRETO.153118.pdf | E15: Hoja 2_Files_/F014.ASEGURAZIONE.105412.pdf | G15: 2021 | H15: DHL | I15: DISPONIBLE | J15: 46021 | K15: 46234 | M15: F014
A16: ET420XR | B16: Alfa Romeo | C16: Hoja 2_Images/ET420XR.IMAGEN.193634.jpg | D16: Hoja 2_Files_/ET420XR.LIBRETO.224609.pdf | E16: Hoja 2_Files_/ET420XR.ASEGURAZIONE.205224.pdf | G16: 2014 | H16: VENDIDO | I16: NO DISPONIBLE | J16: 45853 | K16: 45868 | M16: F015
A17: FY593SE | B17: RENAULT TRAFFIC | C17: Hoja 2_Images/F016.IMAGEN.195920.png | D17: Hoja 2_Files_/FY953SE.LIBRETO.170323.pdf | E17: Hoja 2_Files_/F016.ASEGURAZIONE.160842.pdf | F17: Hoja 2_Files_/FY593SE.COIBENTAZIONE.092433.pdf | G17: 2018 | H17: FARMACIA | I17: DISPONIBLE | J17: 46050 | K17: 46022 | M17: F016
A18: GD079DK | B18: RENAULT TRAFFIC | C18: Hoja 2_Images/F017.IMAGEN.195931.png | D18: Hoja 2_Files_/GD079DK.LIBRETO.135149.pdf | E18: Hoja 2_Files_/F017.ASEGURAZIONE.171037.pdf | F18: Hoja 2_Files_/GD079DK.COIBENTAZIONE.173118.pdf | G18: 2020 | H18: FARMACIA | I18: DISPONIBLE | J18: 46060 | K18: 46387 | M18: F017
A19: GP390DZ | B19: FIAT DUCATO | C19: Hoja 2_Images/F018.IMAGEN.195944.png | D19: Hoja 2_Files_/GP390DZ.LIBRETO.052243.pdf | E19: Hoja 2_Files_/F018.ASEGURAZIONE.105535.pdf | G19: 2023 | H19: FARMACIA | I19: DISPONIBLE | J19: 45988 | M19: F018
A20: GP392DZ | B20: FIAT DUCATO | C20: Hoja 2_Images/F019.IMAGEN.195953.png | D20: Hoja 2_Files_/GP392DZ.LIBRETO.052322.pdf | E20: Hoja 2_Files_/F019.ASEGURAZIONE.105801.pdf | G20: 2023 | H20: FARMACIA | I20: DISPONIBLE | J20: 45988 | M20: F019
A21: GM089XH | B21: FIAT DUCATO | C21: Hoja 2_Images/F020.IMAGEN.200007.png | D21: Hoja 2_Files_/GM089XH.LIBRETO.052528.pdf | E21: Hoja 2_Files_/F020.ASEGURAZIONE.110014.pdf | G21: 2023 | H21: FARMACIA | I21: DISPONIBLE | J21: 45988 | L21: 46053 | M21: F020
A22: CT413YE | B22: Polo | C22: Hoja 2_Images/F021.IMAGEN.194501.png | D22: Hoja 2_Files_/CT413YE.LIBRETO.152918.pdf | E22: Hoja 2_Files_/CT413YE.ASEGURAZIONE.144851.pdf | G22: 2005 | H22: DHL | I22: DISPONIBLE | J22: 46108 | K22: 46507 | M22: F021
A23: EZ009PN | B23: KANGOO | C23: Hoja 2_Images/F022.IMAGEN.194517.png | D23: Hoja 2_Files_/EZ009PN.LIBRETO.120555.pdf | E23: Hoja 2_Files_/EZ009PN.ASEGURAZIONE.124003.pdf | G23: 2015 | H23: DHL | I23: DISPONIBLE | J23: 46106 | K23: 46599 | M23: F022
A24: GJ980KT | B24: LAMBERET BOXER | C24: Hoja 2_Images/F023.IMAGEN.200030.png | D24: Hoja 2_Files_/GJ980KT.LIBRETO.164706.pdf | G24: 2022 | H24: FARMACIA | I24: NO DISPONIBLE | M24: F023
A25: EL49520 | B25: YAMAHA MT-125 | C25: Hoja 2_Images/F024.IMAGEN.194527.png | D25: Hoja 2_Files_/EL49520.LIBRETO.162527.pdf | E25: Hoja 2_Files_/EL49520.ASEGURAZIONE.163944.pdf | G25: 2018 | H25: DHL | I25: DISPONIBLE | J25: 46107 | K25: 46295 | M25: F024
A26: FM342HY | B26: FORD TRANSIT | C26: Hoja 2_Images/F025.IMAGEN.194542.png | D26: Hoja 2_Files_/FM342HY.LIBRETO.124008.pdf | E26: Hoja 2_Files_/FM342HY.ASEGURAZIONE.124008.pdf | G26: 2017 | H26: DHL | I26: DISPONIBLE | J26: 46125 | K26: 46721 | L26: 46295 | M26: F025
A27: ES638NF | B27: FIAT FIORINO | C27: Hoja 2_Images/F026.IMAGEN.194603.png | D27: Hoja 2_Files_/ES638NF.LIBRETO.154251.pdf | E27: Hoja 2_Files_/ES638NF.ASEGURAZIONE.154251.PDF | G27: 2014 | H27: DHL | I27: DISPONIBLE | J27: 46140 | K27: 46053 | M27: F026
A28: GZ992SA | B28: Peugeot | C28: Hoja 2_Images/F027.IMAGEN.181435.png | D28: Hoja 2_Images/F027.LIBRETO.111309.jpg | E28: Hoja 2_Files_/F027.ASEGURAZIONE.110324. GZ992SA.pdf | G28: 2025 | H28: FARMACIA | I28: DISPONIBLE | J28: 46218 | K28: 45875 | M28: F027
A29: FG133WJ | B29: FIAT FIORINO | C29: Hoja 2_Images/F028.IMAGEN.162709.png | D29: Hoja 2_Images/F028.LIBRETO.162709.jpg | E29: Hoja 2_Files_/F028.ASEGURAZIONE.162709.PDF | G29: 2016 | H29: DHL | I29: DISPONIBLE | J29: 46060 | M29: F028
A30: GJ919FZ | B30: CASONATO | C30: Hoja 2_Images/F029.IMAGEN.065135.png | H30: DHL | I30: NO DISPONIBLE | M30: F029
A31: ES270BA | B31: RENAULT TRAFFIC | C31: Hoja 2_Images/F003.IMAGEN.183135.png | D31: Hoja 2_Files_/F003.LIBRETO.134448.52.pdf | G31: 2019 | H31: FARMACIA | I31: DISPONIBLE | J31: 45931 | K31: 46659 | M31: F003
A32: DH950ZM | B32: NOLEGGIO UNIVEX | C32: Hoja 2_Images/999999.IMAGEN.194119.png | H32: FARMACIA | I32: DISPONIBLE | M32: F099
A33: GZ719WV | B33: Vehículo Piazza | C33: Hoja 2_Images/12345.IMAGEN.000123.png | H33: DHL | I33: DISPONIBLE | M33: F097
A34: NOLEGGIO/OTRO | B34: NOLEGGIO/OTRO | C34: Hoja 2_Images/G100.IMAGEN.195101.png | H34: FARMACIA | I34: DISPONIBLE | M34: G100
A35: FG346WJ | B35: FIAT DUCATO | C35: Hoja 2_Images/F030.IMAGEN.163854.png | H35: DHL | I35: DISPONIBLE | J35: 46186 | M35: F030
A36: GS042KA | B36: NOLEGGIO UNIVEX | C36: Hoja 2_Images/F098.IMAGEN.160059.jpg | H36: FARMACIA | I36: DISPONIBLE | M36: F098

Sheet TABLA IDS
A1: Correo | B1: ID TRABAJADOR | C1: Nombre
A2: autista.gamonaltrasporti@gmail.com | B2: G003 | C2: YAN GAMONAL
A3: elizangelasantillan@gmail.com | B3: G023 | C3: ELIZANGELA CHUMBE
A4: Christianrodriguezmarcos@gmail.com | B4: G026 | C4: CHRISTIAN RODRIGUEZ
A5: ceclenjonathan@gmail.com | B5: G033 | C5: JONATHAN CECLEN
A6: Jeanpier1108@gmail.com | B6: G028 | C6: JEAN ALVARADO
A7: jurgen2000pv@gmail.com | B7: G017 | C7: JURGEN PALIZA
A8: Juancarloslazarolozano4@gmail.com | B8: G025 | C8: JUAN LAZARO
A9: 14jatg07@gmail.com | B9: G014 | C9: ALONSO TAMARA
A10: villarrealrenzo2006@gmail.com | B10: G034 | C10: ANGELO VILLAREAL
A11: quispehinostrozaromario1995@gmail.com | B11: G011 | C11: ROMARIO QUISPE
A12: marvin28abril@gmail.com | B12: G008 | C12: MARVIN CASTILLO
... A31: aliaga1303@gmail.com | B31: G042 | C31: JOHANN ALIAGA

Sheet GIROS FARMACIA
A1: NOMBRE | B1: ID TRABAJADOR | C1: MATTINA | D1: INTERMEDIO | E1: POMERIGGIO
A2: ROMARIO | B2: G011 | C2: 101 - SETTIMO MILANESE | E2: 301 - PARABIAGO
A3: CESAR | B3: G007 | C3: 102 - ARESE | E3: 302 - MAGENTA
A4: ADRIAN | B4: G032 | C4: 103 - GUISSANO | E4: 363 - SEREGNO
A5: JUAN | B5: G016 | C5: 114 - MALPIGHI | D5: 210 - MILANO | E5: 314 - MILANO
A6: ANTONIO | B6: G021 | C6: 115 - NOVA MILANESE | E6: 315 - LIMBIATE
A7: FELIPE | B7: G031 | C7: 117 - SESTO | E7: 317 - SESTO
A8: DIEGO | B8: G020 | C8: 119 - VIMERCATE | D8: 228 - MOZZATE | E8: 319 - COMO
A9: JAIRO | B9: G041 | C9: 120 - BRUGHERIO | D9: NAVETTA LALLIO | E9: 311 - MILANO
A10: JULIO | B10: G024 | C10: 123 - MERATE | D10: 211 - SEREGNO | E10: 323 - VIMERCATE
A11: ANGEL | B11: G040 | C11: 128 - MOZZATE | E11: 328 - MOZZATE
A12: JEAN PIER | B12: G035 | C12: 162 - LECCO | D12: 201 - BELLUSCO | E12: 320 - BRUGHERIO
A13: DENNIS | B13: G037 | C13: 198 - MILANO BOOTS | E13: 398- BOOTS
A14: JHON | B14: G029 | C14: 199 - DUOMO | E14: 399 - DUOMO
A15: ORLANDO | B15: G027 | C15: 570 - BERGAMO | E15: 362 - BLUESERVICE

Sheet MECANICA
A2: TARGA | B2: ID_FURGON | C2: MODELO | D2: ESTADO | E2: NOME | F2: DATA | G2: KM | H2: DOCUMENTOS | I2: GPS | J2: CLACSON | K2: RADIO | L2: ANTENA | M2: ACCESORIOS CEL | N2: SPECHIETTO DIESTRO | O2: SPECHIETTO SINIESTRO | P2: TAPPETTINI | Q2: MANIGLIE | R2: ACQUA PER VETRO | S2: TERGICRISTALLI | T2: LUCI DAVANTI | U2: LUCI POSTERIORI | V2: KIT DE SEGURIDAD | W2: ESTADO DE LLANTAS | X2: LLANTA DE REPUESTO | Y2: VETRO ANTERIORE | Z2: FRIGO | AA2: ARIA CONDIZIONATA | AB2: FOTO 1 | AC2: FOTO 2 | AD2: FOTO 3 | AE2: FOTO 4 | AF2: FIRMA | AG2: COMENTARIO | AH2: TIPO | AI2: IMAGEN
A3: ER643VY | B3: F001 | C3: FIAT DOBLO | D3: OPTIMO | E3: ORLANDO SICCHA | F3: 45986 | G3: 481633 | H3: SI | I3: NO | J3: NO | K3: SI | L3: NO | M3: SI | N3: SI | O3: SI | P3: SI | Q3: SI | R3: SI | S3: SI | T3: SI | U3: SI | V3: SI | W3: SI | X3: SI | Y3: NO | Z3: SI | AA3: SI | AF3: MECANICA_Images/ER643VY.FIRMA.090658.png | AG3: Por controlar : mangera de agua .siatema electrico de gas | AH3: FURGONE | AI3: Hoja 2_Images/ER643VY.IMAGEN.023611.jpg
A4: EG403NT | B4: F002 | C4: FORD TRANSIT | D4: NO OPTIMO | E4: ROMARIO QUISPE | F4: 45897 | G4: 244216 | H4: SI | I4: NO | J4: SI | K4: NO | L4: NO | M4: NO | N4: SI | O4: SI | P4: SI | Q4: SI | R4: SI | S4: SI | T4: SI | U4: SI | V4: SI | W4: NO | X4: NO | Y4: NO | Z4: SI | AA4: NO | AF4: MECANICA_Images/EG403NT.FIRMA.150225.png | AG4: falta revisar falla electronica no tiene llanta de repuesto por motivo de glp cambio de bolano y marcia | AH4: FURGONE | AI4: Hoja 2_Images/EG403NT.IMAGEN.025232.png
A5: ES270BA | B5: F003 | C5: RENAULT MASTER | D5: OPTIMO | F5: 45813 | AB5: MECANICA_Images/ES270BA.FOTO 1.110158.jpg | AD5: MECANICA_Images/ES270BA.FOTO 3.110157.jpg | AG5: CINTURÓN DE SEGURIDAD | AH5: FURGONE | AI5: Hoja 2_Images/ES270BA.IMAGEN.025613.png
A6: FY592SE | B6: F004 | C6: RENAULT TRAFFIC T27 | D6: CON FALLAS | E6: EDWAR GUERRERO | F6: 45897 | H6: SI | I6: SI | J6: SI | K6: SI | L6: NO | M6: NO | N6: SI | O6: SI | P6: SI | Q6: SI | R6: NO | S6: SI | T6: SI | U6: SI | V6: SI | W6: SEMINUEVAS | X6: SI | Y6: NO | Z6: SI | AA6: SI | AB6: MECANICA_Images/FY592SE.FOTO 1.074245.jpg | AC6: MECANICA_Images/FY592SE.FOTO 2.074245.jpg | AD6: MECANICA_Images/FY592SE.FOTO 3.074244.jpg | AE6: MECANICA_Images/FY592SE.FOTO 4.074247.jpg | AG6: falta alineamiento, persiste spia antiderrape | AH6: FURGONE | AI6: Hoja 2_Images/FY592SE.IMAGEN.030033.png
A7: FM153VE | B7: F005 | C7: FORD TRANSIT | D7: OPTIMO | E7: ALONSO TAMARA | F7: 45817 | H7: SI | I7: SI | J7: SI | K7: SI | M7: SI | N7: SI | O7: SI | P7: SI | Q7: SI | R7: NO | S7: SI | T7: SI | U7: SI | V7: SI | W7: SEMINUEVAS | X7: SI | Z7: SI | AA7: SI | AH7: FURGONE | AI7: Hoja 2_Images/FM153VE.IMAGEN.032648.png
A8: EM504JT | B8: F006 | C8: RENAULT TRAFFIC | D8: CON FALLAS | E8: DIEGO MOLINA | F8: 45897 | H8: SI | I8: SI | J8: SI | K8: SI | M8: SI | N8: SI | O8: SI | P8: SI | Q8: SI | R8: NO | S8: SI | T8: SI | U8: SI | V8: NO | W8: SEMINUEVAS | X8: SI | Y8: NO | Z8: SI | AA8: SI | AB8: MECANICA_Images/EM504JT.FOTO 1.110503.jpg | AG8: ,Revisar dirección, por el techo está filtrando agua | AH8: FURGONE | AI8: Hoja 2_Images/EM504JT.IMAGEN.033343.png
A9: FY032BD | B9: F007 | C9: RENAULT TRAFFIC | D9: NO OPTIMO | E9: JURGEN PALIZA | F9: 45942 | H9: SI | I9: SI | J9: SI | K9: SI | M9: SI | N9: SI | O9: SI | P9: SI | Q9: SI | R9: SI | S9: SI | T9: SI | U9: SI | V9: SI | W9: SEMINUEVAS | X9: SI | Y9: NO | Z9: SI | AA9: SI | AB9: MECANICA_Images/FY032BD.FOTO 1.105924.jpg | AC9: MECANICA_Images/FY032BD.FOTO 2.105924.jpg | AG9: Esta perdiendo liquido radiatore Fallas Per consumo de olio. | AH9: FURGONE | AI9: Hoja 2_Images/FY032BD.IMAGEN.033605.png
A10: GE027AM | B10: F008 | C10: RENAULT TRAFFIC | D10: OPTIMO | E10: ORLANDO SICCHA | F10: 45817 | G10: 270604 | H10: SI | I10: SI | J10: SI | K10: SI | L10: SI | M10: SI | N10: SI | O10: SI | P10: SI | Q10: SI | R10: SI | S10: SI | T10: SI | U10: SI | V10: SI | W10: SI | X10: SI | Y10: SI | Z10: SI | AA10: SI | AF10: MECANICA_Images/GE027AM.FIRMA.082524.png | AG10: Puerta del copiloto no cierra. | AH10: FURGONE | AI10: Hoja 2_Images/GE027AM.IMAGEN.033744.png
A11: FN505ZH | B11: F009 | C11: MERCEDES VITO | D11: OPTIMO | E11: ANTONIO RIVERA | F11: 45897 | H11: SI | I11: SI | J11: SI | K11: NO | M11: SI | N11: SI | O11: SI | P11: SI | Q11: SI | R11: NO | S11: SI | T11: SI | U11: SI | V11: SI | W11: SEMINUEVAS | X11: SI | Y11: NO | Z11: SI | AA11: SI | AH11: FURGONE | AI11: Hoja 2_Images/FN505ZH.IMAGEN.034022.png
A12: EX030XG | B12: F010 | C12: AUDI A3 | D12: OPTIMO | E12: LIBRE | F12: 45756 | G12: 0 | W12: NA | X12: SI | AB12: MECANICA_Images/EX030XG.FOTO 1.215401.jpg | AF12: MECANICA_Images/EX030XG.FIRMA.062556.png | AG12: Prueba | AH12: AUTO | AI12: Hoja 2_Images/EX030XG.IMAGEN.034226.jpg
A13: GT894FF | B13: F011 | C13: FORD PUMA | D13: SIN REVISAR | AH13: AUTO | AI13: Hoja 2_Images/GT894FF.IMAGEN.034303.jpg
A14: DZ923BS | B14: F012 | C14: SANTA FE | D14: OPTIMO | E14: ROMARIO QUISPE | F14: 45757 | H14: SI | I14: NO | J14: SI | K14: SI | L14: SI | M14: SI | N14: SI | O14: SI | P14: SI | Q14: SI | R14: SI | S14: SI | T14: SI | U14: SI | V14: SI | W14: SI | X14: SI | Y14: SI | Z14: NO | AA14: NA | AF14: MECANICA_Images/DZ923BS.FIRMA.085718.png | AG14: carro en optimas condiciones | AH14: AUTO | AI14: Hoja 2_Images/DZ923BS.IMAGEN.034348.jpg
A15: CV627GV | B15: F013 | C15: MERCEDES BENZ | D15: OPTIMO | E15: MARTIN RODRIGUEZ | F15: 45814 | H15: SI | I15: SI | J15: SI | K15: SI | L15: SI | M15: SI | N15: SI | O15: SI | P15: SI | Q15: SI | R15: SI | S15: SI | T15: SI | U15: SI | V15: NO | W15: NO | X15: NA | Y15: NA | Z15: NO | AA15: SI | AF15: MECANICA_Images/CV627GV.FIRMA.080657.png | AG15: Fermo administrativo | AH15: AUTO | AI15: Hoja 2_Images/CV627GV.IMAGEN.193347.jpg
A16: GB502TP | B16: F014 | C16: FIAT PANDA | D16: OPTIMO | E16: EDUARDO SANTA CRUZ | F16: 45755 | G16: 13271 | H16: SI | I16: NO | J16: SI | K16: SI | L16: SI | M16: SI | N16: SI | O16: SI | P16: SI | Q16: SI | R16: SI | S16: SI | T16: SI | U16: SI | V16: SI | W16: NO | X16: SI | Y16: SI | Z16: NO | AA16: SI | AB16: MECANICA_Images/GB502TP.FOTO 1.075545.jpg | AC16: MECANICA_Images/GB502TP.FOTO 2.075546.jpg | AD16: MECANICA_Images/GB502TP.FOTO 3.075546.jpg | AF16: MECANICA_Images/GB502TP.FIRMA.081911.png | AG16: Por revisar la rueda de adelante lado del chofer | AH16: AUTO | AI16: Hoja 2_Images/GB502TP.IMAGEN.193401.jpg
A17: ET420XR | B17: F015 | C17: ALFA ROMEO | D17: NO OPTIMO | E17: LUIS POMA | F17: 45908 | H17: SI | I17: SI | J17: SI | K17: SI | M17: SI | N17: SI | O17: SI | P17: SI | Q17: SI | R17: SI | S17: SI | T17: SI | U17: SI | V17: SI | W17: SEMINUEVAS | X17: SI | Y17: NO | Z17: NO | AA17: NO | AH17: AUTO | AI17: Hoja 2_Images/ET420XR.IMAGEN.193634.jpg
A18: FY593SE | B18: F016 | C18: RENAULT TRAFFIC | D18: OPTIMO | E18: ELIZANGELA CHUMBE | F18: 45908 | H18: SI | I18: SI | J18: SI | M18: SI | N18: SI | O18: SI | P18: SI | Q18: SI | R18: SI | S18: SI | T18: SI | U18: SI | V18: SI | W18: SEMINUEVAS | X18: SI | Y18: NO | Z18: SI | AA18: SI | AH18: FURGONE | AI18: Hoja 2_Images/FY953SE.IMAGEN.170323.jpg
A19: GD079DK | B19: F017 | C19: RENAULT TRAFFIC | D19: CON FALLAS | E19: JEAN ALVARADO | F19: 45817 | H19: SI | I19: SI | K19: SI | M19: SI | N19: SI | O19: SI | P19: SI | Q19: SI | R19: NO | S19: SI | T19: SI | U19: SI | V19: SI | W19: SEMINUEVAS | X19: SI | Y19: NO | Z19: SI | AA19: SI | AB19: MECANICA_Images/GD079DK.FOTO 1.110825.jpg | AG19: Faro derecho roto por JEANPIER | AH19: FURGONE | AI19: Hoja 2_Images/GD079DK.IMAGEN.173116.png
A20: GP390DZ | B20: F018 | C20: FIAT DUCATO | D20: OPTIMO | E20: MARVIN CASTILLO | F20: 45758 | H20: SI | I20: SI | J20: SI | K20: SI | M20: SI | N20: SI | O20: SI | P20: SI | Q20: SI | R20: SI | S20: SI | T20: SI | U20: SI | V20: SI | Y20: SI | Z20: SI | AA20: SI | AH20: NOLEGGIO | AI20: Hoja 2_Images/GP390DZ.IMAGEN.052243.png
A21: GP392DZ | B21: F019 | C21: FIAT DUCATO | D21: OPTIMO | E21: JULIO DIOSES | F21: 45758 | H21: SI | I21: SI | J21: SI | K21: SI | M21: SI | N21: SI | O21: SI | P21: SI | Q21: SI | R21: SI | S21: SI | T21: SI | U21: SI | V21: SI | Y21: NO | Z21: SI | AA21: SI | AH21: NOLEGGIO | AI21: Hoja 2_Images/GP392DZ.IMAGEN.052322.png
A22: GM089XH | B22: F020 | C22: FIAT DUCATO | D22: OPTIMO | E22: JUAN TEJADA | F22: 45897 | H22: SI | I22: SI | J22: NO | K22: SI | M22: SI | N22: SI | O22: SI | P22: SI | Q22: SI | R22: SI | S22: SI | T22: SI | U22: SI | V22: SI | W22: PARA CAMBIO | X22: SI | Y22: NO | Z22: SI | AA22: NO | AG22: Senza aria condizionata | AH22: NOLEGGIO | AI22: Hoja 2_Images/GM089XH.IMAGEN.052528.png
A23: CT413YE | B23: F021 | C23: POLO | D23: OPTIMO | E23: ROMARIO QUISPE | F23: 45756 | G23: 177382 | H23: SI | I23: NO | J23: SI | K23: SI | L23: SI | M23: SI | N23: SI | O23: SI | P23: SI | Q23: SI | R23: SI | S23: SI | T23: SI | U23: SI | V23: SI | W23: NO | X23: SI | Y23: SI | Z23: NO | AA23: SI | AF23: MECANICA_Images/CT413YE.FIRMA.082832.png | AG23: chanca el amolrtiguador | AH23: AUTO | AI23: Hoja 2_Images/CT413YE.IMAGEN.152918.png
A24: EZ009PN | B24: F022 | C24: KANGOO | D24: OPTIMO | E24: JUAN CARLOS | F24: 45755 | G24: 231665 | H24: SI | I24: SI | J24: SI | K24: SI | L24: SI | M24: SI | N24: SI | O24: SI | P24: SI | Q24: SI | R24: SI | S24: SI | T24: SI | U24: SI | V24: NO | W24: NO | X24: SI | Y24: SI | Z24: NO | AA24: NA | AF24: MECANICA_Images/EZ009PN.FIRMA.085220.png | AG24: programardo tallando sabado 10/05 | AH24: FURGONE | AI24: Hoja 2_Images/EZ009PN.IMAGEN.154153.png
A25: GJ919FZ | C25: VOLKSWAGEN | D25: OPTIMO | AG25: Telonato
A26: EL49520 | B26: F024 | C26: YAMAHA MT-125 | D26: OPTIMO | E26: CHRISTIAN RODRIGUEZ | F26: 45910 | H26: SI | I26: NO | J26: SI | K26: NO | L26: NO | M26: NO | N26: SI | O26: SI | P26: NO | Q26: NO | R26: NO | S26: NO | T26: SI | U26: SI | W26: NO | X26: NO | Y26: NO | Z26: NO | AA26: NO | AF26: MECANICA_Images/EL49520.FIRMA.093145.png | AG26: Moto en optimas condiciones | AH26: MOTO | AI26: Hoja 2_Images/EL49520.IMAGEN.170851.png
A27: FM342HY | B27: F025 | C27: Ford transit | D27: OPTIMO | E27: ROMARIO QUISPE | F27: 45910 | G27: 208357 | H27: SI | I27: NO | J27: SI | K27: SI | L27: SI | M27: NO | N27: SI | O27: SI | P27: SI | Q27: SI | R27: SI | S27: SI | T27: SI | U27: SI | V27: NO | W27: SEMINUEVAS | X27: SI | Y27: SI | Z27: NO | AA27: SI | AB27: MECANICA_Images/FM342HY.FOTO 1.072000.jpg | AC27: MECANICA_Images/FM342HY.FOTO 2.072000.jpg | AD27: MECANICA_Images/FM342HY.FOTO 3.072000.jpg | AE27: MECANICA_Images/FM342HY.FOTO 4.072003.jpg | AF27: MECANICA_Images/FM342HY.FIRMA.072002.png | AG27: Falta aserle su mantenimiento y resivar el aire acondicionado | AH27: FURGONE | AI27: MECANICA_Images/FM342HY.IMAGEN.072058.jpg
A28: ES638NF | B28: F026 | C28: Fiad fiorino | D28: OPTIMO | E28: JUAN CARLOS | F28: 45786 | G28: 84546 | H28: SI | I28: SI | J28: SI | K28: SI | L28: SI | M28: SI | N28: SI | O28: SI | P28: SI | Q28: SI | R28: SI | S28: SI | T28: SI | U28: SI | V28: SI | W28: SEMINUEVAS | X28: SI | Y28: NO | Z28: NO | AA28: SI | AB28: MECANICA_Images/ES638NF.FOTO 1.141612.jpg | AC28: MECANICA_Images/ES638NF.FOTO 2.141612.jpg | AD28: MECANICA_Images/ES638NF.FOTO 3.141612.jpg | AF28: MECANICA_Images/ES638NF.FIRMA.141615.png | AG28: Carro óptimo | AH28: FURGONE | AI28: MECANICA_Images/ES638NF.IMAGEN.141615.jpg

Sheet RECORDATORIOS 
A1: ID | B1: TARGA | C1: SCADENZA | D1: TIPO
A2: 66f77cc6 | B2: GT894FF | C2: 45891 | D2: ASEGURACIÓN
A3: 51305a48 | B3: GT894FF | C3: 46843 | D3: REVISION TECNICA
A4: 25050f71 | B4: GE027AM | C4: 45976 | D4: ASEGURACIÓN
A5: c559c7f3 | B5: GB502TP | C5: 46021 | D5: ASEGURACIÓN
A6: 334143ea | B6: GB502TP | C6: 46234 | D6: REVISION TECNICA
A7: 57f4359b | B7: FY593SE | C7: 46050 | D7: ASEGURACIÓN
A8: d390eedd | B8: FY593SE | C8: 45991 | D8: REVISION TECNICA
A9: 445954eb | B9: FY592SE | C9: 46022 | D9: DEROGHE
A10: 09cf3807 | B10: FY592SE | C10: 45892 | D10: ASEGURACIÓN
A11: f1ceecaf | B11: FY592SE | C11: 45991 | D11: REVISION TECNICA
A12: 74d7c9b3 | B12: FY032BD | C12: 46295 | D12: DEROGHE
A13: 5d952fb3 | B13: FY032BD | C13: 45967 | D13: ASEGURACIÓN
... A52: 89d90ad2 | B52: FM342HY | C52: 46295 | D52: DEROGHE

Sheet EDENRED
A1: ID | B1: MES | C1: ÁREA | D1: NOMBRE | E1: S1 | F1: S2 | G1: S3 | H1: S4 | I1: TOTAL | J1: Id_Trabajador | K1: COMENTARIOS
A2: c5788f93 | B2: 2. FEBRERO | C2: FARMACIA | D2: MARVIN CASTILLO | E2: 25 | F2: 25 | G2: 25 | H2: 25 | I2: 100 | J2: G008 | K2: Buen mes
A3: 6fe80557 | B3: 2. FEBRERO | C3: FARMACIA | D3: JUAN TEJADA | E3: 25 | F3: 25 | G3: 25 | H3: 25 | I3: 100 | J3: G016
A4: 5d88aae9 | B4: 2. FEBRERO | C4: FARMACIA | D4: JURGEN PALIZA | E4: 25 | F4: 25 | G4: 25 | H4: 25 | I4: 100 | J4: G017 | K4: Buen mes
A5: 4ebbd750 | B5: 2. FEBRERO | C5: INACTIVO | D5: ADOLFO ROSALES | F5: 0 | G5: 0 | H5: 0 | I5: 0 | J5: G013
A6: 5133fc87 | B6: 2. FEBRERO | C6: FARMACIA | D6: ALONSO TAMARA | E6: 15 | F6: 15 | G6: 15 | H6: 15 | I6: 60 | J6: G014
A7: 74d2a46a | B7: 2. FEBRERO | C7: FARMACIA | D7: EDWAR GUERRERO | E7: 15 | F7: 15 | G7: 15 | H7: 15 | I7: 60 | J7: G015
A8: 39464ec4 | B8: 2. FEBRERO | C8: FARMACIA | D8: CESAR PLUA | E8: 25 | F8: 25 | G8: 25 | H8: 25 | I8: 100 | J8: G007
A9: 4e6ed272 | B9: 2. FEBRERO | C9: INACTIVO | D9: ROMARIO QUISPE | E9: 25 | F9: 25 | G9: 25 | H9: 25 | I9: 100 | J9: G011
A10: d4a6843d | B10: 2. FEBRERO | C10: INACTIVO | D10: DOMINICK LEON | E10: 10 | F10: 10 | G10: 10 | I10: 30 | J10: G009
A11: 9gd8s13 | B11: 3. MARZO | C11: FARMACIA | D11: MARVIN CASTILLO | E11: 25 | F11: 15 | G11: 20 | H11: 20 | I11: 80 | J11: G008
A12: qw98r1532 | B12: 3. MARZO | C12: FARMACIA | D12: JUAN TEJADA | E12: 20 | F12: 20 | G12: 20 | H12: 15 | I12: 75 | J12: G016
A13: vb988 | B13: 3. MARZO | C13: FARMACIA | D13: JURGEN PALIZA | E13: 20 | F13: 20 | G13: 20 | H13: 20 | I13: 80 | J13: G017
A14: ku6yjm1, | B14: 3. MARZO | C14: FARMACIA | D14: ALONSO TAMARA | E14: 20 | F14: 15 | G14: 15 | H14: 20 | I14: 70 | J14: G014
A15: s98db | B15: 3. MARZO | C15: FARMACIA | D15: EDWAR GUERRERO | E15: 20 | F15: 20 | G15: 20 | H15: 15 | I15: 75 | J15: G015
A16: 9iuo8p4 | B16: 3. MARZO | C16: FARMACIA | D16: CESAR PLUA | E16: 25 | F16: 20 | G16: 20 | H16: 25 | I16: 90 | J16: G007
A17: ljk3ñ21 | B17: 3. MARZO | C17: INACTIVO | D17: ROMARIO QUISPE | E17: 20 | F17: 20 | G17: 20 | H17: 20 | I17: 80 | J17: G011
A18: 665b81nm | B18: 3. MARZO | C18: INACTIVO | D18: DOMINICK LEON | E18: 5 | F18: 10 | G18: 10 | H18: 5 | I18: 30 | J18: G009
A19: q9w87r | B19: 3. MARZO | C19: DHL | D19: JUAN CARLOS | E19: 20 | F19: 20 | G19: 20 | H19: 20 | I19: 80 | J19: G025
A20: t8ur879 | B20: 4. ABRIL | C20: FARMACIA | D20: MARVIN CASTILLO | E20: 15 | F20: 20 | G20: 20 | H20: 25 | I20: 80 | J20: G008
A21: qr98 | B21: 4. ABRIL | C21: FARMACIA | D21: JUAN TEJADA | E21: 15 | F21: 15 | G21: 15 | H21: 0 | I21: 45 | J21: G016
A22: m894yumy | B22: 4. ABRIL | C22: FARMACIA | D22: JURGEN PALIZA | E22: 15 | F22: 20 | G22: 20 | H22: 25 | I22: 80 | J22: G017
... A40: q98wj818l | B40: 1. ENERO | C40: INACTIVO | D40: ROMARIO QUISPE | E40: 25 | F40: 25 | G40: 25 | H40: 25 | I40: 100 | J40: G011
A41: 1 | B41: 5. MAYO | C41: FARMACIA | D41: MARVIN CASTILLO | E41: 20 | F41: 25 | G41: 25 | H41: 25 | I41: 95 | J41: G008
A42: 2 | B42: 5. MAYO | C42: FARMACIA | D42: JUAN TEJADA | E42: 20 | F42: 20 | I42: 40 | J42: G016
A43: 3 | B43: 5. MAYO | C43: FARMACIA | D43: JURGEN PALIZA | E43: 25 | F43: 25 | G43: 20 | I43: 70 | J43: G017
A44: 4 | B44: 5. MAYO | C44: DHL | D44: ALONSO TAMARA | E44: 20 | F44: 20 | G44: 15 | H44: 15 | I44: 70 | J44: G014
A45: 5 | B45: 5. MAYO | C45: FARMACIA | D45: EDWAR GUERRERO | E45: 15 | F45: 25 | G45: 20 | I45: 60 | J45: G015
A46: 6 | B46: 5. MAYO | C46: FARMACIA | D46: CESAR PLUA | E46: 20 | F46: 20 | G46: 20 | H46: 20 | I46: 80 | J46: G007
A47: 7 | B47: 5. MAYO | C47: INACTIVO | D47: ROMARIO QUISPE | E47: 10 | F47: 20 | G47: 20 | H47: 10 | I47: 60 | J47: G011
A48: 9 | B48: 5. MAYO | C48: DHL | D48: JUAN CARLOS | E48: 15 | F48: 20 | G48: 20 | H48: 15 | I48: 70 | J48: G025
A49: 10 | B49: 5. MAYO | C49: FARMACIA | D49: ANTONIO RIVERA | E49: 20 | F49: 25 | G49: 25 | H49: 25 | I49: 95 | J49: G021
A50: 11 | B50: 5. MAYO | C50: DHL | D50: CHRISTIAN RODRIGUEZ | E50: 20 | F50: 25 | G50: 20 | H50: 20 | I50: 85 | J50: G026
A51: 12 | B51: 5. MAYO | C51: INACTIVO | D51: EDUARDO SANTA CRUZ | E51: 10 | F51: 15 | G51: 10 | I51: 35 | J51: G022
A52: 13 | B52: 6. JUNIO | C52: FARMACIA | D52: MARVIN CASTILLO | E52: 20 | F52: 20 | G52: 20 | H52: 20 | I52: 80 | J52: G008 | K52: Cabina de furgon sucio
A53: 14 | B53: 6. JUNIO | C53: FARMACIA | D53: JUAN TEJADA | E53: 20 | F53: 20 | G53: 20 | H53: 20 | I53: 80 | J53: G016 | K53: Furgone un poco sucio
A54: 15 | B54: 6. JUNIO | C54: DHL | D54: JURGEN PALIZA | E54: 15 | F54: 15 | G54: 20 | H54: 20 | I54: 70 | J54: G017
A55: 16 | B55: 6. JUNIO | C55: DHL | D55: ALONSO TAMARA | E55: 15 | F55: 20 | G55: 20 | H55: 15 | I55: 70 | J55: G014
A56: 17 | B56: 6. JUNIO | C56: FARMACIA | D56: EDWAR GUERRERO | E56: 15 | F56: 15 | G56: 15 | H56: 20 | I56: 65 | J56: G015 | K56: Furgone sucio
A57: 18 | B57: 6. JUNIO | C57: FARMACIA | D57: CESAR PLUA | E57: 20 | F57: 20 | G57: 20 | H57: 20 | I57: 80 | J57: G007 | K57: No llega al 100% porque mezcla los dpc de las farmacias generando sbaglio
A58: 19 | B58: 6. JUNIO | C58: INACTIVO | D58: ROMARIO QUISPE | E58: 2 | F58: 3 | G58: 3 | H58: 2 | I58: 10 | J58: G011
A59: 20 | B59: 6. JUNIO | C59: DHL | D59: JUAN CARLOS | E59: 15 | F59: 20 | G59: 15 | H59: 20 | I59: 70 | J59: G025
A60: 21 | B60: 6. JUNIO | C60: FARMACIA | D60: ANTONIO RIVERA | E60: 20 | F60: 20 | G60: 20 | H60: 20 | I60: 80 | J60: G021 | K60: Se olvida el envío de los borderò
A61: 22 | B61: 6. JUNIO | C61: DHL | D61: CHRISTIAN RODRIGUEZ | E61: 20 | F61: 25 | G61: 25 | H61: 20 | I61: 90 | J61: G026
A64: 089a00aa | B64: 5. MAYO | C64: FARMACIA | D64: DIEGO MOLINA | E64: 20 | F64: 25 | G64: 20 | H64: 20 | I64: 85 | J64: G020
A65: 6f0b4a4d | B65: 6. JUNIO | C65: FARMACIA | D65: DIEGO MOLINA | E65: 20 | F65: 20 | G65: 20 | H65: 20 | I65: 80 | J65: G020 | K65: En el mes se a olvidado 2 veces voluminoso
A66: 7b067555 | B66: 7. JULIO | C66: FARMACIA | D66: MARVIN CASTILLO | E66: 15 | F66: 20 | G66: 20 | H66: 20 | I66: 75 | J66: G008
A67: 0eca4e16 | B67: 7. JULIO | C67: FARMACIA | D67: JUAN TEJADA | E67: 15 | F67: 10 | G67: 15 | H67: 15 | I67: 55 | J67: G016
A68: 8ad7a3a9 | B68: 7. JULIO | C68: DHL | D68: JURGEN PALIZA | E68: 20 | F68: 15 | G68: 15 | H68: 20 | I68: 70 | J68: G017
A69: 9568ccc0 | B69: 7. JULIO | C69: DHL | D69: ALONSO TAMARA | E69: 20 | F69: 20 | G69: 15 | H69: 15 | I69: 70 | J69: G014
A71: 7a034dbb | B71: 7. JULIO | C71: FARMACIA | D71: CESAR PLUA | E71: 20 | F71: 20 | G71: 20 | H71: 20 | I71: 80 | J71: G007
A72: 2cac51ff | B72: 7. JULIO | C72: INACTIVO | D72: ROMARIO QUISPE | I72: 20 | J72: G011
A73: QO1O12I | B73: 7. JULIO | C73: DHL | D73: JUAN CARLOS | E73: 20 | F73: 15 | G73: 10 | H73: 15 | I73: 60 | J73: G025
A74: AS00C9C | B74: 7. JULIO | C74: FARMACIA | D74: ANTONIO RIVERA | E74: 15 | F74: 15 | G74: 20 | I74: 50 | J74: G021
A75: GH7FFF | B75: 7. JULIO | C75: DHL | D75: CHRISTIAN RODRIGUEZ | E75: 20 | F75: 25 | G75: 25 | H75: 20 | I75: 90 | J75: G026
A76: E2JOP1P1 | B76: 7. JULIO | C76: FARMACIA | D76: DIEGO MOLINA | E76: 20 | F76: 20 | G76: 20 | H76: 10 | I76: 70 | J76: G020
A77: d8f26536 | B77: 5. MAYO | C77: FARMACIA | D77: JULIO DIOSES | I77: 0
A78: 2b75fffe | B78: 6. JUNIO | C78: FARMACIA | D78: JULIO DIOSES | E78: 15 | F78: 10 | G78: 15 | H78: 15 | I78: 55 | J78: G024
A79: a99b3587 | B79: 7. JULIO | C79: FARMACIA | D79: JHON JULIAN | E79: 20 | F79: 20 | G79: 20 | H79: 20 | I79: 80 | J79: G029
A80: d8206164 | B80: 6. JUNIO | C80: FARMACIA | D80: ORLANDO SICCHA | E80: 20 | F80: 20 | G80: 20 | H80: 20 | I80: 80 | J80: G027
A81: 33c6f76b | B81: 7. JULIO | C81: FARMACIA | D81: JEAN ALVARADO | E81: 20 | F81: 20 | G81: 15 | H81: 15 | I81: 70 | J81: G028
A82: 1da4bc65 | B82: 8. AGOSTO | C82: FARMACIA | D82: CESAR PLUA | E82: 20 | F82: 20 | I82: 40 | J82: G007
A83: 0f588f3b | B83: 8. AGOSTO | C83: FARMACIA | D83: DIEGO MOLINA | E83: 15 | F83: 15 | G83: 15 | I83: 45 | J83: G020
A84: dbe046f3 | B84: 8. AGOSTO | C84: FARMACIA | D84: JHON JULIAN | E84: 20 | F84: 20 | I84: 40 | J84: G029
A85: 2a8859e4 | B85: 8. AGOSTO | C85: FARMACIA | D85: JUAN TEJADA | E85: 15 | F85: 15 | G85: 15 | I85: 45 | J85: G016
A86: c5fd3465 | B86: 7. JULIO | C86: FARMACIA | D86: JULIO DIOSES | E86: 15 | F86: 15 | G86: 15 | H86: 20 | I86: 65 | J86: G024
A87: 895cb804 | B87: 8. AGOSTO | C87: FARMACIA | D87: JULIO DIOSES | E87: 15 | F87: 15 | G87: 15 | I87: 45 | J87: G024
A88: cbe0a086 | B88: 8. AGOSTO | C88: FARMACIA | D88: MARVIN CASTILLO | E88: 20 | F88: 20 | G88: 15 | I88: 55 | J88: G008
A89: 24472c19 | B89: 7. JULIO | C89: FARMACIA | D89: ORLANDO SICCHA | E89: 20 | F89: 20 | G89: 15 | H89: 15 | I89: 70 | J89: G027
A90: fcbde091 | B90: 8. AGOSTO | C90: FARMACIA | D90: ORLANDO SICCHA | E90: 20 | F90: 15 | G90: 20 | I90: 55 | J90: G027
A91: 568a2990 | B91: 8. AGOSTO | C91: FARMACIA | D91: ANTONIO RIVERA | F91: 10 | I91: 10 | J91: G021
A92: 343365f7 | B92: 8. AGOSTO | C92: DHL | D92: ALONSO TAMARA | E92: 15 | F92: 15 | G92: 15 | I92: 45 | J92: G014
A93: 2fc0551e | B93: 8. AGOSTO | C93: DHL | D93: CHRISTIAN RODRIGUEZ | E93: 20 | F93: 20 | G93: 20 | I93: 60 | J93: G026
A94: 2a4bf425 | B94: 8. AGOSTO | C94: DHL | D94: JUAN CARLOS | E94: 20 | F94: 15 | G94: 20 | I94: 55 | J94: G025
A95: f894f34b | B95: 8. AGOSTO | C95: DHL | D95: JURGEN PALIZA | E95: 15 | F95: 20 | G95: 20 | I95: 55 | J95: G017
A96: b433e79c | B96: 7. JULIO | C96: DHL | D96: JEAN ALVARADO | E96: 20 | F96: 15 | G96: 15 | H96: 20 | I96: 70 | J96: G028 | K96: primera recarga
A97: b4a950b6 | B97: 8. AGOSTO | C97: DHL | D97: JEAN ALVARADO | E97: 20 | F97: 20 | G97: 20 | H97: 20 | I97: 80 | J97: G028
A98: 7d322b7d | B98: 7. JULIO | C98: DHL | D98: ELIZANGELA CHUMBE | E98: 15 | F98: 15 | G98: 15 | H98: 15 | I98: 60 | J98: G023
A99: 201e84d5 | B99: 8. AGOSTO | C99: DHL | D99: ELIZANGELA CHUMBE | E99: 15 | F99: 15 | G99: 20 | I99: 50 | J99: G023
A113: 100 | B113: 8. AGOSTO | C113: FARMACIA | D113: CESAR PLUA | E113: 20 | F113: 20 | I113: 40 | J113: G007
A114: 101 | B114: 8. AGOSTO | C114: FARMACIA | D114: DIEGO MOLINA | E114: 15 | F114: 15 | G114: 15 | I114: 45 | J114: G020
A115: 102 | B115: 8. AGOSTO | C115: FARMACIA | D115: JHON JULIAN | E115: 20 | F115: 20 | I115: 40 | J115: G029
A116: 103 | B116: 8. AGOSTO | C116: FARMACIA | D116: JUAN TEJADA | E116: 15 | F116: 15 | G116: 15 | I116: 45 | J116: G016
A117: 104 | B117: 8. AGOSTO | C117: FARMACIA | D117: JULIO DIOSES | E117: 15 | F117: 15 | G117: 15 | I117: 45 | J117: G024
A118: 105 | B118: 8. AGOSTO | C118: FARMACIA | D118: MARVIN CASTILLO | E118: 20 | F118: 20 | G118: 15 | I118: 55 | J118: G008
A119: 106 | B119: 8. AGOSTO | C119: FARMACIA | D119: ORLANDO SICCHA | E119: 20 | F119: 15 | G119: 20 | I119: 55 | J119: G027
A120: 107 | B120: 8. AGOSTO | C120: FARMACIA | D120: ANTONIO RIVERA | F120: 10 | I120: 10 | J120: G021
A121: 108 | B121: 8. AGOSTO | C121: DHL | D121: ALONSO TAMARA | E121: 15 | F121: 15 | G121: 15 | I121: 45 | J121: G014
A122: 109 | B122: 8. AGOSTO | C122: DHL | D122: CHRISTIAN RODRIGUEZ | E122: 20 | F122: 20 | G122: 20 | I122: 60 | J122: G026
A123: 110 | B123: 8. AGOSTO | C123: DHL | D123: JUAN CARLOS | E123: 20 | F123: 15 | G123: 20 | I123: 55 | J123: G025
A124: 111 | B124: 8. AGOSTO | C124: DHL | D124: JURGEN PALIZA | E124: 15 | F124: 20 | G124: 20 | I124: 55 | J124: G017
A125: 112 | B125: 8. AGOSTO | C125: DHL | D125: JEAN ALVARADO | E125: 20 | F125: 20 | G125: 20 | H125: 20 | I125: 80 | J125: G028
A126: 113 | B126: 8. AGOSTO | C126: DHL | D126: ELIZANGELA CHUMBE | E126: 15 | F126: 15 | G126: 20 | I126: 50 | J126: G023

Sheet AGENDA
A1: ID | B1: DATA | C1: HORA DE INICIO | D1: HORA FIN | E1: RESPONSABLE | F1: COLOR ASIGNADO | G1: PRIORIDAD | H1: TAREA
A2: deb57a19 | B2: 45728 | C2: 0.375 | D2: 0.45833333 | E2: MARTIN | F2: Green | G2: MEDIA | H2: DESPACHAR CONSEGNAS DHL
A3: 01bd08ee | B3: 45728 | C3: 0.5 | D3: 0.58333333 | E3: NATALIA | F3: Orange | G3: MEDIA | H3: ALMUERZO
A4: 37cf386a | B4: 45728 | C4: 0.375 | D4: 0.45833333 | E4: CARLOS | F4: Blue | G4: ALTA | H4: CURSO
A5: 45729.646 | B5: Red | C5: Commercialista/ bilancio , renuovo de contratos
A6: 8d1f5f56 | B6: 45729 | C6: 0.64583333 | D6: 0.70833333 | E6: EMERSON | F6: Red | G6: ALTA | H6: Commercialista
A7: 3031df7f | B7: 45730 | C7: 0.29166667 | D7: 0.41666667 | E7: NATALIA | F7: Orange | G7: ALTA | H7: QUESTURA / PERMESSO DI SOGGIORNO
A8: 7dde7001 | B8: 45730 | C8: 0.29166667 | D8: 0.375 | E8: EMERSON | F8: Red | G8: ALTA | H8: comisaria peschiera
A9: d1621b6a | B9: 45730 | C9: 0.41666667 | D9: 0.5 | E9: EMERSON | F9: Red | G9: ALTA | H9: buscar informacion denuncia contra rabanal
A10: 9c96a51c | B10: 45730 | C10: 0.58333333 | D10: 0.66666667 | E10: EMERSON | F10: Red | G10: MEDIA | H10: comercialista presencias busta pags Ivam
A11: e6535a90 | B11: 45730 | C11: 0.29166667 | D11: 0.33333333 | E11: MARTIN | F11: Green | G11: ALTA | H11: Policia peschiera
A12: 7f988056 | B12: 45734 | C12: 0.39583333 | D12: 0.45833333 | E12: LUIS | F12: Yellow | G12: ALTA | H12: Cambio de vidrio alfa Romeo —- via verona1/a pioltello
A13: 19587c7a | B13: 45735 | C13: 0.64583333 | D13: 0.70833333 | E13: LUIS | F13: Yellow | G13: ALTA | H13: Appuntamento avocado
A14: e4e2b8a2 | B14: 45736 | C14: 0.4375 | D14: 0.54166667 | E14: LUIS | F14: Yellow | G14: ALTA | H14: Cita médica de mi hija debemos ir solo padres
A15: 42e857d1 | B15: 45733 | C15: 0.375 | D15: 0.45833333 | E15: LUIS | F15: Yellow | G15: MEDIA | H15: Marvin no llega al intermedio
A16: 9c641170 | B16: 45732 | C16: 0.16666667 | D16: 0.35416667 | E16: EMERSON | F16: Red | G16: ALTA | H16: Consegna grosseto
A17: 9944b2bf | B17: 45733 | C17: 0.33333333 | D17: 0.4375 | E17: NATALIA | F17: Orange | G17: ALTA | H17: Permesso di soggiorno
... A36: 8e39ccca | B36: 45748 | C36: 0.375 | D36: 0.41666667 | E36: LUIS | F36: Yellow | G36: ALTA | H36: Devolución de furgon GF269YE
A37: 0a760495 | B37: 45748 | C37: 0.45833333 | D37: 0.47222222 | E37: LUIS | F37: Yellow | H37: Devolución del furgón placa GR273XE.que tuvimos por reeemplazo gm089xh
A38: 205dc5d2 | B38: 45738 | C38: 0.33333333 | D38: 0.35416667 | E38: LUIS | F38: Yellow | G38: ALTA | H38: Cambio de furgon gm089xh por guasto. Nos dieron este furgon GR273XE
A39: 0e96fcad | B39: 45750 | C39: 0.4375 | D39: 0.45833333 | E39: LUIS | F39: Yellow | G39: ALTA | H39: Cambio de vetro fm153ve
A40: bbd1aecd | B40: 45749 | C40: 0.54166667 | D40: 0.66666667 | E40: LUIS | F40: Yellow | G40: ALTA | H40: Permesso per documenti julio
A41: 6b5e0e6b | B41: 45755 | C41: 0.43055556 | D41: 0.47222222 | E41: NATALIA | F41: Orange | H41: MEDICO
A42: da7616d3 | B42: 45764 | C42: 0.41666667 | D42: 0.625 | E42: LUIS | F42: Yellow | G42: ALTA | H42: Cita medico inps
A43: 02f7401d | B43: 45796 | C43: 0 | D43: 1 | E43: LUIS | F43: Yellow | G43: ALTA | H43: Vacaciones juan 19 de mayo al 31 MAYO
A44: 9f527128 | B44: 45759 | C44: 0 | D44: 1 | E44: LUIS | F44: Yellow | G44: ALTA | H44: Permesso documento juan tejada
A45: 14ae9963 | B45: 45888 | C45: 0 | D45: 1 | E45: LUIS | F45: Yellow | G45: ALTA | H45: Vacaciones cesar 19/08 al 29/09
A46: 58ff98c4 | B46: 45755 | C46: 0.041666667 | D46: 0.083333333 | E46: MARTIN | F46: Green | G46: ALTA | H46: apuntamento scuola
A47: 4fb3e395 | B47: 45784 | C47: 0.41666667 | D47: 0.41666667 | F47: Blue | G47: BAJA | H47: Cumpleaños Carlos Gamonal
A48: afac0f4f | B48: 45919 | C48: 0.41666667 | D48: 0.41666667 | F48: Blue | G48: BAJA | H48: Cumpleaños Emerson Gamonal
A49: d3725d8e | B49: 46046 | C49: 0.41666667 | D49: 0.41666667 | F49: Blue | G49: BAJA | H49: Cumpleaños Yan Gamonal
A50: a3c23bf4 | B50: 45988 | C50: 0.41666667 | D50: 0.41666667 | F50: Blue | G50: BAJA | H50: Cumpleaños Natalia Plua
A51: 068d079a | B51: 45903 | C51: 0.41666667 | D51: 0.41666667 | F51: Blue | G51: BAJA | H51: Cumple Luis Poma
A52: 3a211881 | B52: 46010 | C52: 0.41666667 | D52: 0.41666667 | F52: Blue | G52: BAJA | H52: Cumple Martin Rodriguez
A53: 75887788 | B53: 45779 | C53: 0.41666667 | D53: 0.41666667 | F53: Blue | G53: BAJA | H53: Cumple Cesar Plua
A54: ba55a3c2 | B54: 45775 | C54: 0.41666667 | D54: 0.41666667 | F54: Blue | G54: BAJA | H54: Cumple Marvin Castillo
A55: c83cd4ff | B55: 46041 | C55: 0.41666667 | D55: 0.41666667 | F55: Blue | G55: BAJA | H55: Cumple Domini Leon
A56: 993bc943 | B56: 45901 | C56: 0.41666667 | D56: 0.41666667 | F56: Blue | G56: BAJA | H56: Cumple Romario Quispe
A58: ce30e677 | B58: 45852 | C58: 0.41666667 | D58: 0.41666667 | F58: Blue | G58: BAJA | H58: Cumple Alonso Tamara
A59: 0f2fd551 | B59: 45850 | C59: 0.41666667 | D59: 0.41666667 | F59: Blue | G59: BAJA | H59: Cumple Edward Guerrero
... A71: e865c67c | B71: 45868 | C71: 0.41666667 | D71: 0.41666667 | F71: Blue | G71: BAJA | H71: Cumple Jean Alvarado
A72: e2672150 | B72: 45756 | C72: 0 | D72: 0.79166667 | E72: LUIS | F72: Yellow | G72: ALTA | H72: Renovación de permiso antonio
A73: c50a87e5 | B73: 45757 | C73: 0 | D73: 0.41666667 | E73: LUIS | F73: Yellow | G73: ALTA | H73: Permesso renovación jurgen
A74: 7ab6df30 | B74: 45757 | C74: 0.70833333 | D74: 0.27083333 | E74: MARTIN | F74: Green | G74: ALTA | H74: Appuntamento Doctore Shantha
A75: 7ea1b3a0 | B75: 45765 | C75: 0.54166667 | D75: 0.625 | E75: MARTIN | F75: Green | G75: ALTA | H75: appuntamento per Soggiorno
A76: 65341b78 | B76: 45771 | C76: 0.625 | D76: 0.75 | E76: LUIS | F76: Yellow | G76: ALTA | H76: Appuntamento nell’ comune
A77: c3909f5d | B77: 45782 | C77: 0 | D77: 1 | E77: LUIS | F77: Yellow | G77: ALTA | H77: Furgon FM153VE VA PARA REPARACIÓN 2 dias
A78: 240c8849 | B78: 45782 | C78: 0 | D78: 1 | E78: LUIS | F78: Yellow | G78: ALTA | H78: 2 días para reparación del furgón FM153VE
A79: 163b9ae1 | B79: 45782 | C79: 0 | D79: 1 | E79: LUIS | F79: Yellow | H79: FM153VE REPARACIÓN PER 2 giorno
A80: 628360be | B80: 45782 | C80: 0.41666667 | D80: 0.5 | E80: LUIS | F80: Yellow | G80: ALTA | H80: FM153VE PLANCHADO Y PINTADO
A81: e25dc77d | B81: 45769 | C81: 0.5 | E81: LUIS | F81: Yellow | G81: ALTA | H81: Cita ospedale sacco todo el dia
A82: 88085f38 | B82: 45749 | C82: 0.375 | D82: 0.70833333 | E82: LUIS | F82: Yellow | G82: ALTA | H82: Appuntamento palazzo di giustizia
A83: 09d4eb8b | B83: 45777 | C83: 0.375 | D83: 0.41666667 | E83: LUIS | F83: Yellow | G83: ALTA | H83: Appuntamento palazzo di giustizia
A84: 1300d497 | B84: 45779 | C84: 0.375 | D84: 0.45833333 | E84: LUIS | F84: Yellow | G84: ALTA | H84: Appuntamento nell’ tribunale di minori
A85: 5fb9bba0 | B85: 45789 | C85: 0.29166667 | D85: 0.41666667 | E85: LUIS | F85: Yellow | G85: ALTA | H85: Appuntamento Juan tejada questura
A86: acf2df6f | B86: 45777 | C86: 0.375 | D86: 0.41666667 | E86: LUIS | F86: Yellow | G86: ALTA | H86: Permesso para Marvin por compleanno
A87: da9d0453 | B87: 45806 | C87: 0.375 | D87: 0.5 | E87: LUIS | F87: Yellow | G87: ALTA | H87: Appuntamento per soggiorno luis poma
A88: ee5b65ec | B88: 45798 | C88: 0.375 | D88: 0.41666667 | E88: LUIS | F88: Yellow | G88: ALTA | H88: Appuntamento soggiorno di Jhon Julián
A89: 47eb2d28 | B89: 45785 | C89: 0.29166667 | D89: 0.375 | E89: LUIS | F89: Yellow | G89: ALTA | H89: Appuntamento Jurgen soggiorno
A90: 992abe12 | B90: 45787 | C90: 0.375 | D90: 0.41666667 | E90: LUIS | F90: Yellow | G90: ALTA | H90: Appuntamento soggiorno antonio
A91: 8accb2ef | B91: 45776 | C91: 0.375 | D91: 0.41666667 | E91: LUIS | F91: Yellow | G91: ALTA | H91: Cambio di olio furgon fy592se km 369115
A92: e36d2e36 | B92: 45796 | C92: 0.375 | D92: 0.5 | E92: LUIS | F92: Yellow | G92: ALTA | H92: Inizio Vacanza Juan
A93: 6096640e | B93: 45808 | C93: 0.375 | D93: 0.41666667 | E93: LUIS | F93: Yellow | H93: Fin vacanza Juan
A94: e12aebdf | B94: 45793 | C94: 0.375 | D94: 0.41666667 | E94: LUIS | F94: Yellow | G94: ALTA | H94: Permesso julio y Diego commissione
A95: 6669faee | B95: 45803 | C95: 0.375 | D95: 0.41666667 | E95: LUIS | F95: Yellow | G95: ALTA | H95: Luis appuntamento nell comune. Per la scuola
A96: 1a153ce0 | B96: 45803 | C96: 0.41666667 | D96: 0.45833333 | E96: LUIS | F96: Yellow | G96: ALTA | H96: Permesso orlando todo el dia per cita in questura
A97: 4fe69c47 | B97: 45805 | C97: 0.625 | D97: 0.66666667 | E97: LUIS | F97: Yellow | G97: ALTA | H97: Appuntamento cesar medico
A98: 4b8dc403 | B98: 45804 | C98: 0.375 | D98: 0.41666667 | E98: LUIS | F98: Yellow | G98: ALTA | H98: Jurgen permesso per 3 giorni. Per su esposa
A99: f4d05fb3 | B99: 45808 | C99: 0.375 | D99: 0.41666667 | E99: LUIS | F99: Yellow | G99: ALTA | H99: Permesso Jean Pierre solo pomeriggioo
A100: 3a0804bc | B100: 45811 | C100: 0.375 | D100: 0.41666667 | E100: LUIS | F100: Yellow | G100: ALTA | H100: Cambio de vidrio 270 y 592
A101: 507d1286 | B101: 45808 | C101: 0.375 | D101: 0.41666667 | E101: LUIS | F101: Yellow | G101: ALTA | H101: Permeso solo mattina a orlando
A102: b3ce6d48 | B102: 45811 | C102: 0.375 | D102: 0.41666667 | E102: LUIS | F102: Yellow | G102: ALTA | H102: Permiso diego solo en la mattina
A103: 23d578b5 | B103: 45814 | C103: 0.375 | D103: 0.41666667 | E103: LUIS | F103: Yellow | G103: ALTA | H103: Permiso orlando solo la mattina
A104: ffc5d1ee | B104: 45812 | C104: 0.54166667 | D104: 0.66666667 | E104: LUIS | F104: Yellow | G104: ALTA | H104: Marvin pomeriggio appuntamento
A105: 5bcdf772 | B105: 45814 | C105: 0.375 | D105: 0.45833333 | E105: NATALIA PLUA | F105: Red | G105: MEDIA | H105: APPUNTAMENTO BANCA
... A109: d84f2b94 | B109: 45827 | C109: 0.41666667 | D109: 0.45833333 | E109: LUIS | F109: Yellow | G109: ALTA | H109: Cambio de furgone gs047ka por el gs045ka fatto per cesar
A110: 3z3z3z | B110: 46008 | C110: 0.41666667 | D110: 0.41666667 | F110: Blue | G110: BAJA | H110: Cumple Jhon Julian
A111: 4a4a4a4 | B111: 45921 | C111: 0.41666667 | D111: 0.41666667 | F111: Blue | G111: BAJA | H111: Cumple Felipe Bustamante
A112: 9q9q9q | B112: 46101 | C112: 0.41666667 | D112: 0.41666667 | F112: Blue | G112: BAJA | H112: Cumple Adrian Rojas
A113: 4c90e6b9 | B113: 45833 | C113: 0.41666667 | D113: 0.45833333 | E113: LUIS | F113: Yellow | G113: ALTA | H113: Rilascio per permesso di soggiorno
A114: ec90635c | B114: 45831 | C114: 0.41666667 | D114: 0.45833333 | E114: CARLOS | F114: Blue | G114: ALTA | H114: Cambio de pastiglia fy593se
A115: c4ace197 | B115: 45838 | C115: 0.375 | D115: 0.45833333 | E115: LUIS | F115: Yellow | G115: ALTA | H115: Permeso jeanpier temas personales solo esta facendo giro matina
A116: 6ab32c34 | B116: 45842 | C116: 0.41666667 | D116: 0.45833333 | E116: LUIS | F116: Yellow | G116: ALTA | H116: Cita en la scuola
A117: 12poo | B117: 45914 | C117: 0.41666667 | D117: 0.41666667 | F117: Blue | G117: BAJA | H117: Cumple Jonathan Ceclen
A118: 235p11 | B118: 45958 | C118: 0.41666667 | D118: 0.41666667 | F118: Blue | G118: BAJA | H118: Cumple Angelo Villareal
A119: 6a7d3abe | B119: 45853 | C119: 0.375 | D119: 0.41666667 | E119: LUIS | F119: Yellow | G119: ALTA | H119: Appuntamento Adrian nella questura
A120: 91550c12 | B120: 45866 | C120: 0.375 | D120: 0.41666667 | E120: LUIS | F120: Yellow | G120: ALTA | H120: Vacaciones de Edgar Antonio Rivera. Del 28/07 al 11/08 reingresa el martes 12/08
A121: 86f5a838 | B121: 45856 | C121: 0.375 | D121: 0.41666667 | E121: LUIS | F121: Yellow | G121: ALTA | H121: Appuntamento en questura marvin.
A122: e054c342 | B122: 45876 | C122: 0.41666667 | D122: 0.45833333 | E122: LUIS | F122: Yellow | G122: ALTA | H122: Marvin no hizo intermedio
A123: 7a087887 | B123: 45882 | C123: 0.625 | D123: 0.6875 | E123: EMERSON | F123: Red | G123: ALTA | H123: Reunión con VICTOR RABANAL
A124: 8a449447 | B124: 45880 | C124: 0.41666667 | D124: 0.4375 | E124: LUIS | F124: Yellow | G124: ALTA | H124: No hay giro 210 intermedio porque esta cerrado abazzia e minerva
A125: cfc7bc25 | B125: 45887 | C125: 0.375 | D125: 0.54166667 | E125: LUIS | F125: Yellow | G125: ALTA | H125: Diego permiso por documentos
A126: fd11d6ce | B126: 45904 | C126: 0.47916667 | D126: 0.5 | E126: LUIS | F126: Yellow | G126: ALTA | H126: Cita en el consulado
A127: 1rw1r | B127: 45859 | C127: 0.41666667 | D127: 0.41666667 | F127: Blue | G127: BAJA | H127: Cumple Jean Arteaga
A128: 2e2e2 | B128: 45952 | C128: 0.41666667 | D128: 0.41666667 | F128: Blue | G128: BAJA | H128: Cumple Dennis Ingles
A129: 3e3e3 | B129: 46066 | C129: 0.41666667 | D129: 0.41666667 | F129: Blue | G129: BAJA | H129: Cumple Mauro Agostinello
A130: 577bc1c4 | B130: 45898 | C130: 0.16666667 | D130: 0.41666667 | E130: LUIS | F130: Yellow | G130: ALTA | H130: Diego no podra manejar.
A131: 4a7772bd | B131: 45902 | C131: 0.33333333 | D131: 0.41666667 | E131: LUIS | F131: Yellow | G131: ALTA | H131: Romario permesso por cumpleaños
A132: aaef622a | B132: 45908 | C132: 0.33333333 | D132: 0.41666667 | E132: LUIS | F132: Yellow | G132: ALTA | H132: Permiso por cumpleaños Luis poma
A133: c2b3e286 | B133: 45903 | C133: 0.20833333 | D133: 0.41666667 | E133: LUIS | F133: Yellow | G133: ALTA | H133: Permesso solo la mattina giro 102.
...

Sheet CALENDARIO AUTISTAS
A1: ID | B1: DATA | C1: HORA DE INICIO | D1: HORA FIN | E1: RESPONSABLE | F1: COLOR ASIGNADO | G1: PRIORIDAD | H1: TAREA
A2: 993debab | B2: 45888 | C2: 0.25694444 | E2: G028 | F2: Blue | H2: Lainate - Genova - Novara - Lainate - DHL.
A3: e4105ddb | F3: Black
A4: f3d72339 | B4: 46007 | C4: 0.54453704 | D4: 0.54453704 | E4: Marvin cerquin | F4: Green | G4: Necesito este dia libre

Sheet CALENDARIO FARMACIA
A1: ID | B1: FECHA | C1: HORA INICIO | D1: HORA FIN | E1: PRIORIDAD | F1: COLOR ASIGNADO | G1: TAREA | H1: DETALLE
A2: 01caf82e | B2: 45896 | C2: 0.18055556 | D2: 0.1875 | E2: ALTA | F2: Green | G2: Horario de ingreso al magazzino
A3: 507bc5ec | B3: 45896 | C3: 0.27777778 | D3: 0.32986111 | E3: ALTA | F3: Yellow | G3: Controlar que todos hayan partido. Verificación del app e actualizaciones.
A4: c2f10277 | B4: 45896 | C4: 0.33333333 | D4: 0.48680556 | E4: ALTA | F4: Red | G4: Cambio de aceite del 032 furgon de juan y llevar a la revisión tecnica. No se pudobrealiza por fallas en el furgon
A5: 9d29414a | B5: 45896 | C5: 0.53125 | D5: 0.125 | E5: ALTA | F5: Yellow | G5: Seguimiento de los giros. Controlar uso de uniforme correctamente. Envio de mail.
A6: 9e84c573 | B6: 45898 | C6: 0.125 | D6: 0.20833333 | E6: ALTA | F6: Red | G6: Diego ultimo dia que puede manejar
A7: 0c55b4dc | B7: 45897 | C7: 0.18055556 | D7: 0.27083333 | E7: ALTA | F7: Green | G7: Seguimiento de giri
A8: 702ff56d | B8: 45897 | C8: 0.33333333 | D8: 0.41666667 | E8: ALTA | F8: Yellow | G8: Revisión tecnica furgon 032
A9: 98f329a9 | B9: 45897 | C9: 0.41666667 | D9: 0.45833333 | E9: MEDIA | F9: Orange | G9: Seguimiento de giri intermedio. Verificación de llaves de giro que esten completas | H9: Verificación de llaves de giro que esten completas
A10: 0afa6d18 | B10: 45897 | C10: 0.47916667 | D10: 0.52013889 | E10: MEDIA | G10: Verificación se la app status vehículos
A11: a8913ec1 | B11: 45897 | C11: 0.54166667 | D11: 0.6875 | E11: ALTA | F11: Red | G11: Seguimiento de giro. Controlar giro 301 y 302
A12: 3111d918 | B12: 45897 | C12: 0.29166667 | D12: 0.33333333 | E12: ALTA | G12: Envio de mail descuentos correspondientes al mes de julio yan.
A13: 6258446a | B13: 45898 | C13: 0.25 | D13: 0.33333333 | E13: ALTA | F13: Green | G13: Verificación del formulario de trabajo diario.
A14: 6f551bf5 | B14: 45898 | C14: 0.33333333 | D14: 0.41666667 | E14: ALTA | G14: Verificación de vehículos limpieza.
A15: c399800d | B15: 45898 | C15: 0.45833333 | D15: 0.52083333 | E15: ALTA | G15: Portar el furgon fy593se al parcheggio de carlos.
A16: 18cc7b6e | B16: 45898 | C16: 0.54166667 | D16: 0.625 | E16: ALTA | F16: Red | G16: Revisión y seguimiento de órdenes y verificación de uso de epp
A17: 2d4cd2f9 | B17: 45897 | C17: 0.41666667 | D17: 0.45833333 | E17: ALTA | F17: Red | G17: Envio de mail de descuentos
A18: 88517ce7 | B18: 45899 | C18: 0.29166667 | D18: 0.375 | E18: ALTA | F18: Red | G18: Verificación de mecánica de vehículos y programación.
A19: b2754fa0 | B19: 45899 | C19: 0.41666667 | D19: 0.5 | E19: ALTA | F19: Red | G19: Verificación del llenado del formulario por el cierre de mes.
A20: 97cd194a | B20: 45899 | C20: 0.54166667 | D20: 0.60416667 | E20: ALTA | G20: Verificación de los giros domingo ya que no tengo todos los vehiculos operativos
A21: aeae2f5a | B21: 45899 | C21: 0.375 | D21: 0.41666667 | E21: MEDIA | F21: Green | G21: Verificación de app. Controllo de velocità e documentos.
A22: 8c4fa4c0 | B22: 45899 | C22: 0.60416667 | D22: 0.66666667 | E22: ALTA | F22: Purple | G22: Detalles de programación para la proxima semana è inizio de mes
A23: 9288ead9 | B23: 45901 | C23: 0.25 | D23: 0.33333333 | E23: ALTA | F23: Red | G23: Verificación de llenado correcto de formulario y depuracion de inconsistencias.
A24: 48f2b533 | B24: 45901 | C24: 0.33402778 | D24: 0.39583333 | E24: ALTA | F24: Red | G24: Verificación de traducción de todos y posibles vencimiento de documentos.
A25: b642c520 | B25: 45901 | C25: 0.41666667 | D25: 0.47916667 | E25: ALTA | F25: Red | G25: Envio de mail. Con inconsistencias
A26: 557319d5 | B26: 45901 | C26: 0.52083333 | D26: 0.10416667 | E26: ALTA | F26: Yellow | G26: Cumplimiento y verificación de uniformes limpios
A27: 5c241775 | B27: 45902 | C27: 0.16666667 | D27: 0.41666667 | E27: ALTA | F27: Red | G27: Cubrir el giro de Romario
A28: a012c3ef | B28: 45902 | C28: 0.54166667 | D28: 0.70833333 | E28: ALTA | F28: Red | G28: Cubrir giro de Romario
A29: 46e90b98 | B29: 45902 | C29: 0.4375 | D29: 0.47916667 | E29: ALTA | F29: Yellow | G29: Intermedio
A30: e0b844e9 | B30: 45903 | C30: 0.16666667 | D30: 0.72916667 | E30: ALTA | F30: Red | G30: Cubrir giro Julio Dioses
A31: 9c9e0f49 | B31: 45903 | C31: 0.41666667 | D31: 0.47916667 | E31: ALTA | G31: Coordinación de renovación de traducción.
A32: 4a145318 | B32: 45903 | C32: 0.72916667 | D32: 0.77083333 | E32: ALTA | F32: Yellow | G32: Verificación dell app, llenado de formulario.
A33: a38259b3 | B33: 45904 | C33: 0.16666667 | D33: 0.4375 | E33: ALTA | G33: Cubrir giro 101 Romario quispe
A34: 874279bd | B34: 45904 | C34: 0.54166667 | D34: 0.70833333 | E34: ALTA | F34: Red | G34: Giro 301 cubrir a Romario quispe
A35: ecadd74c
A36: 0c2f82cc | B36: 45904 | C36: 0.45833333 | D36: 0.54166667 | E36: ALTA | F36: Green | G36: Cita consulado luis poma
A37: 02aeb2a1 | B37: 45905 | C37: 0.27083333 | D37: 0.35416667 | E37: ALTA | F37: Green | G37: Verificación de documentos (traducciones)
A38: 5c0abf49 | B38: 45905 | C38: 0.37638889 | D38: 0.47916667 | E38: ALTA | F38: Red | G38: Verificación de llenado del formulario y documentos por vencer.
A39: 7f53cc11 | B39: 45905 | C39: 0.47916667 | D39: 0.54166667 | E39: MEDIA | F39: Yellow | G39: Almuerzos
A40: 470856d8 | B40: 45905 | C40: 0.54166667 | D40: 0.64583333 | E40: MEDIA | G40: Verificación de vehículos y ospedalieros en la PC di univex
A41: 15557eb9 | B41: 45905 | C41: 0.64583333 | D41: 0.6875 | E41: ALTA | G41: Responder mail.
A42: 02f5cc79 | B42: 45909 | C42: 0.29166667 | D42: 0.39583333 | E42: ALTA | F42: Green | G42: Acompañamiento Dennis
A43: adbdd5a7 | B43: 45909 | C43: 0.39583333 | D43: 0.47916667 | E43: MEDIA | G43: Revisión llenado de carburante
A44: 18ace571 | B44: 45909 | C44: 0.54166667 | D44: 0.64583333 | E44: ALTA | F44: Red | G44: Coordinación de cambio de gomme
A45: c4c62d75 | B45: 45910 | C45: 0.29166667 | D45: 0.41666667 | E45: ALTA | G45: Recolección de documentos
A46: 9f26fa4e | B46: 45910 | C46: 0.45833333 | D46: 0.5 | E46: ALTA | G46: Envio documentos yan
A47: 9b9d6763 | B47: 45910 | C47: 0.54166667 | D47: 0.64513889 | E47: ALTA | F47: Green | G47: Revisión de carburante e controllo
A48: b7506685 | B48: 45911 | C48: 0.3125 | D48: 0.375 | E48: ALTA | F48: Green | G48: Limpieza del vito y envio de solicitus para la autorización de transporte a univex.
A49: 26de802f | B49: 45911 | C49: 0.375 | D49: 0.47916667 | E49: ALTA | F49: Orange | G49: Verificación de llenado correcto carburante y Verificación del llenado del formulario
A50: 7dff4521 | B50: 45911 | C50: 0.54166667 | D50: 0.64583333 | E50: ALTA | F50: Black | G50: Verificación de limpieza de furgones e revisión de gps.
A51: ad8c4129 | B51: 45911 | C51: 0.64583333 | D51: 0.72916667 | E51: ALTA | G51: Responder mail.
A52: a4b34c40 | B52: 45912 | C52: 0.16666667 | D52: 0.4375 | E52: ALTA | F52: Green | G52: Giro 101
A53: d25be12c | B53: 45912 | C53: 0.54166667 | D53: 0.70833333 | E53: ALTA | F53: Green | G53: Giro 301
A54: be7d295c | B54: 45912 | C54: 0.45833333 | D54: 0.5 | E54: ALTA | F54: Red | G54: Revisión de carburante en el app
A55: f9121c8d | B55: 45915 | C55: 0.29166667 | D55: 0.375 | E55: ALTA | F55: Green | G55: Revisión de permisos e controllo de la assistenza
A56: a78354c8 | B56: 45915 | C56: 0.41666667 | D56: 0.47916667 | E56: ALTA | F56: Orange | G56: Controlar de carburante app
A57: 20b9dd8c | B57: 45915 | C57: 0.54166667 | D57: 0.625 | E57: ALTA | F57: Orange | G57: Controlar los gps
A58: 0c7d215f | B58: 45916 | C58: 0.16666667 | D58: 0.41666667 | E58: ALTA | F58: Green | G58: Giro 120
A59: 9a296d67 | B59: 45916 | C59: 0.54166667 | D59: 0.70833333 | E59: ALTA | F59: Green | G59: Giro 311
A60: 21dc0871 | B60: 45916 | C60: 0.41666667 | D60: 0.5 | E60: ALTA | G60: Verificación de documentos de vehículos.
A61: 32daeec5 | B61: 45917 | C61: 0.16666667 | D61: 0.45833333 | E61: ALTA | F61: Green | G61: Giro samarate
A62: 16b8855d | B62: 45917 | C62: 0.54166667 | D62: 0.70833333 | E62: ALTA | F62: Green | G62: Giro 329 samarate
A63: 0312a31e | B63: 45918 | C63: 0.16666667 | D63: 0.4375 | E63: ALTA | F63: Green | G63: Giro 129
A65: d5930e24 | B65: 45918 | C65: 0.54166667 | D65: 0.70833333 | E65: ALTA | F65: Orange | G65: Giro 361
A66: c9794169 | B66: 45919 | C66: 0.16666667 | D66: 0.4375 | E66: ALTA | F66: Green | G66: Giro 129 | H66: Giro extra
A67: af987c0a | B67: 45919 | C67: 0.54166667 | D67: 0.72916667 | E67: ALTA | F67: Yellow | G67: Giro 361 como
A68: 1030fc39 | B68: 45923 | C68: 0.16666667 | D68: 0.41666667 | E68: ALTA | F68: Green | G68: Giro 129 samarate
A69: e88c61c0 | B69: 45923 | C69: 0.45833333 | D69: 0.47916667 | E69: ALTA | F69: Yellow | G69: Responsabile di Intermedio.
A70: c417ffce | B70: 45923 | C70: 0.54166667 | D70: 0.70833333 | E70: ALTA | G70: Giro extra 361 como
A71: 26391364 | B71: 45924 | C71: 0.16666667 | D71: 0.41666667 | E71: ALTA | F71: Green | G71: Giro 123 vimercate
A72: 354b09bc | B72: 45924 | C72: 0.4375 | D72: 0.47916667 | E72: MEDIA | G72: Responsabile di giro
A73: 8d22a272 | B73: 45924 | C73: 0.54166667 | D73: 0.72916667 | E73: ALTA | F73: Orange | G73: Giro 323 vimercate
A74: 46f8550f | B74: 45925 | C74: 0.16666667 | D74: 0.4375 | E74: ALTA | F74: Green | G74: Giro 129
A75: 74f35e71 | B75: 45925 | C75: 0.54166667 | D75: 0.72916667 | E75: ALTA | F75: Yellow | G75: Giro 361
A76: 8007d22b | B76: 45926 | C76: 0.16666667 | D76: 0.4375 | E76: ALTA | F76: Green | G76: Giro 129
A77: e49de02f | B77: 45926 | C77: 0.4375 | D77: 0.47916667 | E77: ALTA | F77: Yellow | G77: Controllo di furgone per cambio de olio
A78: dad5ade7 | B78: 45926 | C78: 0.54166667 | D78: 0.72916667 | E78: ALTA | F78: Red | G78: Giro 361 como
A79: 3860f197 | B79: 45929 | C79: 0.16666667 | D79: 0.41666667 | E79: BAJA | F79: Green | G79: Giro 103
A80: 4d99db6e | B80: 45929 | C80: 0.53125 | D80: 0.70833333 | E80: ALTA | F80: Orange | G80: Giro 303
A81: 17117bcf | B81: 45929 | C81: 0.41666667 | D81: 0.52083333 | E81: ALTA | F81: Yellow | G81: Revisione ES270BA
A82: 8887780e | B82: 45930 | C82: 0.17708333 | D82: 0.27083333 | E82: BAJA | F82: Green | G82: Controllo de kilómetros e asistencia
A83: f96d9ae6 | B83: 45930 | C83: 0.54166667 | D83: 0.70833333 | E83: ALTA | G83: Controllo cierre de fin de mes
A84: b69f5266 | B84: 45931 | C84: 0.375 | D84: 0.54166667 | E84: MEDIA | F84: Red | G84: Movimiento de unidades para mantenimiento
A85: 8c77a293 | B85: 45931 | C85: 0.16666667 | D85: 0.375 | E85: MEDIA | G85: Seguimiento de gir
A86: 65f3c7e3 | B86: 45931 | C86: 0.58402778 | D86: 0.72916667 | E86: MEDIA | G86: Recojo soggiorno
A87: 4ef9f2d2 | B87: 45932 | C87: 0.16666667 | D87: 0.29166667 | E87: ALTA | G87: Controllo de kilometraje de todos los furgone
A88: dd2b6d5b | B88: 45932 | C88: 0.33333333 | D88: 0.41666667 | E88: ALTA | F88: Yellow | G88: Verificación de temas pendientes del cierre de mes
A89: bd9999a2 | B89: 45932 | C89: 0.41666667 | D89: 0.47916667 | E89: ALTA | G89: Controllo de velocità
A90: dd8396c1 | B90: 45932 | C90: 0.54166667 | D90: 0.66666667 | E90: ALTA | F90: Green | G90: Verificación de giro e dpc de vaccini
A91: 5c53803d | B91: 45933 | C91: 0.16666667 | D91: 0.41666667 | E91: ALTA | F91: Green | G91: Giro extra 108
A92: 45dcc46e | B92: 45933 | C92: 0.4375 | D92: 0.47916667 | E92: ALTA | F92: Yellow | G92: Registro carburante
A93: 39c3c109 | B93: 45933 | C93: 0.54166667 | D93: 0.625 | E93: ALTA | F93: Red | G93: Control de giro
A94: 7ac18848 | B94: 45952 | C94: 0.20833333 | D94: 0.4375 | F94: Green | G94: Giro 119
A95: fa6be3de | B95: 45952 | C95: 0.53125 | D95: 0.70833333 | E95: MEDIA | F95: Green | G95: Giro 319
A96: d9934cf9 | B96: 45953 | C96: 0.16666667 | D96: 0.27083333 | E96: ALTA | F96: Green | G96: Controllo de olio de tutti le furgone
A97: 7a57e562 | B97: 45953 | C97: 0.36458333 | D97: 0.41666667 | E97: BAJA | F97: Red | G97: Appuntamento medico
A98: ea5e4127 | B98: 45953 | C98: 0.54166667 | D98: 0.72916667 | E98: ALTA | G98: Giro 319
A99: c78069f0 | B99: 45953 | C99: 0.41666667 | D99: 0.47916667 | E99: MEDIA | F99: Yellow | G99: Revisión e controllo app
A100: 0543bb98 | B100: 45954 | C100: 0.1875 | D100: 0.4375 | E100: ALTA | F100: Green | G100: Giro 119 vimercate
A101: 068c0a78 | B101: 45954 | C101: 0.4375 | D101: 0.52083333 | E101: MEDIA | F101: Yellow | G101: Portar el furgon a san giuliano porque esta fallando el freno
...

Sheet CALENDARIO DHL
A1: ID | B1: FECHA | C1: HORA INICIO | D1: HORA FIN | E1: PRIORIDAD | F1: COLOR ASIGNADO | G1: TAREA | H1: DETALLE
A2: a9c83e3a | B2: 45192 | E2: MEDIA | G2: actualizar el app gamonal , grestionar navetas y entregas programadas en la madrugada | H2: actualizar el app gamonal , grestionar navetas y entregas programadas en la madrugada
A3: ad95a613 | B3: 45930 | C3: 0.29166667 | D3: 0.375 | E3: MEDIA | F3: Yellow | G3: actualizar y gestionar los paccos de la repiribilita y los los paccos programados para la mañana
A4: 66b3bc31 | B4: 45930 | C4: 0.375 | D4: 0.5 | E4: MEDIA | F4: Yellow | G4: realizar el seguimiento de las entregas y buscar una mejor gestion en gastos de combustible y telepass
A5: b8a7e578 | B5: 45929 | C5: 0.5 | D5: 0.54166667 | E5: MEDIA | F5: Green | G5: refrigerio
A6: f8789bd7 | B6: 45929 | C6: 0 | D6: 0.54166667 | E6: MEDIA | F6: Green | G6: refrigerio
A7: 46f5f015 | B7: 45930 | C7: 0.5 | D7: 0.54166667 | E7: BAJA | G7: refrigerio
A8: 9385b428 | B8: 45930 | C8: 0.54166667 | D8: 0.625 | E8: MEDIA | F8: Yellow | G8: gestionar consegnas y subir extras al sistema
A9: 4b55784a | B9: 45930 | C9: 0.625 | D9: 0.70833333 | E9: MEDIA | F9: Yellow | G9: subir tagliando de los carros y gestionar carros quec se quedaran en peschiera
A10: 0bf4e52a | B10: 45930 | C10: 0.70833333 | D10: 0.79166667 | E10: MEDIA | F10: Yellow | G10: enviar correo de los furgones dejados en peschiera
A11: fc5121d1 | B11: 45932 | C11: 0.29166667 | D11: 0.375 | E11: ALTA | F11: Red | G11: revisar y actualizar las entregas de la reperibilita
A12: a4f49a1c | B12: 45932 | C12: 0.375 | D12: 0.5 | E12: MEDIA | F12: Orange | G12: revisar km del mes de septiembre
A13: 1ed9d5b7 | B13: 45932 | C13: 0.5 | D13: 0.54166667 | E13: ALTA | F13: Purple | G13: refrigerio
A14: 6a4658e0 | B14: 45932 | C14: 0.54166667 | D14: 0.625 | E14: MEDIA | F14: Yellow | G14: asignasion de revision de vehiculos
A15: d8c9a27e | B15: 45932 | C15: 0.625 | D15: 0.70833333 | E15: MEDIA | F15: Yellow | G15: sistemar los carros que se quedan en peschiera y las consegnas para el dia siguiente
A16: 17aaa2b3 | B16: 45932 | C16: 0.70833333 | D16: 0.79166667 | E16: ALTA | F16: Red | G16: pago de carburante , enviar correo cpon las placas de los carro que se quedan en pesvchiera
A17: 07b946bf | B17: 45952 | C17: 0.29166667 | D17: 0.375 | E17: ALTA | F17: Red | G17: reunion con los chicos , emerson y natalia
A18: 5bd3f3b2 | B18: 45952 | C18: 0.375 | D18: 0.5 | E18: MEDIA | F18: Orange | G18: actualizacion del app gamonal y programacion de entregas
A19: b548aa1e | B19: 45952 | C19: 0.5 | D19: 0.54166667 | E19: ALTA | F19: Yellow | G19: refrigerio
... A21: 8bb5e6ce | B21: 45952 | C21: 0.625 | D21: 0.70833333 | E21: MEDIA | F21: Blue | G21: actualizacion de entregas , gestionn de entregas y corrovorar los gastos de combustible
A22: c6fcdab4 | B22: 45952 | C22: 0.70833333 | D22: 0.79166667 | F22: Orange | G22: programar paquetes para el dia siguiente , pago de carburante , asignacion de vehiculos para el dia siguien
A23: 9a8d978b | B23: 45953 | C23: 0.29166667 | D23: 0.375 | E23: ALTA | F23: Red | G23: reunion via zoom con Natalia y Luis
A24: 2e3587e7 | B24: 45953 | C24: 0.375 | D24: 0.5 | E24: BAJA | F24: Orange | G24: revisar los extra
A25: 3bddd377 | B25: 45953 | C25: 0.5 | D25: 0.54166667 | E25: ALTA | F25: Yellow | G25: refrigerio
A26: 8ff3237e | B26: 45953 | C26: 0.54166667 | D26: 0.625 | E26: MEDIA | F26: Blue | G26: revisar km semanales
A27: 78b453f1 | B27: 45953 | C27: 0.625 | D27: 0.70833333 | E27: MEDIA | F27: Yellow
A28: 16f627a5 | B28: 45953 | C28: 0.70833333 | D28: 0.79166667 | E28: MEDIA | F28: Green | G28: pago de combustible , asignacion de consegna y pacos para el dia siguiente
A29: 2a69c1a9 | B29: 45953 | C29: 0.29166667 | D29: 0.41666667 | E29: ALTA | F29: Yellow | G29: asignacion y verificasion de paccos de la reperibilitad
A30: 3812c214 | B30: 45954 | C30: 0.29166667 | D30: 0.41666667 | E30: ALTA | F30: Orange | G30: asignasion y verificasion de paccos de la frepeeibilitad
A31: 2fa7cd87 | B31: 45954 | C31: 0.41666667 | D31: 0.5 | E31: MEDIA | F31: Yellow | G31: revision de unidades y km de los furgones
A32: 2f9938d1 | B32: 45954 | C32: 0.5 | D32: 0.54166667 | E32: ALTA | F32: Red | G32: refrigerio
A33: ff306fd6 | B33: 45954 | C33: 0.54166667 | D33: 0.625 | E33: MEDIA | F33: Green | G33: actualizasion de km en el app gamonal
A34: ce7a697c | B34: 45954 | C34: 0.625 | D34: 0.70833333 | E34: MEDIA | F34: Purple | G34: asignacion de entregas y estadisticas de carburante
A35: 088fa7e1 | B35: 45954 | C35: 0.70833333 | D35: 0.79166667 | E35: ALTA | F35: Green | G35: asignasion de unidades para el fin de semana y consegnas pendientes para el fin de seman , pago cargurantes
A36: 0d004f57 | B36: 45958 | C36: 0.29166667 | D36: 0.5 | E36: ALTA | G36: revisar km subidos por los muchachos en el app gamonal (extras)
A37: cb30da3b | B37: 45958 | C37: 0.5 | D37: 0.54166667 | E37: MEDIA | F37: Yellow | G37: refrigerio
A38: f2488aa2 | B38: 45958 | C38: 0.54166667 | D38: 0.625 | E38: MEDIA | F38: Orange | G38: revision de km al dia y gastos de carburante
A39: 1e0579f2 | B39: 45958 | C39: 0.625 | D39: 0.70833333 | E39: MEDIA | F39: Purple | G39: revision de limpieza de furgones y asignmacion de los mismos
A40: d344f604 | B40: 45958 | C40: 0.70833333 | D40: 0.79166667 | E40: MEDIA | F40: Orange | G40: asignacion de entregas para el dia siguiente , pago de combustible
A41: bcc228ad | B41: 45959 | C41: 0.29166667 | D41: 0.41666667 | E41: ALTA | F41: Red | G41: gestionar las entregas y actualizar las entregas de la reperibilidad
A42: 20116913 | B42: 45959 | C42: 0.41666667 | D42: 0.5 | E42: MEDIA | F42: Orange | G42: actualizar extras
A43: f4c57292 | B43: 45959 | C43: 0.5 | D43: 0.54166667 | E43: MEDIA | F43: Yellow | G43: refrigerio
A44: f59197d5 | B44: 45959 | C44: 0.54166667 | D44: 0.66666667 | E44: MEDIA | F44: Orange | G44: revisar los mancato pagamentos
A45: 0007672a | B45: 45959 | C45: 0.66666667 | D45: 0.75 | E45: ALTA | G45: alistar programacion para el dia siguiente , asignar consegna par del dia siguiente
A46: 49fe0035 | B46: 45959 | C46: 0.75 | D46: 0.79166667 | E46: MEDIA | F46: Red | G46: hacer erl pago del combustible

Sheet MULTAS
A1: ARCHIVO | B1: ESTADO | C1: NOMBRE | D1: TARGA | E1: MONTO | F1: FECHA P5D -30% | G1: FECHA CT | H1: FECHA | I1: HORA | J1: VERBALE | K1: SCADENZA | L1: DIC | M1: ENE | N1: FEB | O1: MAR | P1: ABR | Q1: MAY | R1: JUN | S1: JUL | T1: AGO | U1: SET | V1: OCT | W1: NOV | X1: DIC | Y1: SALDO | Z1: COMENTARIOS | AA1: PTOS PATENTE | AB1: TIPO | AC1: Id_trabajador | AD1: Id_Multas | AE1: RECIBO DE PAGO | AF1: TIPO | AG1: MES | AH1: ¿60 D? | AI1: C. AVVISO | AJ1: C. FISCALE ENTE CREDITORE
B2: PAGADO | C2: ADOLFO ROSALES | D2: GL089JC | E2: =166+291 -> 457 | H2: 45531 | I2: 0.35486111 | J2: RD00121439 | L2: -100 | M2: -100 | N2: -100 | Y2: =E2+L2+M2+N2+O2+P2+Q2+R2+S2+T2+U2+V2+W2+X2 -> 157 | Z2: SE DESCONTO NOV, DIC Y ENERO 100 CADA MES | AB2: MULTA | AC2: G013 | AD2: qwt9 | AF2: LAVORATORE
B3: PAGADO | C3: ADOLFO ROSALES | D3: GL089JC | E3: 60 | H3: 45543 | I3: 0.33194444 | J3: VI01134932 | Y3: =E3+L3+M3+N3+O3+P3+Q3+R3+S3+T3+U3+V3+W3+X3 -> 60 | AB3: MULTA | AC3: G013 | AD3: bv666 | AF3: LAVORATORE
A4: MULTAS_Images/G015.ARCHIVO.164632.jpg | B4: PAGADO | C4: EDWAR GUERRERO | D4: GP392DZ | E4: 31 | H4: 45695 | I4: 0.45347222 | J4: 700907 | N4: -31 | Y4: =E4+L4+M4+N4+O4+P4+Q4+R4+S4+T4+U4+V4+W4+X4 -> 0 | Z4: Multa por descontar | AA4: NO | AB4: MULTA | AC4: G015 | AD4: kt9 | AF4: LAVORATORE
A5: MULTAS_Files_/9001002063105.ARCHIVO.151039.09.pdf | B5: PAGADO | C5: DOMINICK LEON | D5: GB502TP | E5: 60 | H5: 45716 | I5: 0.7375 | J5: 9001002063105 | N5: -60 | Y5: =E5+L5+M5+N5+O5+P5+Q5+R5+S5+T5+U5+V5+W5+X5 -> 0 | Z5: MULTA PAGATA DA NATALIA | AA5: NO | AB5: MULTA | AC5: G009 | AD5: qet85ss6 | AF5: LAVORATORE
A6: MULTAS_Images/V3822U2025.ARCHIVO.151609.jpg | B6: VENCIDA | C6: DIEGO MOLINA | D6: EM504JT | E6: 222 | F6: 10/03/2025 | G6: 10/03/2025 | H6: 45726 | I6: 0.3 | J6: V3822U2025 | K6: 36892 | O6: -100 | S6: -72 | T6: -50 | Y6: =E6+L6+M6+N6+O6+P6+Q6+R6+S6+T6+U6+V6+W6+X6 -> 0 | AB6: MULTA | AC6: G020 | AD6: xbs199bx | AF6: LAVORATORE
A7: MULTAS_Images/V607S2025.ARCHIVO.155242.jpg | B7: PAGADO | C7: JUAN CARLOS | D7: ER643VY | E7: 128 | H7: 45699 | I7: 0.48888889 | J7: V607S2025 | R7: -40 | S7: -88 | Y7: =E7+L7+M7+N7+O7+P7+Q7+R7+S7+T7+U7+V7+W7+X7 -> 0 | Z7: DA CONTROLLARE!!!! | AB7: MULTA | AC7: G025 | AD7: o9q56s | AF7: LAVORATORE
B8: PAGADO | C8: JURGEN PALIZA | E8: 458 | H8: 45618 | J8: PAMSO222 | L8: -100 | M8: -100 | N8: -58 | O8: -100 | Q8: -100 | Y8: =E8+L8+M8+N8+O8+P8+Q8+R8+S8+T8+U8+V8+W8+X8 -> 0 | Z8: Se desconto en diciembre y enero | AB8: MULTA | AC8: G017 | AD8: lq66 | AF8: LAVORATORE
B9: PAGADO | C9: LUIS POMA | D9: GM089XH | E9: 80 | H9: 45524 | I9: 0.32777778 | J9: 990118/2024/V | M9: -80 | Y9: =E9+L9+M9+N9+O9+P9+Q9+R9+S9+T9+U9+V9+W9+X9 -> 0 | Z9: Descontado en enero | AB9: MULTA | AC9: G005 | AD9: 99ñ78q8 | AF9: LAVORATORE
B10: PAGADO | C10: EMPRESA | D10: GM089XH | E10: 80 | H10: 45525 | I10: 0.31597222 | J10: 990277/2024/V | M10: -80 | Y10: =E10+L10+M10+N10+O10+P10+Q10+R10+S10+T10+U10+V10+W10+X10 -> 0 | Z10: no pagamento de area C, asumido por empresa | AB10: ÁREA C | AC10: 451ba90f | AD10: k23f13zx9 | AF10: HACIENDA
B11: PAGADO | C11: ALONSO TAMARA | E11: 300 | H11: 45735 | J11: 12SAFASF | Y11: =E11+L11+M11+N11+O11+P11+Q11+R11+S11+T11+U11+V11+W11+X11 -> 300 | Z11: Multa | AB11: MULTA | AC11: G014 | AD11: w5t19qq | AF11: LAVORATORE
A12: MULTAS_Files_/bd0ad194.ARCHIVO.181619.pdf | B12: PAGADO | C12: JURGEN PALIZA | D12: FY032BD | E12: 181 | F12: 08/01/2025 | G12: 08/01/2025 | H12: 45665 | I12: 0.70486111 | J12: V/16959R/2025 | P12: -21 | R12: -100 | S12: -60 | Y12: =E12+L12+M12+N12+O12+P12+Q12+R12+S12+T12+U12+V12+W12+X12 -> 0 | Z12: Esta multa llegó con otra multa pero con el verbal en la decripción del otro documento, es decir, está pagada | RIDOTTA: 120,23 (ERA 170, ORA 181 SI PUO PAGARE ANCORA IN APP) | AA12: SI | AB12: MULTA SEMAFORICA | AC12: G017 | AD12: bd0ad194 | AF12: 12/12/1212 12:00:56
A13: MULTAS_Files_/26547eea.ARCHIVO.184652.pdf | B13: VENCIDA | C13: SANTHA NEELAPPAGE | D13: EM504JT | E13: 243 | F13: 06/02/2025 | G13: 06/02/2025 | H13: 45694 | I13: 0.26111111 | J13: V/2945B/2025 | Y13: =E13+L13+M13+N13+O13+P13+Q13+R13+S13+T13+U13+V13+W13+X13 -> 243 | Z13: RIDOTTA: 164,87 (ERA 231, ORA 243 SI PUO ANCORA PAGARE IN APP) | AA13: SI | AB13: MULTA SEMAFORICA | AC13: G019 | AD13: 26547eea | AF13: LAVORATORE
A14: MULTAS_Files_/a72dde34.ARCHIVO.131831.pdf | B14: PAGADO | C14: JURGEN PALIZA | D14: FY032BD | E14: 76 | F14: Y | G14: 04/02/2025 | H14: 45692 | I14: Y | J14: VI01260149 | P14: -76 | Y14: =E14+L14+M14+N14+O14+P14+Q14+R14+S14+T14+U14+V14+W14+X14 -> 0 | Z14: Esta multa se actualizó, llegó otra multa actualizada con el mismo número verbale y ya se pagó | AA14: N | AB14: MULTA VELOCITA' | AC14: G017 | AD14: a72dde34 | AF14: 12/12/1212 14:02:58 | AH14: ✅
A16: MULTAS_Files_/05dfb4f3.ARCHIVO.060958.pdf | B16: PAGADO | C16: JURGEN PALIZA | D16: FY032BD | E16: 251 | F16: 10/02/2025 | G16: 10/02/2025 | H16: 45698 | I16: 0.20833333 | J16: VI01264559 | T16: -200 | U16: -51 | Y16: =E16+L16+M16+N16+O16+P16+Q16+R16+S16+T16+U16+V16+W16+X16 -> 0 | Z16: MULTA DA ADDEBITARE | Fue pagado por NATALIA EL 28/10/25 | AA16: SI | AB16: MULTA VELOCITA' | AC16: G017 | AD16: 05dfb4f3 | AE16: MULTAS_Files_/05dfb4f3.RECIBO DE PAGO.103440.pdf
A17: MULTAS_Files_/dbc2ace1.ARCHIVO.062650.pdf | B17: VENCIDA | C17: EMPRESA | D17: FY032BD | E17: 101 | F17: 08/11/2024 | G17: 08/11/2024 | H17: 45604 | I17: 0.32222222 | J17: 03633035/2024/1/1/1 | O17: -101 | Y17: =E17+L17+M17+N17+O17+P17+Q17+R17+S17+T17+U17+V17+W17+X17 -> 0 | Z17: MULTA DA ADDEBITARE | AA17: NO | AB17: MULTA AREA C | AC17: 451ba90f | AD17: dbc2ace1 | AF17: HACIENDA
A18: MULTAS_Files_/6f9a8a83.ARCHIVO.063438.pdf | B18: VENCIDA | C18: EMPRESA | D18: FY032BD | E18: 101 | F18: 14/11/2024 | G18: 14/11/2024 | H18: 45610 | I18: 0.32569444 | J18: 03633039/2024/1/1/1 | O18: -101 | Y18: =E18+L18+M18+N18+O18+P18+Q18+R18+S18+T18+U18+V18+W18+X18 -> 0 | Z18: MULTA DA PAGARE ENTRO 28/05 | AA18: NO | AB18: MULTA AREA C | AC18: 451ba90f | AD18: 6f9a8a83 | AF18: HACIENDA
A19: MULTAS_Files_/be752ca2.ARCHIVO.071422.pdf | B19: VENCIDA | C19: EMPRESA | D19: FY032BD | E19: 60 | F19: 09/11/2024 | G19: 09/11/2024 | H19: 45605 | I19: 0.46527778 | J19: 03633036/2024/1/1/1 | O19: -60 | Y19: =E19+L19+M19+N19+O19+P19+Q19+R19+S19+T19+U19+V19+W19+X19 -> 0 | Z19: MULTA DA ADDEBITARE / NON REGISTRATO SUL FORMS / GIRO 113 (APROX) | AA19: NO | AB19: MULTA SOSTA MARGINE DESTRO | AC19: 451ba90f | AD19: be752ca2 | AF19: HACIENDA
A20: MULTAS_Files_/d9776622.ARCHIVO.071952.pdf | B20: VENCIDA | C20: EMPRESA | D20: FY032BD | E20: 101 | F20: 20/11/2024 | G20: 20/11/2024 | H20: 45616 | I20: 0.64791667 | J20: 03633040/2024/1/1/1 | O20: -101 | Y20: =E20+L20+M20+N20+O20+P20+Q20+R20+S20+T20+U20+V20+W20+X20 -> 0 | Z20: NON PAGATA AREA C/ MULTA DI NOVEMBRE | AA20: NO | AB20: MULTA AREA C | AC20: 451ba90f | AD20: d9776622 | AF20: HACIENDA
A21: MULTAS_Files_/5fa02650.ARCHIVO.072537.pdf | B21: VENCIDA | C21: SANTHA NEELAPPAGE | D21: EM504JT | E21: 189 | F21: 17/03/2025 | G21: 17/03/2025 | H21: 45733 | I21: 0.42291667 | J21: 3277AX/25 | Y21: =E21+L21+M21+N21+O21+P21+Q21+R21+S21+T21+U21+V21+W21+X21 -> 189 | Z21: RIDOTTA: 124,60 ( ERA 176, ORA 189 SI PUO ANCORA PAGARE IN APP) | AA21: SI | AB21: MULTA VELOCITA' | AC21: G019 | AD21: 5fa02650 | AF21: LAVORATORE
A22: MULTAS_Files_/1c9596c9.ARCHIVO.075217.pdf | B22: PAGADO | C22: LIBRE | D22: GB502TP | E22: 62 | I22: 0.51180556 | J22: VI01261477 | M22: -62 | Y22: =E22+L22+M22+N22+O22+P22+Q22+R22+S22+T22+U22+V22+W22+X22 -> 0 | Z22: Natalia lo pagó con tarjeta en otra multa actualizada pero con el mismo verbale | SEGUN DICEN QUE ES DE NATALIA -.- | AA22: NO | AB22: MULTA VELOCITA' | AD22: 1c9596c9 | AF22: 12/12/1212 12:00:56
A23: MULTAS_Files_/627b2f7f.ARCHIVO.080115.pdf | B23: VENCIDA | C23: SANTHA NEELAPPAGE | D23: EM504JT | E23: 189 | F23: 20/03/2025 | G23: 20/03/2025 | H23: 45736 | I23: 0.41666667 | J23: 3299AX/25 | Y23: =E23+L23+M23+N23+O23+P23+Q23+R23+S23+T23+U23+V23+W23+X23 -> 189 | Z23: RIDOTTA: 124.,60 (ERA 176, ORA 189 SI PUO PAGARE ANCORA IN APP) | AA23: SI | AB23: MULTA VELOCITA' | AC23: G019 | AD23: 627b2f7f | AF23: LAVORATORE
A24: MULTAS_Files_/f9c35989.ARCHIVO.082239.pdf | B24: VENCIDA | C24: DOMINICK LEON | D24: ET420XR | E24: 45 | F24: 21/03/2025 | G24: 21/03/2025 | H24: 45737 | I24: 0.57777778 | J24: 3810763523 | O24: -45 | Y24: =E24+L24+M24+N24+O24+P24+Q24+R24+S24+T24+U24+V24+W24+X24 -> 0 | Z24: MULTA DA ADDEBITARE | AA24: NO | AB24: MULTA VELOCITA' | AC24: G009 | AD24: f9c35989 | AF24: LAVORATORE
A25: MULTAS_Files_/9c57f90e.ARCHIVO.083341.pdf | B25: PAGADO | C25: JURGEN PALIZA | D25: FY032BD | E25: 76 | F25: 08/02/2025 | G25: YA PAGÓ | H25: 45696 | I25: 0.23680556 | J25: VI01276311 | N25: -76 | Y25: =E25+L25+M25+N25+O25+P25+Q25+R25+S25+T25+U25+V25+W25+X25 -> 0 | Z25: Esta multa se actualizó con otra multa y ya se pagó, las 2 multas concuerdan con el mismo número verbal: VI01276311 | AA25: NO | AB25: MULTA VELOCITA' | AC25: G017 | AD25: 9c57f90e | AF25: 12/01/0001 14:00:56
A26: MULTAS_Files_/7ca349a0.ARCHIVO.090454.pdf | B26: VENCIDA | C26: SANTHA NEELAPPAGE | D26: EM504JT | E26: 58 | F26: 17/03/2025 | G26: 17/03/2025 | H26: 45733 | I26: 0.47222222 | J26: V/1154S/2025 | Y26: =E26+L26+M26+N26+O26+P26+Q26+R26+S26+T26+U26+V26+W26+X26 -> 58 | Z26: RIDOTTA: 36,40 (ERA 49, ORA 58,74 SI PUO ANCORA PAGARE IN APP) | AA26: NO | AB26: MULTA VELOCITA' | AC26: G019 | AD26: 7ca349a0 | AF26: LAVORATORE
B27: VENCIDA | D27: FY032BD | E27: 101 | F27: 13/11/2024 | G27: 13/11/2024 | H27: 45609 | I27: 0.32986111 | J27: 03633038/2024/1/1/1 | O27: -101 | Y27: =E27+L27+M27+N27+O27+P27+Q27+R27+S27+T27+U27+V27+W27+X27 -> 0 | Z27: DA ADDEBITARE/ MULTA DI NOVEMBRE | AA27: NO | AB27: MULTA AREA C | AD27: 2ad8f9f0 | AF27: DA ASEGNARE
A28: MULTAS_Files_/9c4a9238.ARCHIVO.114118.pdf | B28: VENCIDA | C28: EMPRESA | D28: FY032BD | E28: 101 | F28: 11/11/2024 | G28: 11/11/2024 | H28: 45607 | I28: 0.65833333 | J28: 03633037/2024/1/1/1 | O28: -101 | Y28: =E28+L28+M28+N28+O28+P28+Q28+R28+S28+T28+U28+V28+W28+X28 -> 0 | Z28: MULTA DI NOVEMBRE | AA28: NO | AB28: MULTA AREA C | AC28: 451ba90f | AD28: 9c4a9238 | AF28: HACIENDA
A29: MULTAS_Files_/42df9cf1.ARCHIVO.115526.pdf | B29: VENCIDA | C29: EMPRESA | D29: DZ923BS | E29: 102 | F29: 14/02/2025 | G29: 14/02/2025 | H29: 45702 | I29: 0.48055556 | J29: 00306368/2025/1/1/1 | N29: -102 | Y29: =E29+L29+M29+N29+O29+P29+Q29+R29+S29+T29+U29+V29+W29+X29 -> 0 | Z29: NO REGISTRADO VEICULO EN FORMS (ROMARIO) | AA29: NO | AB29: MULTA AREA B | AC29: 451ba90f | AD29: 42df9cf1 | AF29: HACIENDA
A30: MULTAS_Files_/f781050b.ARCHIVO.143609.pdf | B30: VENCIDA | C30: EMPRESA | D30: EG403NT | E30: 102 | F30: 04/02/2025 | G30: 04/02/2025 | H30: 45692 | I30: 0.80069444 | J30: 00259589/2025/1/1/1 | Y30: =E30+L30+M30+N30+O30+P30+Q30+R30+S30+T30+U30+V30+W30+X30 -> 102 | AA30: NO | AB30: MULTA AREA C | AC30: 451ba90f | AD30: f781050b | AF30: HACIENDA
A31: MULTAS_Files_/d6f615ee.ARCHIVO.152813.pdf | B31: VENCIDA | C31: EMERSON GAMONAL | D31: GT894FF | E31: 510 | F31: 16/01/2025 | G31: 16/01/2025 | H31: 45673 | I31: 0.53472222 | J31: 70/15779649 | M31: -510 | Y31: =E31+L31+M31+N31+O31+P31+Q31+R31+S31+T31+U31+V31+W31+X31 -> 0 | Z31: DA ADDEBITARE | AA31: SI | AB31: MULTA CELLULARE | AC31: G002 | AD31: d6f615ee | AF31: HACIENDA
A32: MULTAS_Files_/5247b9b8.ARCHIVO.153320.pdf | B32: VENCIDA | C32: EMPRESA | D32: EX030XG | E32: 120 | F32: 25/01/2025 | G32: 25/01/2025 | H32: 45682 | I32: 0.37777778 | J32: P01001706421 | M32: -120 | Y32: =E32+L32+M32+N32+O32+P32+Q32+R32+S32+T32+U32+V32+W32+X32 -> 0 | AA32: NO | AB32: MULTA VIGNETTA AUSTRIA | AC32: 451ba90f | AD32: 5247b9b8 | AF32: HACIENDA
B33: VENCIDA | C33: EMPRESA | D33: EX030XG | E33: 120 | F33: 04/02/2025 | G33: 04/02/2025 | H33: 45692 | I33: 0.21736111 | J33: P01001881984 | N33: -120 | Y33: =E33+L33+M33+N33+O33+P33+Q33+R33+S33+T33+U33+V33+W33+X33 -> 0 | Z33: DA ADDEBITARE | AA33: NO | AB33: MULTA VIGNETTA AUSTRIA | AC33: 451ba90f | AD33: 7863629e | AF33: HACIENDA
A34: MULTAS_Files_/9f87521f.ARCHIVO.154642.pdf | B34: VENCIDA | C34: DOMINICK LEON | D34: GB502TP | E34: 184 | F34: 26/02/2025 | G34: 26/02/2025 | H34: 45714 | I34: 0.069444444 | J34: 250085806 013 3 | P34: -184 | Y34: =E34+L34+M34+N34+O34+P34+Q34+R34+S34+T34+U34+V34+W34+X34 -> 0 | Z34: SCADUTA AD APRILE | AA34: NO | AB34: MULTA VELOCITA' | AC34: G009 | AD34: 9f87521f | AF34: LAVORATORE
A35: MULTAS_Files_/3bc0fcc6.ARCHIVO.155518.pdf | B35: VENCIDA | C35: EMPRESA | D35: GB502TP | E35: 120 | F35: 04/08/2025 | G35: 11/08/2025 | H35: 45707 | I35: 0.71805556 | J35: P01002225520 | Y35: =E35+L35+M35+N35+O35+P35+Q35+R35+S35+T35+U35+V35+W35+X35 -> 120 | Z35: SCADUTA AD APRILE + AVVISO DI ANNULLAMENTO MULTA PRECEDENTE | AA35: NO | AB35: MULTA VIGNETTA AUSTRIA | AC35: 451ba90f | AD35: 3bc0fcc6 | AF35: HACIENDA
A36: MULTAS_Files_/8063beba.ARCHIVO.160812.pdf | B36: VENCIDA | C36: EMPRESA | D36: FN505ZH | E36: 101 | H36: 45630 | I36: 0.41180556 | J36: 03304008/2024/1/1/1 | Y36: =E36+L36+M36+N36+O36+P36+Q36+R36+S36+T36+U36+V36+W36+X36 -> 101 | Z36: SCADEVA A MARZO | AA36: NO | AB36: MULTA AREA C | AC36: 451ba90f | AD36: 8063beba
A37: MULTAS_Files_/89d3efcf.ARCHIVO.162037.pdf | B37: VENCIDA | C37: EMPRESA | D37: GE027AM | E37: 101 | F37: 29/11/2024 | G37: 29/11/2024 | H37: 45625 | I37: 0.31875 | J37: 03299795/2024/1/1/1 | Y37: =E37+L37+M37+N37+O37+P37+Q37+R37+S37+T37+U37+V37+W37+X37 -> 101 | Z37: SCADEVA A MARZO | AA37: NO | AB37: MULTA AREA C | AC37: 451ba90f | AD37: 89d3efcf | AF37: HACIENDA
A38: MULTAS_Files_/48142490.ARCHIVO.162756.pdf | B38: VENCIDA | C38: EMPRESA | D38: GE027AM | E38: 101 | H38: 45989 | I38: 0.32569444 | J38: 03298859/2024/1/1/1 | Y38: =E38+L38+M38+N38+O38+P38+Q38+R38+S38+T38+U38+V38+W38+X38 -> 101 | Z38: SCADEVA A MARZO | AA38: NO | AB38: MULTA AREA C | AC38: 451ba90f | AD38: 48142490
A39: MULTAS_Files_/eec31369.ARCHIVO.163111.pdf | B39: VENCIDA | C39: EMPRESA | D39: GE027AM | E39: 101 | F39: 09/01/2025 | G39: 09/01/2025 | H39: 45666 | I39: 0.31666667 | J39: 00096633/2025/1/1/1 | Y39: =E39+L39+M39+N39+O39+P39+Q39+R39+S39+T39+U39+V39+W39+X39 -> 101 | Z39: RIDOTTA: 76,89 | AA39: NO | AB39: MULTA AREA C | AC39: 451ba90f | AD39: eec31369 | AF39: HACIENDA
A40: MULTAS_Files_/4cbacd48.ARCHIVO.163818.pdf | B40: VENCIDA | C40: EDUARDO SANTA CRUZ | D40: EG403NT | E40: 101 | F40: 14/01/2025 | G40: 14/01/2025 | H40: 45671 | I40: 0.28958333 | J40: 00076974/2025/1/1/1 | Q40: -101 | Y40: =E40+L40+M40+N40+O40+P40+Q40+R40+S40+T40+U40+V40+W40+X40 -> 0 | Z40: RIDOTTA: 76,89 | AA40: NO | AB40: MULTA CORSIA RISERVATA | AC40: G022 | AD40: 4cbacd48 | AF40: LAVORATORE
A41: MULTAS_Files_/69c26cac.ARCHIVO.164927.pdf | B41: PAGADO | C41: EDUARDO SANTA CRUZ | D41: CV626GV | E41: 62 | H41: 45712 | I41: 0.60208333 | J41: V/303224A/2025 | N41: -62 | Y41: =E41+L41+M41+N41+O41+P41+Q41+R41+S41+T41+U41+V41+W41+X41 -> 0 | AA41: NO | AB41: MULTA VELOCITA' | AC41: G022 | AD41: 69c26cac | AF41: LAVORATORE
A42: MULTAS_Files_/1c228947.ARCHIVO.165634.pdf | B42: VENCIDA | C42: JUAN CARLOS | D42: ER643VY | E42: 191 | F42: 11/02/2025 | G42: 11/02/2025 | H42: 45699 | I42: 0.48888889 | J42: V/607S/2025 | R42: -191 | Y42: =E42+L42+M42+N42+O42+P42+Q42+R42+S42+T42+U42+V42+W42+X42 -> 0 | Z42: RIDOTTO: 128,10 (ERA 180, SULL'APP SI E' ALZATA 191, SI PUO ANCORA PAGARE IN APP) | AA42: SI | AB42: MULTA VELOCITA' | AC42: G025 | AD42: 1c228947 | AF42: LAVORATORE
A43: MULTAS_Files_/babdd426.ARCHIVO.170753.pdf | B43: PAGADO | C43: EDUARDO SANTA CRUZ | D43: CV627GV | E43: 5117 | H43: 45717 | I43: 0.66666667 | J43: 010511/V/25 | P43: -317 | Q43: -100 | Y43: =E43+L43+M43+N43+O43+P43+Q43+R43+S43+T43+U43+V43+W43+X43 -> 4700 | AA43: NO | AB43: MULTA CIRCOLO SENZA PATENTE | AC43: G022 | AD43: babdd426 | AF43: LAVORATORE
A44: MULTAS_Files_/3c60dec3.ARCHIVO.091610.pdf | B44: VENCIDA | C44: ALONSO TAMARA | D44: FM153VE | E44: 102 | F44: 07/03/2025 | G44: 07/03/2025 | H44: 45723 | I44: 0.37222222 | J44: 00461679/2025/1/1/1 | S44: -52 | V44: -50 | Y44: =E44+L44+M44+N44+O44+P44+Q44+R44+S44+T44+U44+V44+W44+X44 -> 0 | AB44: ZTL | AC44: G014 | AD44: 3c60dec3
A45: MULTAS_Files_/26dd3499.ARCHIVO.103610.8.pdf | B45: VENCIDA | C45: NATALIA PLUA | D45: EX030XG | E45: 93.5 | F45: Y | G45: PENDIENTE | H45: 45699 | I45: 0.50763889 | J45: 23.7524808.8 | Y45: =E45+L45+M45+N45+O45+P45+Q45+R45+S45+T45+U45+V45+W45+X45 -> 93.5 | Z45: ARRIVATO SECONDO AVVISO: 93,50€ | AA45: NO | AB45: MULTA VELOCITA' | AC45: G004 | AD45: 26dd3499 | AF45: 11/02/2025
A46: MULTAS_Files_/acbb504d.ARCHIVO.111456.pdf | B46: VENCIDA | C46: EMPRESA | D46: ET420XR | E46: 102 | F46: 30/01/2025 | G46: 30/01/2025 | H46: 45687 | I46: 0.74791667 | J46: 00231965/2025/1/1/1 | Y46: =E46+L46+M46+N46+O46+P46+Q46+R46+S46+T46+U46+V46+W46+X46 -> 102 | Z46: RENZO (ME DIJO CARLITOS QUE YA LO HABIA CONVERSADO CON EMERSON Y LA MULTA RESULTA DE EL) | AA46: NO | AB46: MULTA AREA B | AC46: 451ba90f | AD46: acbb504d | AF46: HACIENDA
A47: MULTAS_Files_/b224a92c.ARCHIVO.112849.pdf | B47: VENCIDA | C47: ROMARIO QUISPE | D47: DZ923BS | E47: 102 | F47: 04/03/2025 | G47: 04/03/2025 | H47: 45720 | I47: 0.54513889 | J47: 00448615/2025/1/1/1 | Q47: -102 | Y47: =E47+L47+M47+N47+O47+P47+Q47+R47+S47+T47+U47+V47+W47+X47 -> 0 | AA47: NO | AB47: MULTA AREA B | AC47: G011 | AD47: b224a92c | AF47: LAVORATORE
A48: MULTAS_Files_/4df0d064.ARCHIVO.113637.pdf | B48: VENCIDA | C48: JURGEN PALIZA | D48: FY032BD | E48: 250 | F48: 14/02/2025 | G48: 14/02/2025 | H48: 45702 | I48: 0.24236111 | J48: VI01267408 | U48: -150 | Y48: =E48+L48+M48+N48+O48+P48+Q48+R48+S48+T48+U48+V48+W48+X48 -> 100 | Z48: DA ADDEBITARE | AA48: SI | AB48: MULTA VELOCITA' | AC48: G017 | AD48: 4df0d064
A49: MULTAS_Files_/7c33a998.ARCHIVO.122401.pdf | B49: VENCIDA | C49: DIEGO MOLINA | D49: EM504JT | E49: 76 | F49: 20/02/2025 | G49: 20/02/2025 | H49: 45708 | I49: 0.22361111 | J49: VI01272577 | Q49: -76 | Y49: =E49+L49+M49+N49+O49+P49+Q49+R49+S49+T49+U49+V49+W49+X49 -> 0 | Z49: RIDOTTA: 59,70 | AA49: NO | AB49: MULTA VELOCITA' | AC49: G020 | AD49: 7c33a998 | AF49: LAVORATORE
A50: MULTAS_Files_/48fcc95c.ARCHIVO.123128.pdf | B50: VENCIDA | C50: JURGEN PALIZA | D50: FY032BD | E50: 76 | F50: 15/02/2025 | G50: 15/02/2025 | H50: 45703 | I50: 0.24236111 | J50: VI01268171 | P50: -76 | Y50: =E50+L50+M50+N50+O50+P50+Q50+R50+S50+T50+U50+V50+W50+X50 -> 0 | Z50: RIDOTTA: 59,70 | AA50: NO | AB50: MULTA VELOCITA' | AC50: G017 | AD50: 48fcc95c | AF50: LAVORATORE
A51: MULTAS_Files_/ca2ba89d.ARCHIVO.124953.pdf | B51: VENCIDA | C51: ALONSO TAMARA | D51: FM153VE | E51: 102 | F51: 03/03/2025 | G51: 03/03/2025 | H51: 45719 | I51: 0.37638889 | J51: 00394297/2025/1/1/1 | Q51: -102 | Y51: =E51+L51+M51+N51+O51+P51+Q51+R51+S51+T51+U51+V51+W51+X51 -> 0 | Z51: RIDOTTA: 77,68 / POSTFESTIVO / EL AUTISTA ME DICE QUE NO SABIA | AA51: NO | AB51: ZTL | AC51: G014 | AD51: ca2ba89d | AF51: LAVORATORE
A52: MULTAS_Files_/bf5dd6e0.ARCHIVO.155039.pdf | B52: VENCIDA | C52: NATALIA PLUA | D52: EX030XG | E52: 61 | F52: 03/03/2025 | G52: 03/03/2025 | H52: 45719 | I52: 0.51180556 | J52: 00377230/2025/1/1/1 | Y52: =E52+L52+M52+N52+O52+P52+Q52+R52+S52+T52+U52+V52+W52+X52 -> 61 | Z52: RIDOTTA: 48,98 | AA52: NO | AB52: MULTA SOSTA SENZA ORARIO | AC52: G004 | AD52: bf5dd6e0 | AF52: LAVORATORE
A53: MULTAS_Files_/99b75f2e.ARCHIVO.160015.pdf | B53: VENCIDA | C53: EDUARDO SANTA CRUZ | D53: CV627GV | E53: 102 | F53: 14/02/2025 | G53: 14/02/2025 | H53: 45702 | I53: 0.28125 | J53: 00360526/2025/1/1/1 | Q53: -102 | Y53: =E53+L53+M53+N53+O53+P53+Q53+R53+S53+T53+U53+V53+W53+X53 -> 0 | Z53: RIDOTTA: 77,68 | AA53: NO | AB53: MULTA CORSIA RISERVATA | AC53: G022 | AD53: 99b75f2e | AF53: LAVORATORE
A54: MULTAS_Files_/55622ec4.ARCHIVO.161652.pdf | B54: VENCIDA | C54: ROMARIO QUISPE | D54: DZ923BS | E54: 245 | F54: 05/03/2025 | G54: 05/03/2025 | H54: 45721 | I54: 0.28611111 | J54: 208746/2025/T | P54: -245 | Y54: =E54+L54+M54+N54+O54+P54+Q54+R54+S54+T54+U54+V54+W54+X54 -> 0 | Z54: RIDOTTA: 176,47 | AA54: SI | AB54: MULTA VELOCITA' | AC54: G011 | AD54: 55622ec4 | AF54: LAVORATORE
A55: MULTAS_Files_/e8484e86.ARCHIVO.133758.pdf | B55: PAGADO | C55: JUAN CARLOS | D55: GE027AM | E55: 77 | H55: 45676 | I55: 0.88541667 | J55: V/1968R/2025 | Q55: -77 | Y55: =E55+L55+M55+N55+O55+P55+Q55+R55+S55+T55+U55+V55+W55+X55 -> 0 | AA55: NO | AB55: ZTL | AC55: G025 | AD55: e8484e86 | AF55: LAVORATORE
A56: MULTAS_Files_/1755fddc.ARCHIVO.134734.pdf | B56: VENCIDA | C56: EMPRESA | D56: FM153VE | E56: 59 | F56: 23/01/2025 | G56: 23/01/2025 | H56: 45680 | I56: 0.41875 | J56: 004632/D/25 | Y56: =E56+L56+M56+N56+O56+P56+Q56+R56+S56+T56+U56+V56+W56+X56 -> 59 | Z56: RIDOTTA: 46,96 (SI PUò PAGARE ANCORA IN APP) | AA56: NO | AB56: DIVIETO PULIZIA STRADALE | AC56: 451ba90f | AD56: 1755fddc | AF56: HACIENDA
A57: MULTAS_Files_/93583908.ARCHIVO.140432.pdf | B57: VENCIDA | C57: JUAN CARLOS | D57: ER643VY | E57: 58 | F57: 18/02/2025 | G57: 18/02/2025 | H57: 45706 | I57: 0.46111111 | J57: V/714S/2025 | Q57: -58 | Y57: =E57+L57+M57+N57+O57+P57+Q57+R57+S57+T57+U57+V57+W57+X57 -> 0 | Z57: RIDOTTA: 36,40 (SI PUO ANCORA PAGARE IN APP) | AA57: NO | AB57: MULTA VELOCITA' | AC57: G025 | AD57: 93583908 | AF57: LAVORATORE
B58: VENCIDA | C58: EMERSON GAMONAL | D58: EG403NT | E58: 56 | F58: 28/03/2025 | G58: 28/03/2025 | H58: 45744 | I58: 0.49236111 | J58: 3368AX/25 | Y58: =E58+L58+M58+N58+O58+P58+Q58+R58+S58+T58+U58+V58+W58+X58 -> 56 | Z58: RIDOTTA: 32,90 (ERA 45,50, ORA 56,15 SI PUO PAGARE ANCORA IN APP) | AA58: NO | AB58: MULTA VELOCITA' | AC58: G002 | AD58: 039f7837
A59: MULTAS_Files_/61e2fe5c.ARCHIVO.153940.pdf | B59: VENCIDA | C59: SANTHA NEELAPPAGE | D59: EG403NT | E59: 187 | F59: 02/04/2025 | G59: 02/04/2025 | H59: 45749 | I59: 0.43055556 | J59: 3401AX/25 | Y59: =E59+L59+M59+N59+O59+P59+Q59+R59+S59+T59+U59+V59+W59+X59 -> 187 | Z59: RIDOTTA: 124,60 (ERA 176,50. ORA 187 SI PUO ANCORA PAGARE IN APP) | AA59: SI | AB59: MULTA VELOCITA' | AC59: G019 | AD59: 61e2fe5c
A60: MULTAS_Files_/f821e82a.ARCHIVO.154213.pdf | B60: VENCIDA | C60: EMPRESA | D60: EM504JT | E60: 185 | F60: 03/02/2025 | G60: 03/02/2025 | H60: 45691 | I60: 0.64861111 | J60: V/10752/2025 | Y60: =E60+L60+M60+N60+O60+P60+Q60+R60+S60+T60+U60+V60+W60+X60 -> 185 | Z60: RIDOTTA: 123,10 (ERA 175. ORA 185,49 SI PUO ANCORA PAGARE IN APP) | AA60: NO | AB60: MULTA SENZA REVISIONE | AC60: 451ba90f | AD60: f821e82a | AF60: HACIENDA
A61: MULTAS_Files_/fcfa5226.ARCHIVO.155212.pdf | B61: VENCIDA | C61: ALONSO TAMARA | D61: FM153VE | E61: 44 | F61: 28/02/2025 | G61: 28/02/2025 | H61: 45716 | I61: 0.39791667 | J61: 010103/A/25 | Q61: -44 | Y61: =E61+L61+M61+N61+O61+P61+Q61+R61+S61+T61+U61+V61+W61+X61 -> 0 | Z61: DUE MESI: 56 (SI PUO ANCORA PAGARE IN APP) | AA61: NO | AB61: DIVIETO PULIZIA STRADALE | AC61: G014 | AD61: fcfa5226 | AF61: LAVORATORE
A62: MULTAS_Files_/c5782df7.ARCHIVO.160811.pdf | B62: VENCIDA | C62: SANTHA NEELAPPAGE | D62: EG403NT | E62: 49 | F62: 25/03/2025 | G62: 25/03/2025 | H62: 45741 | I62: 0.45277778 | J62: V/1218S/2025 | Y62: =E62+L62+M62+N62+O62+P62+Q62+R62+S62+T62+U62+V62+W62+X62 -> 49 | Z62: RIDOTTA: 36,40 (SI PUO ANCORA PAGARE IN APP 49,00) | AA62: NO | AB62: MULTA VELOCITA' | AC62: G019 | AD62: c5782df7 | AF62: LAVORATORE
A63: MULTAS_Files_/70c909f6.ARCHIVO.161127.pdf | B63: VENCIDA | C63: SANTHA NEELAPPAGE | D63: EG403NT | E63: 180 | H63: 45803 | I63: 0.45416667 | J63: V/1234S/2025 | Y63: =E63+L63+M63+N63+O63+P63+Q63+R63+S63+T63+U63+V63+W63+X63 -> 180 | Z63: RIDOTTA: 128,10 (SI PUO ANCORA PAGARE 180 IN APP) | AA63: SI | AB63: MULTA VELOCITA' | AC63: G019 | AD63: 70c909f6
A64: MULTAS_Files_/405c0e42.ARCHIVO.161647.pdf | B64: VENCIDA | C64: ALONSO TAMARA | D64: EZ009PN | E64: 51 | G64: DESCONTADO | H64: 45771 | I64: 0.43888889 | J64: 4982/2025/Z | Q64: -51 | Y64: =E64+L64+M64+N64+O64+P64+Q64+R64+S64+T64+U64+V64+W64+X64 -> 0 | Z64: RIDOTTA: 38,96 (ORA 51,56. SI PUO ANCORA PAGARE IN APP) | AA64: NO | AB64: MULTA VELOCITA' | AC64: G014 | AD64: 405c0e42
A65: MULTAS_Files_/e75db61b.ARCHIVO.093053.pdf | B65: PAGADO | C65: NATALIA PLUA | D65: GT894FF | E65: 50 | H65: 45721 | J65: BHMU/614250013792/2025 | Y65: =E65+L65+M65+N65+O65+P65+Q65+R65+S65+T65+U65+V65+W65+X65 -> 50 | Z65: PAGATO CON CARTA PERSONALE | AA65: NO | AB65: MULTA VELOCITA' | AC65: G004 | AD65: e75db61b | AE65: MULTAS_Files_/e75db61b.RECIBO DE PAGO.093053.pdf | AF65: LAVORATORE
A66: MULTAS_Files_/093347bb.ARCHIVO.141608.pdf | B66: PAGADO | C66: SANTHA NEELAPPAGE | D66: EG403NT | E66: 62 | F66: 03/03/2025 | G66: 03/03/2025 | H66: 45719 | I66: 0.30347222 | J66: VI01283654 | Y66: =E66+L66+M66+N66+O66+P66+Q66+R66+S66+T66+U66+V66+W66+X66 -> 62 | Z66: RIDOTTA: 49,90 | AA66: NO | AB66: MULTA VELOCITA' | AC66: G019 | AD66: 093347bb | AF66: 18/11/2025 14:00:00
A67: MULTAS_Files_/4fff35c8.ARCHIVO.125706.pdf | B67: PAGADO | C67: EMPRESA | D67: GE027AM | E67: 123 | H67: 45730 | I67: 0.63611111 | J67: V/20344/2025 | Y67: =E67+L67+M67+N67+O67+P67+Q67+R67+S67+T67+U67+V67+W67+X67 -> 123 | Z67: RIDOTTA: 123,10 (POI 175) / DA ADDEBITARE | AA67: NO | AB67: MULTA SENZA REVISIONE | AC67: 451ba90f | AD67: 4fff35c8 | AE67: MULTAS_Files_/4fff35c8.RECIBO DE PAGO.090658.pdf | AF67: HACIENDA
A68: MULTAS_Files_/9ff32106.ARCHIVO.151700.pdf | B68: PAGADO | C68: ALONSO TAMARA | D68: EZ009PN | E68: 29 | H68: 45806 | I68: 0.41944444 | J68: 002760/A/25 | S68: -29 | Y68: =E68+L68+M68+N68+O68+P68+Q68+R68+S68+T68+U68+V68+W68+X68 -> 0 | Z68: DA ADDEBBITARE | AA68: NO | AB68: DIVIETO PULIZIA STRADALE | AC68: G014 | AD68: 9ff32106 | AF68: LAVORATORE
A69: MULTAS_Files_/f31c2126.ARCHIVO.142256.pdf | B69: PAGADO | C69: FELIPE BUSTAMANTE | D69: FY593SE | E69: 66 | H69: 45794 | I69: 0.73055556 | J69: V/80864Z/2025 | R69: -66 | Y69: =E69+L69+M69+N69+O69+P69+Q69+R69+S69+T69+U69+V69+W69+X69 -> 0 | AA69: NO | AB69: ZTL | AC69: G031 | AD69: f31c2126 | AE69: Unable to load image data. The selected image could not be found.#filename=V%3A80864Z%3A2025.jpeg
A70: MULTAS_Files_/d0136400.ARCHIVO.132850.pdf | B70: PAGADO | C70: EMPRESA | D70: FM342HY | E70: 82 | H70: 45762 | I70: 0.69583333 | J70: 00801985/2025/1/1/1 | Y70: =E70+L70+M70+N70+O70+P70+Q70+R70+S70+T70+U70+V70+W70+X70 -> 82 | Z70: SENZA RICEVUTA | AA70: NO | AB70: MULTA AREA C | AC70: 451ba90f | AD70: d0136400 | AF70: HACIENDA
A71: MULTAS_Files_/03a062c9.ARCHIVO.133147.pdf | B71: PAGADO | C71: EMPRESA | D71: FM342HY | E71: 82 | H71: 45764 | I71: 0.57430556 | J71: 00803606/2025/1/1/1 | Y71: =E71+L71+M71+N71+O71+P71+Q71+R71+S71+T71+U71+V71+W71+X71 -> 82 | Z71: SENZA RICEVUTA / PAGATA DA CARLOS | AA71: NO | AB71: MULTA AREA C | AC71: 451ba90f | AD71: 03a062c9 | AF71: HACIENDA
A72: MULTAS_Files_/0147f6e6.ARCHIVO.133455.pdf | B72: PAGADO | C72: JURGEN PALIZA | D72: FY032BD | E72: 77 | H72: 45751 | I72: 0.66805556 | J72: 00741801/2025/1/1/1 | R72: -77 | Y72: =E72+L72+M72+N72+O72+P72+Q72+R72+S72+T72+U72+V72+W72+X72 -> 0 | Z72: SENZA RICEVUTA / PAGATO DA CARLOS | AA72: NO | AB72: MULTA CORSIA RISERVATA | AC72: G017 | AD72: 0147f6e6 | AF72: LAVORATORE
A73: MULTAS_Files_/8dd7eb39.ARCHIVO.134415.pdf | B73: PAGADO | C73: ROMARIO QUISPE | D73: CT413YE | E73: 105 | H73: 45799 | I73: 0.59513889 | J73: V/51222328T/2025 | S73: -105 | Y73: =E73+L73+M73+N73+O73+P73+Q73+R73+S73+T73+U73+V73+W73+X73 -> 0 | AA73: NO | AB73: MULTA TARIFFA PARCHEGGIO | AC73: G011 | AD73: 8dd7eb39 | AE73: MULTAS_Images/8dd7eb39.RECIBO DE PAGO.134415.jpg | AF73: LAVORATORE
A74: MULTAS_Files_/a25d2bad.ARCHIVO.091952.pdf | B74: PAGADO | C74: SANTHA NEELAPPAGE | D74: EG403NT | E74: 70 | H74: 45742 | I74: 0.41805556 | J74: 1760868039 | Y74: =E74+L74+M74+N74+O74+P74+Q74+R74+S74+T74+U74+V74+W74+X74 -> 70 | Z74: PAGAMENTO EFFETTUATO NEI 5 GIORNI | AA74: SI | AB74: MULTA CASELLO AUTOSTRADALE | AC74: G019 | AD74: a25d2bad | AE74: MULTAS_Files_/a25d2bad.RECIBO DE PAGO.091952.pdf | AF74: LAVORATORE
A75: MULTAS_Files_/6cd1b73f.ARCHIVO.093324.pdf | B75: PAGADO | C75: SANTHA NEELAPPAGE | D75: EG403NT | E75: 70 | H75: 45742 | I75: 0.47152778 | J75: 1760868040 | Y75: =E75+L75+M75+N75+O75+P75+Q75+R75+S75+T75+U75+V75+W75+X75 -> 70 | Z75: MULTA PAGATA NEI 5 GIORNI | AA75: SI | AB75: MULTA CASELLO AUTOSTRADALE | AC75: G019 | AD75: 6cd1b73f | AE75: MULTAS_Files_/6cd1b73f.RECIBO DE PAGO.093324.pdf | AF75: LAVORATORE
A76: MULTAS_Files_/92155126.ARCHIVO.155521.pdf | B76: PAGADO | C76: JURGEN PALIZA | D76: FY032BD | E76: 213 | H76: 45643 | J76: 1260001108132 | S76: -150 | T76: -63 | Y76: =E76+L76+M76+N76+O76+P76+Q76+R76+S76+T76+U76+V76+W76+X76 -> 0 | Z76: VERBALE: 176/0830746. MANCATO DATI CONDUCENTE | AA76: NO | AB76: MULTA MANCATO DATI CONDUCENTE | AC76: G017 | AD76: 92155126 | AE76: MULTAS_Files_/92155126.RECIBO DE PAGO.155521.pdf
A77: MULTAS_Files_/59ade102.ARCHIVO.161310.pdf | B77: PAGADO | C77: JURGEN PALIZA | D77: ER643VY | E77: 291 | J77: 000096/D/25 | Y77: =E77+L77+M77+N77+O77+P77+Q77+R77+S77+T77+U77+V77+W77+X77 -> 291 | Z77: VERBALE: 000593/S/24 del 22/11/24 | AA77: NO | AB77: MULTA MANCATO DATI CONDUCENTE | AC77: G017 | AD77: 59ade102 | AE77: MULTAS_Files_/59ade102.RECIBO DE PAGO.161310.pdf | AF77: LAVORATORE
A78: MULTAS_Files_/adcb67a4.ARCHIVO.162004.pdf | B78: PAGADO | C78: CHRISTIAN RODRIGUEZ | D78: GE027AM | E78: 50 | H78: 45764 | I78: 0.82569444 | J78: VI01319747 | R78: -50 | Y78: =E78+L78+M78+N78+O78+P78+Q78+R78+S78+T78+U78+V78+W78+X78 -> 0 | AA78: NO | AB78: MULTA VELOCITA' | AC78: G026 | AD78: adcb67a4 | AE78: MULTAS_Files_/adcb67a4.RECIBO DE PAGO.162004.pdf | AF78: LAVORATORE
A79: MULTAS_Files_/c0a7c0a7.ARCHIVO.162713.pdf | B79: PAGADO | C79: JEAN ALVARADO | D79: FN505ZH | E79: 71 | H79: 45756 | I79: 0.45625 | J79: 1760872997 | S79: -71 | Y79: =E79+L79+M79+N79+O79+P79+Q79+R79+S79+T79+U79+V79+W79+X79 -> 0 | AA79: SI | AB79: MULTA CASELLO AUTOSTRADALE | AC79: G028 | AD79: c0a7c0a7 | AE79: MULTAS_Files_/c0a7c0a7.RECIBO DE PAGO.162713.pdf | AF79: LAVORATORE
A80: MULTAS_Files_/4ed28097.ARCHIVO.164024.pdf | B80: PAGADO | C80: JURGEN PALIZA | D80: FY032BD | E80: 78 | H80: 45779 | I80: 0.66041667 | J80: 00909827/2025/1/1/1 | R80: -78 | Y80: =E80+L80+M80+N80+O80+P80+Q80+R80+S80+T80+U80+V80+W80+X80 -> 0 | AA80: NO | AB80: MULTA CORSIA RISERVATA | AC80: G017 | AD80: 4ed28097 | AE80: MULTAS_Files_/4ed28097.RECIBO DE PAGO.164451.pdf | AF80: LAVORATORE
A81: MULTAS_Files_/7ff23429.ARCHIVO.163251.pdf | B81: PAGADO | C81: ROMARIO QUISPE | D81: EZ009PN | E81: 71 | H81: 45765 | I81: 0.50902778 | J81: 1760876305 | T81: -71 | Y81: =E81+L81+M81+N81+O81+P81+Q81+R81+S81+T81+U81+V81+W81+X81 -> 0 | AA81: SI | AB81: MULTA CASELLO AUTOSTRADALE | AC81: G011 | AD81: 7ff23429 | AE81: MULTAS_Files_/7ff23429.RECIBO DE PAGO.163251.pdf | AF81: LAVORATORE
A82: MULTAS_Files_/35c0df58.ARCHIVO.145526.52.pdf | B82: PAGADO | C82: EMPRESA | D82: EG403NT | E82: 78 | H82: 45736 | I82: 0.65486111 | J82: 00581845/2025/1/1/1 | Y82: =E82+L82+M82+N82+O82+P82+Q82+R82+S82+T82+U82+V82+W82+X82 -> 78 | AA82: NO | AB82: MULTA AREA C | AC82: 451ba90f | AD82: 35c0df58 | AE82: MULTAS_Files_/35c0df58.RECIBO DE PAGO.145526.pdf | AF82: HACIENDA
A83: MULTAS_Files_/96ee1f54.ARCHIVO.130148.59.pdf | B83: VENCIDA | C83: DOMINICK LEON | D83: GB502TP | E83: 184 | F83: 26/02/2025 | G83: 26/02/2025 | H83: 45714 | I83: 0.069444444 | J83: 250085806 013 3 | Y83: =E83+L83+M83+N83+O83+P83+Q83+R83+S83+T83+U83+V83+W83+X83 -> 184 | Z83: ARRIVATA INTORNO 05/GIUGNO | AA83: NO | AB83: MULTA VELOCITA' | AC83: G009 | AD83: 96ee1f54 | AF83: LAVORATORE
A84: MULTAS_Files_/3e353bfc.ARCHIVO.153848.pdf | B84: PAGADO | C84: CARLOS GAMONAL | D84: F010 | E84: 350 | H84: 45692 | I84: 0.21736111 | J84: IL/309250061897 | Y84: =E84+L84+M84+N84+O84+P84+Q84+R84+S84+T84+U84+V84+W84+X84 -> 350 | Z84: CONTROLLARE: PASSATE LE DUE SETTIMANE | AA84: NO | AB84: MULTA AUSTRIA PEDAGGIO | AC84: G001 | AD84: 3e353bfc | AE84: MULTAS_Files_/3e353bfc.RECIBO DE PAGO.153848.pdf | AF84: LAVORATORE
A85: MULTAS_Files_/a8478241.ARCHIVO.154521.44.pdf | B85: VENCIDA | C85: MARTÍN RODRÍGUEZ | D85: F010 | E85: 120 | F85: 01/01/2025 | G85: DESCONTADO | H85: 45850 | I85: 0.69791667 | J85: P01003252788 | K85: 45789 | Q85: -120 | Y85: =E85+L85+M85+N85+O85+P85+Q85+R85+S85+T85+U85+V85+W85+X85 -> 0 | Z85: ARRIVATA: 12 MAGGIO 2025 | AA85: NO | AB85: MULTA AUSTRIA PEDAGGIO | AC85: G006 | AD85: a8478241 | AF85: 12/06/2025 12:00:00
B86: VENCIDA | C86: DOMINICK LEON | D86: F014 | E86: 184 | F86: 26/02/2025 | G86: 26/02/2025 | H86: 45714 | I86: 0.069444444 | J86: 2500858060133 | Y86: =E86+L86+M86+N86+O86+P86+Q86+R86+S86+T86+U86+V86+W86+X86 -> 184 | Z86: ARRIVATA INTORNO A GIUGNO (NATALIA) | AA86: NO | AB86: MULTA VELOCITA AUSTRIA | AC86: G009 | AD86: 9e72570d | AF86: LAVORATORE
A87: MULTAS_Files_/3af18914.ARCHIVO.165248.51.pdf | B87: PAGADO | C87: EMPRESA | D87: F011 | E87: 190 | H87: 45649 | J87: 1144881853 | Y87: =E87+L87+M87+N87+O87+P87+Q87+R87+S87+T87+U87+V87+W87+X87 -> 190 | Z87: AVVISO BONARIO GENOVA | AA87: NO | AB87: MULTA AVVISO BONARIO | AC87: 451ba90f | AD87: 3af18914 | AE87: MULTAS_Files_/3af18914.RECIBO DE PAGO.165248.pdf | AF87: HACIENDA
A88: MULTAS_Files_/e6ec1820.ARCHIVO.083115.28.pdf | B88: Vencido Julio 2025 | D88: F002 | E88: 593.08 | F88: Y | G88: HA DESCONTAR | H88: 45903 | J88: 1260001109051 | K88: 45841 | Y88: =E88+L88+M88+N88+O88+P88+Q88+R88+S88+T88+U88+V88+W88+X88 -> 593.08 | Z88: 03/07 ENTRO 03/09/25 (NO SE SABE DE QUIEN ES) | AA88: N | AB88: MULTA MANCATO DATI CONDUCENTE | AC88: 451ba90f | AD88: e6ec1820 | AF88: 03/08/2025 | AG88: 7. Julio
A89: MULTAS_Files_/12093039.ARCHIVO.090652.03.pdf | B89: Vencido Julio 2025 | C89: ROMARIO QUISPE | D89: F025 | E89: 102 | F89: Y | G89: HA DESCONTAR | H89: 45903 | I89: 0.38333333 | J89: 01035461/2025/1/1/1 | K89: 45841 | W89: -102 | Y89: =E89+L89+M89+N89+O89+P89+Q89+R89+S89+T89+U89+V89+W89+X89 -> 0 | Z89: Dice que por acuerdo como Empresa, las multas con tiempo de fin de Julio hacia atrás se haría cargo del pago la empresa misma y que está de acuerdo que le vayan descontando poco a poco cada mes de pagos | AA89: N | AB89: MULTA ZTL | AC89: G011 | AD89: 12093039 | AF89: 03/08/2025 | AG89: 7. Julio
A90: MULTAS_Files_/32d554a8.ARCHIVO.182021.pdf | B90: Vencido Septiembre 2025 | C90: JUAN CARLOS | D90: F026 | E90: 105 | F90: Y | G90: DESCONTADO | H90: 45931 | I90: Y | J90: 1844606 | K90: 45901 | S90: -105 | Y90: =E90+L90+M90+N90+O90+P90+Q90+R90+S90+T90+U90+V90+W90+X90 -> 0 | Z90: YA SE LE DESCONTÓ, ES DECIR QUE LA EMPRESA DEBE PAGARLO | Esta multa ya la tenía, revisar el PDF, ya son 3 veces que la envían. En las 3, están cobrando lo mismo. INFRACCIÓN: Jueves, 3 de julio de 2025, a las 21:47 horas | AA90: N | AB90: MULTA VELOCITA' GERMANIA | AC90: G025 | AD90: 32d554a8 | AF90: 01/10/2025 00:00:00 | AG90: 9. Septiembre
A91: MULTAS_Files_/a5f1c1e9.ARCHIVO.105846.44.pdf | B91: PAGADO | C91: JEAN ALVARADO | D91: F017 | E91: 71 | F91: 06/08/2025 | G91: 06/08/2025 | H91: 45765 | I91: 0.48263889 | J91: 1760876304 | S91: -71 | Y91: =E91+L91+M91+N91+O91+P91+Q91+R91+S91+T91+U91+V91+W91+X91 -> 0 | Z91: 97,08 -> 1/07 DA PAGARE ENTRO 01/09/25 | AA91: SI | AB91: MULTA CASELLO AUTOSTRADALE | AC91: G028 | AD91: a5f1c1e9 | AE91: MULTAS_Files_/a5f1c1e9.RECIBO DE PAGO.104747.pdf | AF91: LAVORATORE
A92: MULTAS_Files_/890444ad.ARCHIVO.163644.35.pdf | B92: PAGADO | C92: EDUARDO SANTA CRUZ | D92: F002 | F92: Y | G92: YA PAGÓ | H92: 45910 | I92: Y | J92: 1760878034 | K92: 45848 | Y92: =E92+L92+M92+N92+O92+P92+Q92+R92+S92+T92+U92+V92+W92+X92 -> 0 | Z92: 10/07 ENTRO 09/09 / PAGATO NATALIA | AA92: N | AB92: MULTA CASELLO AUTOSTRADALE | AC92: 451ba90f | AD92: 890444ad | AE92: MULTAS_Files_/890444ad.RECIBO DE PAGO.193635.TO PUBBLICA SICURE_02-273787626 2.pdf | AF92: 10/08/2025 | AG92: 7. Julio | AH92: ✅
A93: MULTAS_Files_/0d4983f3.ARCHIVO.164237.41.pdf | B93: PAGADO | C93: EDUARDO SANTA CRUZ | D93: F002 | F93: Y | G93: YA PAGÓ | H93: 45920 | I93: Y | J93: 1760883638 | K93: 45858 | Y93: =E93+L93+M93+N93+O93+P93+Q93+R93+S93+T93+U93+V93+W93+X93 -> 0 | Z93: ENTRO 19/09 | AA93: N | AB93: MULTA CASELLO AUTOSTRADALE | AC93: 451ba90f | AD93: 0d4983f3 | AE93: MULTAS_Files_/0d4983f3.RECIBO DE PAGO.080358.TO PUBBLICA SICURE_02-283717432.pdf | AF93: 20/08/2025 | AG93: 7. Julio | AH93: ✅
A94: MULTAS_Files_/5f55e6c9.ARCHIVO.145322.45.pdf | B94: Vencido Julio 2025 | C94: EMPRESA | D94: F010 | E94: 300 | F94: Y | G94: HA DESCONTAR | H94: 45889 | J94: IL/309250101852 | K94: 45858 | Y94: =E94+L94+M94+N94+O94+P94+Q94+R94+S94+T94+U94+V94+W94+X94 -> 300 | Z94: NESSUN REGISTRO. ENTRO 17/08 | AA94: N | AB94: MULTA AUSTRIA PEDAGGIO | AC94: 451ba90f | AD94: 5f55e6c9 | AF94: 20/08/2025 00:00:00 | AG94: 7. Julio
A95: MULTAS_Files_/03d3b848.ARCHIVO.151726.15.pdf | B95: PAGADO | C95: MARINO ORTEGA | D95: F002 | F95: Y | G95: YA PAGÓ | H95: 45924 | I95: Y | J95: 01216941/2025/1/1/1 | K95: 45862 | Y95: =E95+L95+M95+N95+O95+P95+Q95+R95+S95+T95+U95+V95+W95+X95 -> 0 | Z95: R: 77 | AA95: N | AB95: MULTA CORSIA RISERVATA | AC95: 451ba90f | AD95: 03d3b848 | AE95: MULTAS_Files_/03d3b848.RECIBO DE PAGO.081243.pdf | AF95: 24/08/2025 | AG95: 7. Julio | AH95: ✅
A96: MULTAS_Files_/2feea8af.ARCHIVO.153325.32.pdf | B96: PAGADO | C96: JHON JULIAN | D96: F005 | E96: 102 | F96: 17/04/2025 | G96: 27/04/2025 | H96: 45814 | I96: 0.38125 | J96: 01227212/2025/1/1/1 | S96: -102 | Y96: =E96+L96+M96+N96+O96+P96+Q96+R96+S96+T96+U96+V96+W96+X96 -> 0 | Z96: R: 77 | AA96: NO | AB96: MULTA CORSIA RISERVATA | AC96: G029 | AD96: 2feea8af | AE96: MULTAS_Files_/2feea8af.RECIBO DE PAGO.113700.pdf | AF96: LAVORATORE
A97: MULTAS_Files_/7a46a064.ARCHIVO.161014.09.pdf | B97: PAGADO | C97: ADRIAN ROJAS | D97: F007 | E97: 102 | F97: Y | G97: DESCONTADO | H97: 45924 | I97: Y | J97: 01229640/2025/1/1/1 | K97: 45862 | T97: -102 | Y97: =E97+L97+M97+N97+O97+P97+Q97+R97+S97+T97+U97+V97+W97+X97 -> 0 | Z97: R: 77 ENTRO IL 20/09 | AA97: NO | AB97: MULTA CORSIA RISERVATA | AC97: G032 | AD97: 7a46a064 | AE97: MULTAS_Files_/7a46a064.RECIBO DE PAGO.071726. 01229640-2025-1-1-1.pdf | AF97: 24/08/2025 | AG97: 7. Julio | AH97: ✅
A98: MULTAS_Files_/321b8b98.ARCHIVO.103848.pdf | B98: PAGADO | C98: ALONSO TAMARA | D98: F021 | E98: 38 | F98: Y | G98: DESCONTADO | H98: 45934 | I98: Y | J98: V/91474425X/2025 | K98: 45873 | S98: -38 | Y98: =E98+L98+M98+N98+O98+P98+Q98+R98+S98+T98+U98+V98+W98+X98 -> 0 | Z98: PAGATA DAL LAVORATORE | AA98: N | AB98: MULTA VELOCITA' | AC98: G014 | AD98: 321b8b98 | AE98: MULTAS_Images/321b8b98.RECIBO DE PAGO.070303.jpg | AF98: 04/09/2025 | AG98: 8. Agosto | AH98: ✅
A99: MULTAS_Files_/9c438654.ARCHIVO.105019.pdf | B99: PAGADO | C99: JUAN CARLOS | D99: F026 | E99: 176 | F99: Y | G99: DESCONTADO | H99: 45924 | I99: Y | J99: V/41648R/2025 | K99: 45862 | S99: -118 | T99: -58 | Y99: =E99+L99+M99+N99+O99+P99+Q99+R99+S99+T99+U99+V99+W99+X99 -> 0 | AA99: N | AB99: MULTA SEMAFORICA | AC99: G025 | AD99: 9c438654 | AE99: MULTAS_Files_/9c438654.RECIBO DE PAGO.163006.pdf | AF99: 24/08/2025 | AG99: 7. Julio | AH99: ✅
A100: MULTAS_Files_/31155904.ARCHIVO.152501.24.pdf | B100: VENCIDA | C100: ROMARIO QUISPE | D100: F012 | E100: 102 | F100: 14/03/2025 | G100: 14/03/2025 | H100: 45730 | I100: 0.78958333 | J100: 00503538/2025/1/1/1 | W100: -102 | Y100: =E100+L100+M100+N100+O100+P100+Q100+R100+S100+T100+U100+V100+W100+X100 -> 0 | Z100: R: 77 | AA100: NO | AB100: MULTA AREA B | AC100: G011 | AD100: 31155904
A101: MULTAS_Files_/6fabacc4.ARCHIVO.152905.27.pdf | B101: VENCIDA | C101: EMPRESA | D101: F002 | E101: 102 | F101: 17/03/2025 | G101: 17/03/2025 | H101: 45733 | I101: 0.51041667 | J101: 00519390/2025/1/1/1 | Y101: =E101+L101+M101+N101+O101+P101+Q101+R101+S101+T101+U101+V101+W101+X101 -> 102 | Z101: R: 77 | AA101: NO | AB101: MULTA AREA C | AC101: 451ba90f | AD101: 6fabacc4
...

Sheet REQUERIMIENTOS
A1: COMPROBANTE | B1: ID | C1: CONCEPTO | D1: HECHO | E1: PRECIO ( UN ) | F1: UN | G1: TOTAL INVERSION | H1: MONTO APROX EUROS | I1: MAY | J1: JUN | K1: JUL | L1: AGO | M1: SET | N1: POR PAGAR | O1: COMENTARIOS
B2: 1 | C2: DOMINIO / CORREOS CORPORATIVOS | D2: TRUE | E2: 150 | F2: 1 | G2: =E2*F2 -> 150 | H2: =G2/3.93 -> 38.167939 | O2: Propiedad por 2 años
B3: 2 | C3: PAGINA WEB | D3: TRUE | E3: 350 | F3: 1 | G3: =E3*F3 -> 350 | H3: =G3/3.93 -> 89.058524 | O3: Realizado por programador de experiencia
B4: 3 | C4: POLOS PERSONALIZADOS | D4: FALSE | E4: 25 | F4: 1 | G4: =E4*F4 -> 25 | H4: =G4/3.93 -> 6.3613232 | O4: 10 polos
B5: 4 | C5: CHALECOS PERSONALIZADOS | D5: FALSE | E5: 30 | F5: 28 | G5: =E5*F5 -> 840 | H5: =G5/3.93 -> 213.74046 | O5: Talla M /S 25 / 1 docena de simples
B6: 5 | C6: LANYARD LLAVEROS | D6: FALSE | E6: 3 | F6: 100 | G6: =E6*F6 -> 300 | H6: =G6/3.93 -> 76.335878 | O6: Por confirmar a la llegada de Emerson
B7: 6 | C7: LOGOS PLANCHADO | D7: FALSE | E7: 50 | F7: 2 | G7: =E7*F7 -> 100 | H7: =G7/3.93 -> 25.445293 | O7: Cruces 80 (20x20) / Logo (25) / Numeración
B8: 7 | C8: TARJETAS PERSONALIZADAS | D8: FALSE | E8: 50 | F8: 3 | G8: =E8*F8 -> 150 | H8: =G8/3.93 -> 38.167939 | O8: Por confirmar a la llegada de Emerson
B9: 8 | C9: DISCO DURO Y ADAPTADOR | D9: TRUE | E9: 400 | F9: 1 | G9: 400 | H9: =G9/3.93 -> 101.78117 | O9: Comprado con adaptador
G22: =SUM(G2:G20) -> 2315 | H22: =SUM(H2:H20) -> 589.05852

Sheet COMBUSTIBLE
A1: ID_REGISTRO | B1: ID_TRABAJADOR | C1: FECHA | D1: MONTO | E1: TARGA | F1: METODO | G1: AREA | H1: MES | I1: ARCHIVO
A2: 45901.475 | B2: G026 | C2: 45901 | G2: DHL | H2: 9. SETIEMBRE | I2: Respuestas de formulario 1_Images/09-01-2025 11-23-18.FOTO COMBUSTIBLE.092600.jpg
A3: 45902.76 | B3: G034 | C3: 45901 | D3: 37 | F3: AUTOBOT / IP | G3: DHL | H3: 9. SETIEMBRE | I3: Respuestas de formulario 1_Images/09-02-2025 18-14-08.FOTO COMBUSTIBLE.161647.jpg
A4: 45902.771 | B4: G023 | C4: 45901 | D4: 48.4 | F4: AUTOBOT / IP | G4: DHL | H4: 9. SETIEMBRE | I4: Respuestas de formulario 1_Images/09-02-2025 18-29-48.FOTO COMBUSTIBLE.163919.jpg
A5: 45902.788 | B5: G014 | C5: 45901 | D5: 74 | F5: AUTOBOT / IP | G5: DHL | H5: 9. SETIEMBRE | I5: Respuestas de formulario 1_Images/09-02-2025 18-54-31.FOTO COMBUSTIBLE.165715.jpg
A6: 45903.437 | B6: G026 | C6: 45903 | D6: 16.79 | G6: DHL | H6: 9. SETIEMBRE | I6: Respuestas de formulario 1_Images/09-03-2025 10-28-47.FOTO COMBUSTIBLE.083028.jpg
A7: 45904.396 | B7: G036 | C7: 45903 | D7: 50 | E7: F011 | F7: OTRO | G7: DHL | H7: 9. SETIEMBRE | I7: COMBUSTIBLE_Images/09-04-2025 09-29-37.ARCHIVO.201157.jpg
A8: 45904.501 | B8: G034 | C8: 45903 | D8: 46 | F8: AUTOBOT / IP | G8: DHL | H8: 9. SETIEMBRE | I8: Respuestas de formulario 1_Images/09-04-2025 12-01-30.FOTO COMBUSTIBLE.100529.jpg
A9: 45904.823 | B9: G025 | C9: 45903 | F9: AUTOBOT / IP | G9: DHL | H9: 9. SETIEMBRE
A10: 45904.897 | B10: G028 | C10: 45903 | D10: 70.33 | F10: AUTOBOT / IP | G10: DHL | H10: 9. SETIEMBRE | I10: Respuestas de formulario 1_Images/09-04-2025 21-31-58.FOTO COMBUSTIBLE.193755.jpg
A11: 45904.905 | B11: G028 | C11: 45904 | D11: 177.38 | F11: AUTOBOT / IP | G11: DHL | H11: 9. SETIEMBRE | I11: Respuestas de formulario 1_Images/09-04-2025 21-43-50.FOTO COMBUSTIBLE.200123.jpg
A12: 45905.318 | B12: G026 | C12: 45904 | D12: 36.86 | G12: DHL | H12: 9. SETIEMBRE | I12: Respuestas de formulario 1_Images/09-05-2025 07-37-31.FOTO COMBUSTIBLE.053945.jpg
A13: 45905.49 | B13: G026 | C13: 45905 | G13: DHL | H13: 9. SETIEMBRE | I13: Respuestas de formulario 1_Images/09-05-2025 11-46-07.FOTO COMBUSTIBLE.094811.jpg
A14: 45905.579 | B14: G034 | C14: 45905 | D14: 54.05 | F14: AUTOBOT / IP | G14: DHL | H14: 9. SETIEMBRE | I14: Respuestas de formulario 1_Images/09-05-2025 13-54-23.FOTO COMBUSTIBLE.115624.jpg
A15: 45905.871 | B15: G014 | C15: 45905 | D15: 53 | F15: AUTOBOT / IP | G15: DHL | H15: 9. SETIEMBRE | I15: Respuestas de formulario 1_Images/09-05-2025 20-53-43.FOTO COMBUSTIBLE.185627.jpg
A16: 45906.865 | B16: G014 | C16: 45906 | D16: 42 | G16: DHL | H16: 9. SETIEMBRE | I16: Respuestas de formulario 1_Images/09-06-2025 20-45-48.FOTO COMBUSTIBLE.185110.jpg
A17: 45901.406 | B17: G016 | C17: 45901 | D17: 91.01 | G17: FARMACIA | H17: 9. SETIEMBRE
A18: 45901.471 | B18: G005 | C18: 45901 | D18: 108.18 | G18: FARMACIA | H18: 9. SETIEMBRE
A19: 45902.456 | B19: G005 | C19: 45902 | D19: 125.1 | G19: FARMACIA | H19: 9. SETIEMBRE
A20: 45903.457 | B20: G031 | C20: 45902 | D20: 27.29 | E20: F001 | F20: EKOPOINT | G20: FARMACIA | H20: 9. SETIEMBRE | I20: COMBUSTIBLE_Images/09-03-2025 10-58-12.ARCHIVO.183503.jpg
A21: 45903.464 | B21: G031 | C21: 45903 | D21: 116.87 | E21: F016 | F21: AUTOBOT / IP | G21: FARMACIA | H21: 9. SETIEMBRE | I21: COMBUSTIBLE_Images/09-03-2025 11-07-44.ARCHIVO.183357.jpg
A22: 45903.536 | B22: G005 | C22: 45903 | D22: 98.8 | G22: FARMACIA | H22: 9. SETIEMBRE
A23: 45905.423 | B23: G011 | C23: 45905 | D23: 142.43 | G23: FARMACIA | H23: 9. SETIEMBRE
A24: 45906.399 | B24: G016 | C24: 45906 | D24: 123.32 | G24: FARMACIA | H24: 9. SETIEMBRE
A25: 45904.743 | B25: G008 | C25: 45904 | D25: 95.73 | F25: AUTOBOT / IP | G25: FARMACIA | H25: 9. SETIEMBRE | I25: Respuestas de formulario 2_Images/09-04-2025 17-50-32.FOTO COMBUSTIBLE.155241.jpg
A26: 45905.749 | B26: G008 | C26: 45902 | D26: 95.96 | F26: AUTOBOT / IP | G26: FARMACIA | H26: 9. SETIEMBRE | I26: Respuestas de formulario 2_Images/09-05-2025 17-58-58.FOTO COMBUSTIBLE.160101.jpg
A27: 45905.912 | B27: G035 | C27: 45901 | D27: 89.42 | E27: F004 | G27: FARMACIA | H27: 9. SETIEMBRE | I27: Respuestas de formulario 2_Images/09-05-2025 21-52-44.FOTO COMBUSTIBLE.195606.jpg
A28: 45905.916 | B28: G035 | C28: 45905 | D28: 104.07 | E28: F004 | F28: AUTOBOT / IP | G28: FARMACIA | H28: 9. SETIEMBRE | I28: Respuestas de formulario 2_Images/09-05-2025 21-59-24.FOTO COMBUSTIBLE.200154.jpg
A29: 45906.7 | B29: G008 | C29: 45906 | D29: 120.35 | F29: AUTOBOT / IP | G29: FARMACIA | H29: 9. SETIEMBRE | I29: Respuestas de formulario 2_Images/09-06-2025 16-48-02.FOTO COMBUSTIBLE.144920.jpg
A30: 45907.505 | B30: G025 | C30: 45905 | D30: 43.52 | F30: OTRO | G30: DHL | H30: 9. SETIEMBRE | I30: COMBUSTIBLE_Images/09-07-2025 12-06-42.ARCHIVO.100956.jpg
A31: 45907.515 | B31: G025 | C31: 45906 | D31: 47 | F31: CARTA PERSONAL | G31: DHL | H31: 9. SETIEMBRE | I31: COMBUSTIBLE_Images/09-07-2025 12-21-06.ARCHIVO.102251.jpg
A32: 45908.343 | B32: G028 | C32: 45908 | D32: 39.39 | F32: OTRO | G32: DHL | H32: 9. SETIEMBRE | I32: COMBUSTIBLE_Images/09-08-2025 08-14-30.ARCHIVO.061612.jpg
A33: 45908.472 | B33: G014 | C33: 45908 | D33: 70 | F33: OTRO | G33: DHL | H33: 9. SETIEMBRE | I33: COMBUSTIBLE_Images/09-08-2025 11-20-19.ARCHIVO.092150.jpg
A34: 45908.731 | B34: G025 | C34: 45908 | D34: 43.77 | F34: OTRO | G34: DHL | H34: 9. SETIEMBRE | I34: COMBUSTIBLE_Images/09-08-2025 17-33-11.ARCHIVO.153420.jpg
A35: 45908.733 | B35: G023 | C35: 45908 | D35: 74.11 | F35: OTRO | G35: DHL | H35: 9. SETIEMBRE | I35: COMBUSTIBLE_Images/09-08-2025 17-35-58.ARCHIVO.155234.jpg
A36: 45908.745 | B36: G023 | C36: 45908 | D36: 10 | F36: CARTA PERSONAL | G36: DHL | H36: 9. SETIEMBRE | I36: COMBUSTIBLE_Images/09-08-2025 17-52-31.ARCHIVO.155359.jpg
A37: 45908.781 | B37: G032 | C37: 45903 | D37: 106.53 | E37: F020 | F37: AUTOBOT / IP | G37: FARMACIA | H37: 9. SETIEMBRE | I37: COMBUSTIBLE_Images/09-08-2025 18-45-13.ARCHIVO.164840.jpg
A38: 45908.784 | B38: G032 | C38: 45906 | D38: 97.01 | E38: F020 | F38: AUTOBOT / IP | G38: FARMACIA | H38: 9. SETIEMBRE | I38: COMBUSTIBLE_Images/09-08-2025 18-48-51.ARCHIVO.164934.jpg
A39: 45908.791 | B39: G037 | C39: 45901 | D39: 87.44 | E39: F027 | F39: AUTOBOT / IP | G39: FARMACIA | H39: 9. SETIEMBRE | I39: COMBUSTIBLE_Images/09-08-2025 18-59-00.ARCHIVO.170203.jpg
A40: 45908.792 | B40: G037 | C40: 45906 | D40: 133.06 | E40: F027 | F40: AUTOBOT / IP | G40: FARMACIA | H40: 9. SETIEMBRE | I40: COMBUSTIBLE_Images/09-08-2025 19-00-29.ARCHIVO.170211.jpg
A41: 45908.793 | B41: G037 | C41: 45908 | D41: 37.79 | E41: F027 | F41: AUTOBOT / IP | G41: FARMACIA | H41: 9. SETIEMBRE | I41: COMBUSTIBLE_Images/09-08-2025 19-02-12.ARCHIVO.170313.jpg
A42: 45908.856 | B42: G031 | C42: 45908 | D42: 111.78 | E42: F016 | F42: Autobot | G42: FARMACIA | H42: 9. SETIEMBRE | I42: COMBUSTIBLE_Images/09-08-2025 20-32-11.ARCHIVO.183249.jpg
A43: 45909.603 | B43: G028 | C43: 45909 | D43: 60 | F43: CARTA PERSONAL | G43: DHL | H43: 9. SETIEMBRE | I43: COMBUSTIBLE_Images/09-09-2025 14-27-37.ARCHIVO.122931.jpg
A44: 45909.791 | B44: G021 | C44: 45908 | D44: 130.01 | F44: AUTOBOT / IP | G44: FARMACIA | H44: 9. SETIEMBRE | I44: COMBUSTIBLE_Images/09-09-2025 18-58-37.ARCHIVO.170250.jpg
A45: 45909.794 | B45: G021 | C45: 45902 | D45: 123.03 | F45: AUTOBOT / IP | G45: FARMACIA | H45: 9. SETIEMBRE | I45: COMBUSTIBLE_Images/09-09-2025 19-03-17.ARCHIVO.170408.jpg
A46: 45909.815 | B46: G032 | C46: 45909 | D46: 90.02 | E46: F020 | F46: AUTOBOT / IP | G46: FARMACIA | H46: 9. SETIEMBRE | I46: COMBUSTIBLE_Images/09-09-2025 19-33-34.ARCHIVO.173413.jpg
A47: 45909.835 | B47: G020 | C47: 45901 | D47: 135.15 | E47: F006 | F47: AUTOBOT / IP | G47: FARMACIA | H47: 9. SETIEMBRE | I47: COMBUSTIBLE_Images/09-09-2025 20-01-50.ARCHIVO.180250.jpg
A48: 45909.835 | B48: G020 | C48: 45904 | D48: 110.75 | E48: F006 | F48: AUTOBOT / IP | G48: FARMACIA | H48: 9. SETIEMBRE | I48: COMBUSTIBLE_Images/09-09-2025 20-02-54.ARCHIVO.180336.jpg
A49: 45909.836 | B49: G020 | C49: 45908 | D49: 134 | E49: F006 | F49: AUTOBOT / IP | G49: FARMACIA | H49: 9. SETIEMBRE | I49: COMBUSTIBLE_Images/09-09-2025 20-03-39.ARCHIVO.180416.jpg
A50: 45909.835 | B50: G024 | C50: 45901 | D50: 117.75 | E50: F019 | F50: AUTOBOT / IP | G50: FARMACIA | H50: 9. SETIEMBRE | I50: COMBUSTIBLE_Images/09-09-2025 20-02-55.ARCHIVO.180558.jpg
A51: 45909.838 | B51: G024 | C51: 45903 | D51: 98.8 | E51: F019 | F51: AUTOBOT / IP | G51: FARMACIA | H51: 9. SETIEMBRE | I51: COMBUSTIBLE_Images/09-09-2025 20-06-09.ARCHIVO.180809.jpg
A52: 45909.84 | B52: G024 | C52: 45906 | D52: 111.81 | E52: F019 | F52: AUTOBOT / IP | G52: FARMACIA | H52: 9. SETIEMBRE | I52: COMBUSTIBLE_Images/09-09-2025 20-08-56.ARCHIVO.181010.jpg
A53: 45910.308 | B53: G014 | C53: 45910 | D53: 52.99 | F53: OTRO | G53: DHL | H53: 9. SETIEMBRE | I53: COMBUSTIBLE_Images/09-10-2025 07-23-19.ARCHIVO.052411.jpg
A54: 45910.435 | B54: G024 | C54: 45910 | D54: 126.98 | E54: F019 | F54: AUTOBOT / IP | G54: FARMACIA | H54: 9. SETIEMBRE | I54: COMBUSTIBLE_Images/09-10-2025 10-26-58.ARCHIVO.082816.jpg
A55: 45910.27 | B55: G027 | C55: 45909 | D55: 120 | F55: AUTOBOT / IP | G55: FARMACIA | H55: 9. SETIEMBRE | I55: COMBUSTIBLE_Images/09-10-2025 06-28-21.ARCHIVO.063116.jpg
A56: 45910.518 | B56: G027 | C56: 45904 | D56: 125 | F56: AUTOBOT / IP | G56: FARMACIA | H56: 9. SETIEMBRE | I56: COMBUSTIBLE_Images/09-10-2025 12-25-15.ARCHIVO.102725.jpg
A57: 45910.714 | B57: G025 | C57: 45910 | D57: 50.72 | F57: OTRO | G57: DHL | H57: 9. SETIEMBRE | I57: COMBUSTIBLE_Images/09-10-2025 17-08-11.ARCHIVO.150936.jpg
A58: 45910.771 | B58: G029 | C58: 45910 | D58: 94.21 | E58: F005 | F58: AUTOBOT / IP | G58: FARMACIA | H58: 9. SETIEMBRE | I58: COMBUSTIBLE_Images/09-10-2025 18-29-36.ARCHIVO.163120.jpg
A59: 45910.772 | B59: G029 | C59: 45906 | D59: 100.62 | E59: F005 | G59: FARMACIA | H59: 9. SETIEMBRE | I59: COMBUSTIBLE_Images/09-10-2025 18-31-49.ARCHIVO.163215.jpg
A60: 45910.773 | B60: G029 | C60: 45902 | D60: 85.06 | E60: F005 | F60: AUTOBOT / IP | G60: FARMACIA | H60: 9. SETIEMBRE | I60: COMBUSTIBLE_Images/09-10-2025 18-32-40.ARCHIVO.051932.jpg
A61: 45911.49 | B61: G037 | C61: 45911 | D61: 103.1 | E61: F027 | F61: AUTOBOT / IP | G61: FARMACIA | H61: 9. SETIEMBRE | I61: COMBUSTIBLE_Images/09-11-2025 11-45-50.ARCHIVO.094705.jpg
A62: 45911.687 | B62: G023 | C62: 45910 | D62: 48.55 | F62: OTRO | G62: DHL | H62: 9. SETIEMBRE | I62: COMBUSTIBLE_Images/09-11-2025 16-29-27.ARCHIVO.143057.jpg
A63: 45911.688 | B63: G023 | C63: 45911 | D63: 61.69 | F63: OTRO | G63: DHL | H63: 9. SETIEMBRE | I63: COMBUSTIBLE_Images/09-11-2025 16-31-00.ARCHIVO.143201.jpg
A64: 45911.72 | B64: G026 | C64: 45911 | D64: 27.74 | F64: OTRO | G64: DHL | H64: 9. SETIEMBRE | I64: COMBUSTIBLE_Images/09-11-2025 17-16-37.ARCHIVO.151753.jpg
A65: 45911.761 | B65: G034 | C65: 45908 | D65: 41 | F65: OTRO | G65: DHL | H65: 9. SETIEMBRE | I65: COMBUSTIBLE_Images/09-11-2025 18-15-18.ARCHIVO.161802.jpg
A66: 45911.763 | B66: G034 | C66: 45911 | D66: 30.02 | F66: OTRO | G66: DHL | H66: 9. SETIEMBRE | I66: COMBUSTIBLE_Images/09-11-2025 18-18-20.ARCHIVO.161909.jpg
A67: 45911.764 | B67: G034 | C67: 45910 | D67: 34.59 | F67: OTRO | G67: DHL | H67: 9. SETIEMBRE | I67: COMBUSTIBLE_Images/09-11-2025 18-19-45.ARCHIVO.162016.jpg
A68: 45911.8 | B68: G025 | C68: 45911 | D68: 34.66 | F68: OTRO | G68: DHL | H68: 9. SETIEMBRE | I68: COMBUSTIBLE_Images/09-11-2025 19-12-38.ARCHIVO.171322.jpg
A69: 45911.959 | B69: G028 | C69: 45911 | D69: 44.24 | F69: AUTOBOT / IP | G69: DHL | H69: 9. SETIEMBRE | I69: COMBUSTIBLE_Images/09-11-2025 23-00-48.ARCHIVO.210155.jpg
A70: 45911.96 | B70: G028 | C70: 45911 | D70: 99.8 | F70: AUTOBOT / IP | G70: DHL | H70: 9. SETIEMBRE | I70: COMBUSTIBLE_Images/09-11-2025 23-02-14.ARCHIVO.210315.jpg
A71: 45912.447 | B71: G005 | C71: 45912 | D71: 129.46 | E71: F017 | F71: AUTOBOT / IP | G71: FARMACIA | H71: 9. SETIEMBRE | I71: COMBUSTIBLE_Images/09-12-2025 10-43-04.ARCHIVO.084559.jpg
A72: 45912.473 | B72: G011 | C72: 45902 | D72: 125.1 | E72: F017 | F72: AUTOBOT / IP | G72: FARMACIA | H72: 9. SETIEMBRE | I72: COMBUSTIBLE_Images/09-12-2025 11-21-45.ARCHIVO.092648.jpg
A73: 45912.475 | B73: G011 | C73: 45909 | D73: 125.89 | E73: F017 | F73: AUTOBOT / IP | G73: FARMACIA | H73: 9. SETIEMBRE | I73: COMBUSTIBLE_Images/09-12-2025 11-23-22.ARCHIVO.092657.jpg
A74: 45912.476 | B74: G037 | C74: 45905 | D74: 40.25 | E74: F027 | F74: EKOPOINT | G74: FARMACIA | H74: 9. SETIEMBRE | I74: COMBUSTIBLE_Images/09-12-2025 11-25-38.ARCHIVO.092703.jpg
A75: 45912.515 | B75: G014 | C75: 45912 | D75: 64 | F75: OTRO | G75: DHL | H75: 9. SETIEMBRE | I75: COMBUSTIBLE_Images/09-12-2025 12-21-54.ARCHIVO.102231.jpg
A76: 45912.74 | B76: G008 | C76: 45911 | D76: 105.45 | E76: F018 | F76: AUTOBOT / IP | G76: FARMACIA | H76: 9. SETIEMBRE | I76: COMBUSTIBLE_Images/09-12-2025 17-45-02.ARCHIVO.154611.jpg
A77: 45912.752 | B77: G008 | C77: 45909 | D77: 122.48 | E77: F018 | F77: AUTOBOT / IP | G77: FARMACIA | H77: 9. SETIEMBRE | I77: COMBUSTIBLE_Images/09-12-2025 18-02-55.ARCHIVO.160353.jpg
A78: 45912.761 | B78: G016 | C78: 45910 | D78: 101.23 | E78: F007 | F78: AUTOBOT / IP | G78: FARMACIA | H78: 9. SETIEMBRE | I78: COMBUSTIBLE_Images/09-12-2025 18-15-20.ARCHIVO.161556.jpg
A79: 45912.761 | B79: G035 | C79: 45908 | D79: 106 | E79: F009 | F79: AUTOBOT / IP | G79: FARMACIA | H79: 9. SETIEMBRE | I79: COMBUSTIBLE_Images/09-12-2025 18-15-18.ARCHIVO.161716.jpg
A80: 45912.762 | B80: G031 | C80: 45912 | D80: 105.67 | E80: F016 | F80: Autobot | G80: FARMACIA | H80: 9. SETIEMBRE | I80: COMBUSTIBLE_Images/09-12-2025 18-17-51.ARCHIVO.161824.jpg
A81: 45912.762 | B81: G035 | C81: 45912 | D81: 105.01 | E81: F004 | F81: AUTOBOT / IP | G81: FARMACIA | H81: 9. SETIEMBRE | I81: COMBUSTIBLE_Images/09-12-2025 18-17-25.ARCHIVO.161840.jpg
A82: 45912.936 | B82: G028 | C82: 45912 | D82: 56.75 | F82: OTRO | G82: DHL | H82: 9. SETIEMBRE | I82: COMBUSTIBLE_Images/09-12-2025 22-27-44.ARCHIVO.202902.jpg
A83: 45913.329 | B83: G020 | C83: 45911 | D83: 124.29 | E83: F006 | F83: AUTOBOT / IP | G83: FARMACIA | H83: 9. SETIEMBRE | I83: COMBUSTIBLE_Images/09-13-2025 07-53-10.ARCHIVO.055516.jpg
A84: 45913.333 | B84: G032 | C84: 45912 | D84: 96.4 | E84: F020 | F84: AUTOBOT / IP | G84: FARMACIA | H84: 9. SETIEMBRE | I84: COMBUSTIBLE_Images/09-13-2025 07-59-31.ARCHIVO.061132.jpg
A85: 45913.334 | B85: G032 | C85: 45912 | D85: 7.77 | E85: F020 | F85: EKOPOINT | G85: FARMACIA | H85: 9. SETIEMBRE | I85: COMBUSTIBLE_Images/09-13-2025 08-01-05.ARCHIVO.061138.jpg
A86: 45913.352 | B86: G027 | C86: 45913 | D86: 127.99 | F86: AUTOBOT / IP | G86: FARMACIA | H86: 9. SETIEMBRE | I86: COMBUSTIBLE_Images/09-13-2025 08-26-47.ARCHIVO.062807.jpg
A87: 45913.439 | B87: G023 | C87: 45912 | D87: 67.93 | F87: OTRO | G87: DHL | H87: 9. SETIEMBRE | I87: COMBUSTIBLE_Images/09-13-2025 10-32-10.ARCHIVO.083323.jpg
A88: 45913.448 | B88: G037 | C88: 45913 | D88: 66.41 | E88: F027 | F88: AUTOBOT / IP | G88: FARMACIA | H88: 9. SETIEMBRE | I88: COMBUSTIBLE_Images/09-13-2025 10-44-36.ARCHIVO.084527.jpg
A89: 45913.449 | B89: G024 | C89: 45913 | D89: 118.3 | E89: F019 | F89: AUTOBOT / IP | G89: FARMACIA | H89: 9. SETIEMBRE | I89: COMBUSTIBLE_Images/09-13-2025 10-46-18.ARCHIVO.084713.jpg
A90: 45913.503 | B90: G026 | C90: 45912 | D90: 43.15 | F90: OTRO | G90: DHL | H90: 9. SETIEMBRE | I90: COMBUSTIBLE_Images/09-13-2025 12-04-09.ARCHIVO.100457.jpg
A91: 45913.857 | B91: G008 | C91: 45913 | D91: 103.23 | E91: F018 | F91: AUTOBOT / IP | G91: FARMACIA | H91: 9. SETIEMBRE | I91: COMBUSTIBLE_Images/09-13-2025 20-34-23.ARCHIVO.183536.jpg
A92: 45914.994 | B92: G034 | C92: 45906 | D92: 50.01 | F92: CARTA PERSONAL | G92: DHL | H92: 9. SETIEMBRE | I92: COMBUSTIBLE_Images/09-14-2025 23-50-50.ARCHIVO.215127.jpg
A93: 45915.42 | B93: G021 | C93: 45913 | D93: 121 | F93: AUTOBOT / IP | G93: FARMACIA | H93: 9. SETIEMBRE | I93: COMBUSTIBLE_Images/09-15-2025 10-04-13.ARCHIVO.080455.jpg
A94: 45915.421 | B94: G016 | C94: 45913 | D94: 109.99 | E94: F007 | F94: AUTOBOT / IP | G94: FARMACIA | H94: 9. SETIEMBRE | I94: COMBUSTIBLE_Images/09-15-2025 10-06-32.ARCHIVO.080726.jpg
A95: 45915.631 | B95: G020 | C95: 45915 | D95: 132.94 | E95: F006 | F95: AUTOBOT / IP | G95: FARMACIA | H95: 9. SETIEMBRE | I95: COMBUSTIBLE_Images/09-15-2025 15-08-19.ARCHIVO.130947.jpg
A96: 45915.659 | B96: G029 | C96: 45915 | D96: 107.19 | E96: F005 | F96: AUTOBOT / IP | G96: FARMACIA | H96: 9. SETIEMBRE | I96: COMBUSTIBLE_Images/09-15-2025 15-48-36.ARCHIVO.134922.jpg
A97: 45915.669 | B97: G025 | C97: 45915 | D97: 67.12 | F97: OTRO | G97: DHL | H97: 9. SETIEMBRE | I97: COMBUSTIBLE_Images/09-15-2025 16-03-26.ARCHIVO.140453.jpg
A98: 45915.878 | B98: G035 | C98: 45915 | D98: 110.5 | E98: F004 | F98: AUTOBOT / IP | G98: FARMACIA | H98: 9. SETIEMBRE | I98: COMBUSTIBLE_Images/09-15-2025 21-03-41.ARCHIVO.190443.jpg
A99: 45916.371 | B99: G028 | C99: 45915 | D99: 60.83 | F99: OTRO | G99: DHL | H99: 9. SETIEMBRE | I99: COMBUSTIBLE_Images/09-16-2025 08-54-29.ARCHIVO.065625.jpg
A100: 45916.373 | B100: G028 | C100: 45916 | D100: 49.11 | F100: OTRO | G100: DHL | H100: 9. SETIEMBRE | I100: COMBUSTIBLE_Images/09-16-2025 08-56-25.ARCHIVO.065710.jpg
...

Sheet MANCATO P.
A1: Id_Multas | B1: ESTADO | C1: FECHA | D1: VERBALE | E1: HORA | F1: TARGA | G1: MONTO | H1: ID_ TRABAJADOR | I1: COMENTARIOS | J1: ARCHIVO | K1: RECIBO DE PAGO | L1: TIPO | M1: MES | N1: FECHA RECEPCIÓN | O1: PEAJE/SALIDA | P1: NOTA AUTISTA
A2: fccbd646 | B2: PAGADO | C2: 26/03/2025 | F2: EG403NT | G2: 6.91 | J2: MANCATO P._Files_/fccbd646.ARCHIVO.092245.pdf | K2: MANCATO P._Files_/fccbd646.RECIBO DE PAGO.092644.pdf | M2: 03. MARZO | N2: 45727
A3: c6cc69bd | B3: PAGADO | C3: 26/03/2025 | F3: EG403NT | G3: 6.91 | J3: MANCATO P._Files_/c6cc69bd.ARCHIVO.094438.pdf | K3: MANCATO P._Files_/c6cc69bd.RECIBO DE PAGO.094438.pdf | M3: 03. MARZO | N3: 45727
A4: f6e6eb6e | B4: PAGADO | C4: 05/06/2025 | E4: 0.63194444 | F4: EG403NT | G4: 5.3 | I4: PAGATO IN TEMPO | J4: MANCATO P._Files_/f6e6eb6e.ARCHIVO.081851.pdf | K4: MANCATO P._Files_/f6e6eb6e.RECIBO DE PAGO.081851.pdf | M4: 05. MAYO | N4: 45798
A5: 0938c39a | B5: PAGADO | C5: 05/06/2025 | E5: 0.55694444 | F5: EG403NT | G5: 4.6 | I5: PAGATO IN TEMPO | J5: MANCATO P._Files_/0938c39a.ARCHIVO.082315.pdf | K5: MANCATO P._Files_/0938c39a.RECIBO DE PAGO.082315.pdf | M5: 05. MAYO | N5: 45798
A6: 959ac8ba | B6: PAGADO | C6: 05/06/2025 | E6: 0.69652778 | F6: EG403NT | G6: 7.9 | I6: PAGATO IN TEMPO | J6: MANCATO P._Files_/959ac8ba.ARCHIVO.083243.pdf | K6: MANCATO P._Files_/959ac8ba.RECIBO DE PAGO.083243.pdf | M6: 05. MAYO | N6: 45798
A7: c62274ba | B7: PAGADO | C7: 5/6/2025 | E7: 0.47013889 | I7: PAGATO IN TEMPO | J7: MANCATO P._Files_/c62274ba.ARCHIVO.084736.pdf | K7: MANCATO P._Files_/c62274ba.RECIBO DE PAGO.084736.pdf | M7: 05. MAYO | N7: 45798
A8: 2a6bc0d9 | B8: PAGADO | C8: 05/06/2025 | E8: 0.48263889 | F8: EG403NT | G8: 1.9 | I8: PAGATO IN TEMPO | J8: MANCATO P._Files_/2a6bc0d9.ARCHIVO.085319.pdf | K8: MANCATO P._Files_/2a6bc0d9.RECIBO DE PAGO.085319.pdf | M8: 05. MAYO | N8: 45798
A9: 11687cf9 | B9: PAGADO | C9: 03/06/2025 | E9: 0.73611111 | F9: EG403NT | G9: 13.3 | H9: 451ba90f | I9: PAGATO IN TEMPO | J9: MANCATO P._Files_/11687cf9.ARCHIVO.094615.pdf | K9: MANCATO P._Files_/11687cf9.RECIBO DE PAGO.094615.pdf | M9: 05. MAYO | N9: 45796
A10: c585fec6 | B10: PAGADO | C10: 03/06/2025 | E10: 0.79861111 | F10: EG403NT | G10: 13.3 | H10: 451ba90f | I10: PAGATO IN TEMPO | J10: MANCATO P._Files_/c585fec6.ARCHIVO.095330.pdf | K10: MANCATO P._Files_/c585fec6.RECIBO DE PAGO.095330.pdf | M10: 05. MAYO | N10: 45796
A11: 1d0cea16 | B11: PAGADO | C11: 03/06/2025 | E11: 0.69027778 | F11: EG403NT | G11: 68.7 | H11: 451ba90f | I11: PAGATO IN TEMPO | J11: MANCATO P._Images/1d0cea16.ARCHIVO.102437.jpg | K11: MANCATO P._Files_/1d0cea16.RECIBO DE PAGO.102437.pdf | M11: 05. MAYO | N11: 45796
A12: b8dcd34f | B12: PAGADO | C12: 07/05/2025 | E12: 0.57222222 | F12: ER643VY | G12: 14.65 | H12: G030 | I12: SOLLECITO MANCATO PAGAMENTO | J12: Unable to load image data. The selected image could not be found.#filename=80250017128.pdf | K12: Unable to load image data. The selected image could not be found.#filename=IMG_B056FE17F8C8-1.jpeg | L12: MULTA | M12: 04. ABRIL | N12: 45769
A13: 511936f2 | B13: PAGADO | C13: 09/07/2025 | G13: 34.5 | I13: SERIE DI PASSAGGI DI DIVERSI FURGONI | J13: MANCATO P._Images/511936f2.ARCHIVO.085416.jpg | K13: MANCATO P._Files_/511936f2.RECIBO DE PAGO.085416.pdf | L13: MULTA | M13: 06. JUNIO | N13: 45832
A14: 01f8e8bd | B14: PAGADO | C14: 21/03/2025 | E14: 0.85277778 | F14: ET420XR | G14: 9.13 | H14: 451ba90f | I14: PEDAGGI DI RENZO | J14: MANCATO P._Images/01f8e8bd.ARCHIVO.112231.jpg | K14: MANCATO P._Images/01f8e8bd.RECIBO DE PAGO.112231.jpg | L14: MULTA | M14: 03. MARZO | N14: 45720
A15: bd72e045 | B15: PAGADO | C15: 18/07/2025 | E15: 0 | F15: ET420XR | H15: 451ba90f | I15: DUE PEDAGGI DI RENZO EL OTRO ES DE ES638NF | J15: MANCATO P._Images/bd72e045.ARCHIVO.112734.jpg | M15: 07. JULIO | N15: 45841
A16: 54051449 | B16: PAGADO | C16: 22/07/2025 | D16: 77250097999 | E16: 0.52430556 | F16: EG403NT | G16: 7.54 | H16: G030 | J16: MANCATO P._Files_/54051449.ARCHIVO.161054.pdf | K16: MANCATO P._Files_/54051449.RECIBO DE PAGO.161054.pdf | L16: MULTA | M16: 07. JULIO | N16: 45845
A17: 005bd6e2 | B17: PAGADO | C17: 22/05/2025 | D17: 77250050968 | E17: 0.66875 | F17: GB502TP | G17: 6.61 | H17: G022 | I17: multa pagata in ritardo (vediamo se c'è un'altra multa in corso) | J17: MANCATO P._Files_/005bd6e2.ARCHIVO.133956.pdf | K17: MANCATO P._Files_/005bd6e2.RECIBO DE PAGO.133956.pdf | L17: MULTA | M17: 05. MAYO | N17: 45784
A18: 4582bffb | B18: PAGADO | C18: 23/04/2025 | D18: 77250064502 | E18: 0.77291667 | F18: EG403NT | G18: 6.74 | H18: 451ba90f | I18: passaggio fatto da Juancarlos Lazaro. | J18: MANCATO P._Files_/4582bffb.ARCHIVO.144015.pdf | K18: MANCATO P._Files_/4582bffb.RECIBO DE PAGO.144015.pdf | L18: MULTA | M18: 04. ABRIL | N18: 45755
A19: a0d6f2d3 | B19: PAGADO | C19: 13/05/2025 | D19: 100070984396 | E19: 0 | F19: EG403NT | G19: 13.28 | H19: 451ba90f | I19: VARI PASSAGGI CABALLITO | J19: MANCATO P._Files_/a0d6f2d3.ARCHIVO.150124.57.pdf | K19: MANCATO P._Files_/a0d6f2d3.RECIBO DE PAGO.150124.pdf | L19: SOLLECITO | M19: 04. ABRIL | N19: 45775
A20: edaed6bf | B20: PAGADO | C20: 21/03/2025 | D20: 77250102143 | E20: 0.50763889 | F20: F002 | G20: 12.49 | H20: 451ba90f | I20: EG403NT + ET420XR | J20: MANCATO P._Files_/edaed6bf.ARCHIVO.100552.pdf | K20: MANCATO P._Files_/edaed6bf.RECIBO DE PAGO.100552.pdf | L20: SOLLECITO | M20: 03. MARZO | N20: 45720
A21: 6a73fd3c | B21: PAGADO | C21: 6/5/2025 | D21: 14250061816 | E21: 0.29097222 | F21: F002 | G21: 7.35 | H21: 451ba90f | J21: MANCATO P._Files_/6a73fd3c.ARCHIVO.103014.pdf | K21: MANCATO P._Files_/6a73fd3c.RECIBO DE PAGO.103014.pdf | L21: SOLLECITO | M21: 04. ABRIL | N21: 45768
A23: 8250482b | B23: PAGADO | C23: 25/06/2025 | D23: 3148417714 | E23: 0.75972222 | F23: F002 | G23: 4.3 | H23: 451ba90f | I23: MILANO SERRAVALLE | J23: MANCATO P._Files_/8250482b.ARCHIVO.155537.54.pdf | K23: MANCATO P._Files_/8250482b.RECIBO DE PAGO.155537.pdf | L23: MANCATO PAGAMENTO | M23: 06. JUNIO | N23: 45818
A24: 3f9e15f6 | B24: PAGADO | C24: 24/06/2025 | D24: 3148368875 | E24: 0.88611111 | F24: F013 | G24: 3.9 | H24: 451ba90f | I24: MILANO SERRAVALLE / PAGATO 7,94€ | J24: MANCATO P._Files_/3f9e15f6.ARCHIVO.160031.58.pdf | K24: MANCATO P._Files_/3f9e15f6.RECIBO DE PAGO.160031.pdf | L24: MANCATO PAGAMENTO | M24: 06. JUNIO | N24: 45817
A25: 79232bb9 | B25: PAGADO | C25: 10/06/2025 | D25: 80/2025/001707 | E25: 0.36319444 | F25: F001 | G25: 15.85 | H25: 451ba90f | I25: NON RIESCO A PAGARLO/ pagato FUORI TEMPO | J25: MANCATO P._Files_/79232bb9.ARCHIVO.161229.10.pdf | K25: MANCATO P._Images/79232bb9.RECIBO DE PAGO.145616.jpg | L25: SOLLECITO | M25: 05. MAYO | N25: 45803
A26: ae3a7386 | B26: PAGADO | C26: 09/07/2025 | D26: 0078034858 | E26: 0 | F26: F001 | G26: 34.5 | H26: 451ba90f | I26: ER643VY/EZ009PN/FY032BD/GE027AM/EG403NT -> 09/07/2025 (RISULTA GIA' PAGATO) | J26: MANCATO P._Files_/ae3a7386.ARCHIVO.161800.15.pdf | K26: MANCATO P._Images/ae3a7386.RECIBO DE PAGO.161800.png | L26: SOLLECITO | M26: 06. JUNIO | N26: 45832
A27: 8ad4b5d8 | B27: PAGADO | C27: 12/03/2025 | D27: 100071498230 | G27: 6.71 | H27: 451ba90f | I27: ET420XR/EG403NT -> PAGAMENTO SCADUTO SECONDO PORTALE | J27: MANCATO P._Files_/8ad4b5d8.ARCHIVO.162558.21.pdf | L27: MANCATO PAGAMENTO | M27: 02. FEBRERO | N27: 45713
A28: 3fe8fa38 | B28: PAGADO | C28: 24/06/2025 | D28: SOLLECITO 77250104877 | E28: 0.88611111 | F28: F013 | G28: 7.94 | H28: 451ba90f | J28: MANCATO P._Files_/3fe8fa38.ARCHIVO.075840.54.pdf | K28: MANCATO P._Files_/3fe8fa38.RECIBO DE PAGO.075840.pdf | L28: SOLLECITO | M28: 06. JUNIO | N28: 45817
A29: a80364dc | B29: PAGADO | C29: 22/3/2025 | D29: SOLLECITO: 77250102148 | E29: 0.63541667 | F29: F014 | G29: 6.07 | H29: 451ba90f | I29: RACCOMANDATA A NATALIA | J29: MANCATO P._Files_/a80364dc.ARCHIVO.080721.02.pdf | K29: MANCATO P._Files_/a80364dc.RECIBO DE PAGO.080721.pdf | L29: SOLLECITO | M29: 03. MARZO | N29: 45723
A30: b9244a87 | B30: PAGADO | C30: 25/06/2025 | D30: 77250104878 | E30: 0.75972222 | F30: F002 | G30: 8.34 | H30: 451ba90f | J30: MANCATO P._Images/b9244a87.ARCHIVO.110918.jpg | K30: MANCATO P._Files_/b9244a87.RECIBO DE PAGO.130357.pdf | L30: MANCATO PAGAMENTO | M30: 06. JUNIO | N30: 45818
A31: 6278fbcc | B31: PAGADO | C31: 07/07/2025 | D31: 77250108706 | E31: 0.66319444 | F31: F002 | G31: 6.94 | H31: 451ba90f | J31: MANCATO P._Files_/6278fbcc.ARCHIVO.131348.10.pdf | K31: MANCATO P._Files_/6278fbcc.RECIBO DE PAGO.131348.pdf | L31: SOLLECITO | M31: 06. JUNIO | N31: 45830
A32: b7b624ad | B32: PAGADO | C32: 07/07/2025 | D32: 77250108707 | E32: 0.72430556 | F32: F002 | G32: 6.94 | H32: 451ba90f | J32: MANCATO P._Files_/b7b624ad.ARCHIVO.134041.34.pdf | K32: MANCATO P._Files_/b7b624ad.RECIBO DE PAGO.134041.pdf | L32: SOLLECITO | M32: 06. JUNIO | N32: 45830
A33: 79b7d106 | B33: PAGADO | C33: 04/04/2025 | D33: 283734/2025 | E33: 0.47847222 | F33: F001 | G33: 8.8 | H33: 451ba90f | J33: MANCATO P._Files_/79b7d106.ARCHIVO.104357.25.pdf | K33: MANCATO P._Images/79b7d106.RECIBO DE PAGO.104357.jpg | L33: SOLLECITO | M33: 03. MARZO | N33: 45736
A34: f186f205 | B34: PAGADO | C34: 12/03/2025 | D34: 100071498230 | E34: 0 | G34: 6.71 | H34: 451ba90f | I34: caballito + alfa romeo | J34: MANCATO P._Files_/f186f205.ARCHIVO.111739.47.pdf | K34: MANCATO P._Files_/f186f205.RECIBO DE PAGO.111739.pdf | M34: 02. FEBRERO | N34: 45713
A35: e1c989e5 | B35: PAGADO | C35: 02/05/2025 | D35: 0078076490 | E35: 0 | F35: F002 | G35: 11.58 | H35: 451ba90f | J35: MANCATO P._Files_/e1c989e5.ARCHIVO.072513.20.pdf | K35: MANCATO P._Files_/e1c989e5.RECIBO DE PAGO.072513.pdf | L35: SOLLECITO | M35: 04. ABRIL | N35: 45764
A36: 1cfe409f | B36: PAGADO | C36: 03/09/2025 | D36: 77250109426 | E36: 0.28819444 | F36: F005 | G36: 6.14 | H36: 451ba90f | I36: PAGATO FUORI TEMPO | J36: MANCATO P._Files_/1cfe409f.ARCHIVO.114048.pdf | K36: MANCATO P._Files_/1cfe409f.RECIBO DE PAGO.145219.pdf | L36: SOLLECITO | M36: 08. AGOSTO | N36: 45888
A37: c8e95c11 | B37: PAGADO | C37: 10/09/2025 | D37: 77250109831 | E37: 0.80694444 | F37: F002 | G37: 7.54 | H37: 451ba90f | J37: MANCATO P._Files_/c8e95c11.ARCHIVO.193556.pdf | K37: MANCATO P._Files_/c8e95c11.RECIBO DE PAGO.145305.pdf | L37: SOLLECITO | M37: 08. AGOSTO | N37: 45895
A38: 3b49110c | B38: PAGADO | C38: 10/9/2025 | D38: 14250074908 | E38: 0.66597222 | F38: F013 | G38: 43.95 | H38: 451ba90f | J38: MANCATO P._Files_/3b49110c.ARCHIVO.133621.pdf | K38: MANCATO P._Files_/3b49110c.RECIBO DE PAGO.145359.pdf | L38: SOLLECITO | M38: 08. AGOSTO | N38: 45895
A39: 72179ab0 | B39: PAGADO | C39: 10/9/2025 | D39: 81250018525 | E39: 0.095833333 | F39: F001 | G39: 8.55 | H39: 451ba90f | J39: MANCATO P._Files_/72179ab0.ARCHIVO.214736.pdf | K39: MANCATO P._Images/72179ab0.RECIBO DE PAGO.145835.jpg | L39: SOLLECITO | M39: 08. AGOSTO | N39: 45895
A40: dc2f6e81 | B40: PAGADO | C40: 26/09/2025 | D40: 77250117274 | E40: 0.41111111 | F40: F005 | G40: 8.5 | H40: 451ba90f | J40: MANCATO P._Files_/dc2f6e81.ARCHIVO.201231.pdf | K40: MANCATO P._Files_/dc2f6e81.RECIBO DE PAGO.195206.pdf | L40: SOLLECITO | M40: 09. SEPTIEMBRE | N40: 45911
A41: 564f143b | B41: PAGADO | C41: 04/10/2025 | D41: 77250131321 | E41: 0.65277778 | F41: F024 | G41: 12.39 | H41: 451ba90f | I41: Son 2 vehículos, el otro es: ER643VY | J41: MANCATO P._Files_/564f143b.ARCHIVO.145442.pdf | K41: MANCATO P._Files_/564f143b.RECIBO DE PAGO.064403.pdf | L41: SOLLECITO | M41: 09. SEPTIEMBRE | N41: 45949
A42: 00469b1f | B42: PAGADO | C42: 04/10/2025 | D42: 3148817889 | E42: 0.43333333 | F42: F009 | G42: 2 | H42: G016 | I42: Enlace para pagar online: www.serravalle.it | J42: MANCATO P._Images/00469b1f.ARCHIVO.080259.png | K42: MANCATO P._Images/00469b1f.RECIBO DE PAGO.083102.jpg | L42: MANCATO PAGAMENTO | M42: 09. SEPTIEMBRE | N42: 45949
A43: f93fc742 | B43: PAGADO | C43: 04/10/2025 | D43: 3148770872 | E43: 0.49861111 | F43: F009 | G43: 2 | H43: G016 | I43: Fecha de último día pago (15 días después del tránsito): 👉 Si el tránsito fue el 19-09-2025, el último día para pagar sería el 04-10-2025. 🌐 Enlace para pagar online: www.serravalle.it | J43: MANCATO P._Images/f93fc742.ARCHIVO.081058.png | K43: MANCATO P._Images/f93fc742.RECIBO DE PAGO.082959.jpg | L43: MANCATO PAGAMENTO | M43: 09. SEPTIEMBRE | N43: 45919
A44: 47f471ef | B44: PAGADO | C44: 10/10/2025 | D44: 3452652971 | E44: 0.70694444 | F44: F026 | G44: 9.6 | H44: G025 | I44: 🗓️ Fecha de emisión del Mancato Pagamento: 25/09/2025 ⏳ Fecha límite de pago: 15 días después de la emisión → 10/10/2025 🌐 Enlace para pagar online: www.itpspa.it | J44: MANCATO P._Files_/47f471ef.ARCHIVO.091058.pdf | K44: MANCATO P._Images/47f471ef.RECIBO DE PAGO.154826.jpg | L44: MANCATO PAGAMENTO | M44: 09. SEPTIEMBRE | N44: 45925
A45: 5521a7c2 | B45: PAGADO | C45: 10/10/2025 | D45: 3452652559 | E45: 0.58263889 | F45: F026 | G45: 12 | H45: G025 | I45: Fecha de emisión del Mancato Pagamento: 25/09/2025 ⏳ Fecha límite de pago: 15 días después → 10/10/2025 🌐 Enlace para pagar online: www.itpspa.it | J45: MANCATO P._Files_/5521a7c2.ARCHIVO.091510.pdf | K45: MANCATO P._Images/5521a7c2.RECIBO DE PAGO.154732.jpg | L45: MANCATO PAGAMENTO | M45: 09. SEPTIEMBRE | N45: 45925
A46: 2fcc9030 | B46: PAGADO | C46: 27/09/2025 | D46: 5062565899 | E46: 0.77777778 | F46: F014 | G46: 73.1 | H46: G004 | I46: Fecha en que se hizo el Mancato Pagamento (transito/verbale): 05/02/2025 ⏳ Fecha límite de pago (urgente): ⚠️ No aparece explícita en el documento. Normalmente Autostrade da 15 días desde la fecha de notificación (o desde la emisión de la lettera di sollecito). Te recomiendo revisar la carta física o el PDF completo: ahí suele aparecer en frases como "entro il…". 🔗 Enlace web para pagar: 👉 https://cittadino.plugandpay.it (Además puedes pagar en www.pagopa.gov.it , App IO, banca online, tabaccherie o poste italiane). | J46: MANCATO P._Files_/2fcc9030.ARCHIVO.121437.pdf | K46: MANCATO P._Files_/2fcc9030.RECIBO DE PAGO.121437.pdf | L46: MANCATO PAGAMENTO | M46: 09. SEPTIEMBRE | N46: 45912
A47: 0aabc89b | B47: PAGADO | C47: 15/10/2025 | D47: 0078138080 | E47: 0.5 | F47: F002 | G47: 90 | H47: 451ba90f | I47: Son en realidad 2 furgones en un solo mancato pagamento: EG403NT y ES638NF | 📅 Fecha en la que se hizo el Mancato Pagamento: 22/09/2025 (indicado en la parte superior: FIRENZE, 22/09/2025) ⛔ Fecha límite de pago (URGENTE): 15/10/2025 🔗 Enlace para pagar online: www.autostrade.it 📧 Contacto útil: info@autostrade.it WhatsApp: +39 055 8883600 | J47: MANCATO P._Files_/0aabc89b.ARCHIVO.091326.pdf | K47: MANCATO P._Files_/0aabc89b.RECIBO DE PAGO.062724.pdf | L47: MANCATO PAGAMENTO | M47: 09. SEPTIEMBRE | N47: 45930
A48: 060f4d86 | B48: PAGADO | C48: 14/10/2025 | D48: 3452660552 | E48: 0.33819444 | F48: F028 | G48: 13.4 | H48: G034 | I48: 📅 Fecha en la que se hizo el Mancato Pagamento: 29/09/2025 ⛔ Fecha límite de pago (URGENTE): 15 días desde el 29/09/2025 → 14/10/2025 🔗 Enlace para pagar online: www.itpspa.it | J48: MANCATO P._Files_/060f4d86.ARCHIVO.125542.pdf | K48: MANCATO P._Images/060f4d86.RECIBO DE PAGO.062204.jpg | L48: MANCATO PAGAMENTO | M48: 09. SEPTIEMBRE | N48: 45959
A49: 68ea87d9 | B49: PAGADO | C49: 14/10/2025 | D49: 4453587588 | E49: 0.35416667 | F49: F028 | G49: 1.7 | H49: G034 | I49: 💶 Importo total a pagar: € 1,70 📅 Fecha en la que se hizo el Mancato Pagamento: 29/09/2025 ⛔ Fecha límite de pago (URGENTE): 15 días desde el 29/09/2025 → 14/10/2025 (después de esta fecha se añade una maggiorazione de €2,58 más gastos de notificación y procedimiento) 🔗 Enlace para pagar online: www.itpspa.it 📧 Contacto: dpo@ivreatorinopiacenzaspa.it | J49: MANCATO P._Files_/68ea87d9.ARCHIVO.131028.pdf | K49: MANCATO P._Images/68ea87d9.RECIBO DE PAGO.062303.jpg | L49: MANCATO PAGAMENTO | M49: 09. SEPTIEMBRE | N49: 45959
A50: 846606c7 | B50: PAGADO | C50: 14/10/2025 | D50: 4453587430 | E50: 0.34583333 | F50: F028 | G50: 1.9 | H50: G034 | I50: 📅 Fecha en la que se hizo el Mancato Pagamento: 29/09/2025 ⛔ Fecha límite de pago (URGENTE): 15 días desde el 29/09/2025 → 14/10/2025 (después de esta fecha se añade una maggiorazione de €2,58 más gastos de notificación y procedimiento) 🔗 Enlace para pagar online: www.itpspa.it 📧 Contacto: dpo@ivreatorinopiacenzaspa.it | J50: MANCATO P._Files_/846606c7.ARCHIVO.132957.pdf | K50: MANCATO P._Images/846606c7.RECIBO DE PAGO.062351.jpg | L50: MANCATO PAGAMENTO | M50: 09. SEPTIEMBRE | N50: 45959
A51: f0127425 | B51: PAGADO | C51: 15/10/2025 | D51: 3225614480 | E51: 0.58055556 | F51: F026 | G51: 17.9 | H51: G025 | I51: Entrata: Rondissone (420) Uscita: Milano Ghisolfa (443) Pista: 54 Classe di pedaggio: A Acconto pagato: € 0,00 Si indica que en caso de omesso pagamento → multa entre € 87,00 y € 344,00 + decurtazione di 2 punti patente | Fecha del Mancato Pagamento (emisión): 30/09/2025 ⛔ Fecha límite de pago (urgente): 15 días → 15/10/2025 💸 Recargo si se paga después: + € 2,58 por spese di riscossione 🔗 Enlace web para pagar: www.satapweb.it | J51: MANCATO P._Files_/f0127425.ARCHIVO.143918.pdf | K51: MANCATO P._Files_/f0127425.RECIBO DE PAGO.062607.pdf | L51: MANCATO PAGAMENTO | M51: 09. SEPTIEMBRE | N51: 45930
A52: db7576bc | B52: PAGADO | C52: 18/10/2025 | D52: 77250141619 | E52: 0.79236111 | F52: F015 | G52: 6.9 | H52: 451ba90f | I52: 📅 Fecha límite para el pago (urgente): 🔹 18/10/2025 🌐 Enlace para pagar: 🔹 www.serravalle.it → Home page, clic en “PAGA ORA” 🔹 También se pueden usar otros canales indicados: www.agid.gov.it/pagopa | J52: MANCATO P._Files_/db7576bc.ARCHIVO.182246.pdf | K52: MANCATO P._Images/db7576bc.RECIBO DE PAGO.161850.png | L52: SOLLECITO | M52: 10. OCTUBRE | N52: 45933
... A65: e25568b2 | B65: PAGADO | C65: 16/10/2025 | D65: 3148844669 | E65: 0.44097222 | F65: F028 | G65: 1.5 | H65: 451ba90f | I65: "Renzo Villareal" | 🌐 Dónde pagar: 💻 Online: www.serravalle.it → Pago con tarjeta de crédito 🏢 Físico: “Punti Cortesia” en las barreras de Milano Serravalle SpA Oficinas de la sociedad Oficinas postales (bollettino c/c, indicando la matrícula en la causale) 🏢 Entidad que expide el Mancato Pagamento: Milano Serravalle Milano Tangenziali SpA 📍 Dirección: Via del Bosco Rinnovato 4/A – 20057 Assago (MI) 📞 Teléfono: 02-575941 📧 Email: info@serravalle.it | J65: MANCATO P._Files_/e25568b2.ARCHIVO.191917.pdf | K65: MANCATO P._Images/e25568b2.RECIBO DE PAGO.082058.png | L65: MANCATO PAGAMENTO | M65: 10. OCTUBRE | N65: 45931
A66: a76605cf | B66: PAGADO | C66: 17/10/2025 | D66: 3079245282 | E66: 0.85833333 | F66: F013 | G66: 15.6 | H66: G026 | I66: Se pagó con telepass: 309274520 (Lo hizo Emerson) | J66: MANCATO P._Files_/a76605cf.ARCHIVO.192925.pdf | L66: MANCATO PAGAMENTO | M66: 10. OCTUBRE | N66: 45932
A67: f6c33855 | B67: PAGADO | C67: 17/10/2025 | D67: 3079175547 | E67: 0.61597222 | F67: F013 | G67: 20.4 | H67: G026 | I67: Se pagó con telepass: 276922952 (Lo hizo Emerson) | J67: MANCATO P._Files_/f6c33855.ARCHIVO.194107.pdf | L67: MANCATO PAGAMENTO | M67: 10. OCTUBRE | N67: 45932
A68: 437d88cd | B68: PAGADO | C68: 16/10/2025 | D68: 3148797800 | E68: 0.45347222 | F68: F021 | G68: 9.8 | H68: G033 | I68: 🌐 Dónde pagar: 💻 Online: www.serravalle.it → Pago vía web con tarjeta de crédito 🏢 Físico: “Punti Cortesia” en las barreras de Milano Serravalle SpA Oficinas de la sociedad Oficinas postales con versamento en c/c 🏢 Entidad que expide el Mancato Pagamento: Milano Serravalle Milano Tangenziali SpA 📍 Sede legale: Via del Bosco Rinnovato 4/A, 20057 Assago (MI) 📞 Tel: 02-575941 🌐 Web: www.serravalle.it | J68: MANCATO P._Files_/437d88cd.ARCHIVO.194614.pdf | K68: MANCATO P._Images/437d88cd.RECIBO DE PAGO.074648.png | L68: MANCATO PAGAMENTO | M68: 10. OCTUBRE | N68: 45931
A69: 099d89c4 | B69: PAGADO | C69: 16/10/2025 | D69: 3079134288 | E69: 0.34375 | F69: F021 | G69: 7.8 | H69: G033 | I69: Se pagó con telepass: 276922952 (Emerson lo hizo) | J69: MANCATO P._Files_/099d89c4.ARCHIVO.195059.pdf | L69: MANCATO PAGAMENTO | M69: 10. OCTUBRE | N69: 45931
A70: 6026888d | B70: PAGADO | C70: 22/10/2025 | D70: 5412390873 | E70: 0.63402778 | F70: F013 | G70: 23.9 | H70: G026 | I70: ⏰ Fecha límite de pago (15 días después): 22/10/2025 🌐 Enlace para pagar: www.sav-a5.it 🏢 Entidad emisora: S.A.V. S.p.A. (Società Autostrade Valdostane) 📍 Ubicación: 11024 Chatillon, Aosta – Italia ℹ️ Extras: Entrada: Arluno (441) Salida: Aosta G.S.B. (413) Clase del vehículo: A Motivo: Sprovvisto di denaro (Sin dinero para pagar en el peaje) Si no se paga dentro del plazo de 15 días, el importe se incrementa con gastos de gestión. En caso de impago, el caso será enviado a la Polizia Stradale, con una sanción administrativa entre €87,00 y €344,00, además de la obligación de pagar el peaje original. Datos personales tratados conforme al Reglamento UE 2016/679 (GDPR). | J70: MANCATO P._Files_/6026888d.ARCHIVO.140930.pdf | K70: MANCATO P._Images/6026888d.RECIBO DE PAGO.164336.png | L70: MANCATO PAGAMENTO | M70: 10. OCTUBRE | N70: 45937
A71: de10864c | B71: PAGADO | C71: 18/10/2025 | D71: 10092296 | E71: 0.47291667 | F71: F001 | G71: 4.9 | H71: G033 | I71: ⏰ Fecha límite de pago (15 días después): 18/10/2025 🌐 Enlace para pagar: www.a22.it 🏢 Entidad emisora: AUTOSTRADA DEL BRENNERO S.p.A. 📧 Correo: rmpp@autobrennero.it 📍 Ubicación: Italia (Tramo: Affi ➜ Trento Sud) ℹ️ Extras: Entrada: Affi (669) Salida: Trento Sud (684) Clase del vehículo: A Motivo: Sprovvisto di denaro (Sin dinero para pagar en el peaje) Importe original: €4,90 Importe pagado: €0,00 Incremento por pago fuera de plazo: +€2,60 (gastos de recaudación) Si no se paga, el crédito será recuperado de forma coactiva y los datos serán enviados a la Polizia Stradale, según el art. 176 del Código de la Strada (D.Lgs. 285/1992). Tratamiento de datos personales: conforme al Reglamento UE 2016/679 (GDPR). | J71: MANCATO P._Files_/de10864c.ARCHIVO.141401.pdf | K71: MANCATO P._Images/de10864c.RECIBO DE PAGO.093704.png | L71: MANCATO PAGAMENTO | M71: 10. OCTUBRE | N71: 45933
A72: c0364519 | B72: PAGADO | C72: 18/10/2025 | D72: 10094460 | E72: 0.56666667 | F72: F001 | G72: 4.9 | H72: G033 | I72: ⏰ Fecha límite de pago (15 días después): 18/10/2025 🌐 Enlace para pagar: www.a22.it 🏢 Entidad emisora: AUTOSTRADA DEL BRENNERO S.p.A. 📧 Correo: rmpp@autobrennero.it 📍 Ubicación: Tramo Trento Sud ➜ Affi (Italia) ℹ️ Detalles adicionales: Entrada: Trento Sud (684) Salida: Affi (669) Clase del vehículo: A Motivo: Sprovvisto di denaro (Sin dinero al momento del peaje) Importe original: €4,90 Importe pagado: €0,00 Incremento por pago fuera de plazo: +€2,60 (gastos de recaudación) ⚠️ Consecuencias si no se paga: Si el pago no se realiza dentro del plazo, se procederá al recupero coattivo del credito (cobro forzoso) y el caso podrá ser trasladado a la Polizia Stradale, conforme al art. 176, commi 11 e 21 del Codice della Strada (D.Lgs. 285/1992). | J72: MANCATO P._Files_/c0364519.ARCHIVO.142007.pdf | K72: MANCATO P._Images/c0364519.RECIBO DE PAGO.090751.png | L72: MANCATO PAGAMENTO | M72: 10. OCTUBRE | N72: 45933
A73: 625fc03c | B73: PAGADO | C73: 18/10/2025 | D73: 3079265454 | E73: 0.63958333 | F73: F001 | G73: 8.6 | H73: G033 | I73: Se pagó con telepass: 276922952 (Lo hizo Emerson) | J73: MANCATO P._Files_/625fc03c.ARCHIVO.142551.pdf | L73: MANCATO PAGAMENTO | M73: 10. OCTUBRE | N73: 45933
A74: bbc53fb3 | B74: PAGADO | C74: 18/10/2025 | D74: 5622634391 | E74: 0.43055556 | F74: F001 | G74: 10.5 | H74: G033 | I74: ⏳ Fecha límite de pago (último día sin recargo): 18/10/2025 (15 días después del tránsito) 🌐 Enlace para pagar: https://payonline.autobspd.it 📎 Página oficial: https://www.autobspd.it 🏢 Entidad emisora: Autostrada Brescia Verona Vicenza Padova S.p.A. 📍 Dirección: Via Flavio Gioia 71, 37135 Verona, Italia 📞 Teléfono: 045 8272222 — Número verde: 800 012 812 🏦 Pago por transferencia bancaria: Banco: Banco BPM S.p.A. – Agenzia VR-37 IBAN: IT19L050411710000000025252 SWIFT/BIC: BAPPIT21010 Titular: Autostrada Brescia Verona Vicenza Padova S.p.A. Causal: Numero Mancato Pagamento + Targa + Data | J74: MANCATO P._Files_/bbc53fb3.ARCHIVO.143057.pdf | K74: MANCATO P._Images/bbc53fb3.RECIBO DE PAGO.085404.png | L74: MANCATO PAGAMENTO | M74: 10. OCTUBRE | N74: 45933
A75: 5abd0c04 | B75: VENCIDO | C75: 01/11/2025 | D75: 77250148709 | E75: 0 | F75: F007 | G75: 33.54 | H75: 451ba90f | I75: Se avisó a Natalia de poder hacer los pagos antes de que venzan, no se hicieron los pagos por falta de tiempo | Son en realidad 5 M.Pagamento: (N:3540081183 - FY032BD - 20/02/2025 - 6.01€)(N:3540118076 - EM504JT - 14/03/2025 - 6.91€)(N:3540118183 - EM504JT - 14/03/25 - 6.91€)(N:6202902117 - EG403NT - 04/01/2025 - 7.60€)(N:6202964737 - FY592SE - 18/02/25 - 6.11€) | J75: MANCATO P._Files_/5abd0c04.ARCHIVO.101330.pdf | L75: SOLLECITO | M75: 10. OCTUBRE | N75: 45947
A76: 16ff4a3d | B76: PAGADO | C76: 24/10/2025 | D76: 6157077808 | E76: 0 | F76: F014 | G76: 18.5 | H76: G036 | I76: 🌐 Enlace web para pagar 👉 www.salt.it/paga-online/01 O también se puede pagar: 📮 En la oficina postal con el número de cuenta 14381438 a nombre de SALT p.A. Indicando la matrícula (Targa) y el número del mancato pagamento (6157077808) en la causale (motivo del pago). | J76: MANCATO P._Files_/16ff4a3d.ARCHIVO.130843.pdf | K76: MANCATO P._Images/16ff4a3d.RECIBO DE PAGO.165640.png | L76: MANCATO PAGAMENTO | M76: 10. OCTUBRE | N76: 45939
A77: 5e4bcff0 | B77: PAGADO | C77: 29/10/2025 | D77: 5622660412 | E77: 0 | F77: F014 | G77: 13 | H77: G036 | I77: 🌐 Enlace para pagar 👉 https://payonline.autobspd.it También puedes pagar de las siguientes formas: 💳 Con tarjeta de crédito en el sitio web anterior. 🏢 En las estaciones de peaje de la Autostrada Brescia Verona Vicenza Padova S.p.A. con personal autorizado. 🏬 En los Centros de Servicio (ver lista en www.autobspd.it ) de lunes a viernes de 8:30 a 17:30. 📮 En la oficina postal con c/c n° 1008204941, a nombre de Autostrada Brescia Verona Vicenza Padova S.p.A., indicando el número de mancato pagamento (5622660412) en la “causale”. 🏦 Por transferencia bancaria a: Banco: BANCO BPM S.p.A. IBAN: IT92 L 05034 11710 000000025252 SWIFT: BAPPIT21010 | J77: MANCATO P._Files_/5e4bcff0.ARCHIVO.131630.pdf | K77: MANCATO P._Images/5e4bcff0.RECIBO DE PAGO.084854.png | L77: MANCATO PAGAMENTO | M77: 10. OCTUBRE | N77: 45944
A78: 83f7b168 | B78: PAGADO | C78: 24/10/2025 | D78: 3079620518 | E78: 0 | F78: F014 | G78: 23.4 | H78: G036 | I78: 🌐 Enlaces y formas de pago Puedes pagar el importe de €23,40 mediante las siguientes opciones: 💻 En línea: www.autostrade.it 📱 A través de la App “Autostrade per l’Italia” 🏪 En los puntos Mooney (bares, estancos, quioscos) 🔍 Más detalles en la sección “Servizi al cliente” del sitio web www.autostrade.it | J78: MANCATO P._Files_/83f7b168.ARCHIVO.132241.pdf | K78: MANCATO P._Images/83f7b168.RECIBO DE PAGO.165245.png | L78: MANCATO PAGAMENTO | M78: 10. OCTUBRE | N78: 45939
A79: 6ce1ca52 | B79: PAGADO | C79: 28/10/2025 | D79: 3079809285 | E79: 0 | F79: F014 | G79: 6.8 | H79: G036 | I79: 🌐 Enlaces y formas de pago Puedes pagar los €6,80 mediante las siguientes opciones: 💻 En línea: www.autostrade.it 📱 A través de la App Muovy 🏪 En los puntos Mooney (bares, estancos, quioscos) 📚 También puedes consultar más información o métodos alternativos de pago en la sección “Muovy” del sitio web oficial. | J79: MANCATO P._Files_/6ce1ca52.ARCHIVO.132714.pdf | K79: MANCATO P._Images/6ce1ca52.RECIBO DE PAGO.084616.png | L79: MANCATO PAGAMENTO | M79: 10. OCTUBRE | N79: 45943
A80: f6d6e4f2 | B80: PAGADO | C80: 25/10/2025 | D80: 3079582643 | E80: 0 | F80: F014 | G80: 11.4 | H80: G034 | I80: 💳 Formas oficiales de pago Puedes pagar de 3 formas válidas: 📱 App Autostrade per l’Italia 🏪 Puntos Mooney (en bares, tabacchi o edicole) 🌐 También puedes consultar y pagar en línea desde la web oficial 👉 www.autostrade.it 🔍 Dentro de la web, ve a la sección “Servizi al cliente → Mancato pagamento pedaggio”, donde puedes introducir el número 3079582643 para ver y pagar el importe. | J80: MANCATO P._Files_/f6d6e4f2.ARCHIVO.134558.pdf | K80: MANCATO P._Images/f6d6e4f2.RECIBO DE PAGO.212220.png | L80: MANCATO PAGAMENTO | M80: 10. OCTUBRE | N80: 45940
A81: eb7d8994 | B81: PAGADO | C81: 25/10/2025 | D81: 3079578013 | E81: 0 | F81: F014 | G81: 16.3 | H81: G034 | I81: Puedes pagar fácilmente por varios medios oficiales: 🌐 En línea: www.autostrade.it → Ve a “Servizi al cliente → Mancato pagamento pedaggio” → Introduce el número 3079578013 y tu matrícula GB502TP. 📱 App “Autostrade per l’Italia” 🏪 Puntos Mooney (bar, tabacchi, edicole) | J81: MANCATO P._Files_/eb7d8994.ARCHIVO.135118.pdf | K81: MANCATO P._Images/eb7d8994.RECIBO DE PAGO.211908.png | L81: MANCATO PAGAMENTO | M81: 10. OCTUBRE | N81: 45940
A82: 826bf65c | B82: PAGADO | C82: 21/10/2025 | D82: 3148856739 | E82: 0 | F82: F025 | G82: 4.5 | H82: G017 | I82: 💳 Dónde y cómo pagar Tienes varias opciones oficiales para realizar el pago: 🌐 En línea: www.serravalle.it → Usa la opción “Pagamento on-line con carta di credito” → Introduce el número de mancato pagamento (3148856739) y la matrícula FM342HY 🏦 En oficinas postales (Uffici Postali) → Realiza un pago en el c/c indicado en el documento → En la causal escribe la matrícula del vehículo y el número del documento 🏢 En persona: En los “Punti Cortesia” de las barreras de Milano Serravalle O directamente en la sede de la sociedad | J82: MANCATO P._Files_/826bf65c.ARCHIVO.135959.pdf | K82: MANCATO P._Images/826bf65c.RECIBO DE PAGO.163656.png | L82: MANCATO PAGAMENTO | M82: 10. OCTUBRE | N82: 45936
A83: fd57ea55 | B83: PAGADO | C83: 21/10/2025 | D83: 3079437103 | E83: 0 | F83: F025 | G83: 12.9 | H83: G017 | I83: 💳 Dónde y cómo pagar Tienes varias formas válidas de pago: 🌐 En línea: 👉 www.autostrade.it En la sección “Muovy” → opción Pagamento Mancato Pedaggio (necesitarás introducir el número 3079437103 y la matrícula FM342HY) 📱 App: A través de la App Autostrade per l’Italia o App Muovy 🏪 Presencialmente: En puntos Mooney (bares, tabaquerías, quioscos) | J83: MANCATO P._Files_/fd57ea55.ARCHIVO.140658.pdf | K83: MANCATO P._Images/fd57ea55.RECIBO DE PAGO.163235.png | L83: MANCATO PAGAMENTO | M83: 10. OCTUBRE | N83: 45936
A84: c994b877 | B84: PAGADO | C84: 25/10/2025 | D84: 3452684339 | E84: 0 | F84: F025 | G84: 9.7 | H84: G017 | I84: 💳 Dónde y cómo pagar 🌐 En línea: www.itpspa.it → sección Pagamento Online (también compatible con Satispay) Necesario indicar el Número de referencia RMPP (3452684339) y la matrícula FM342HY. 🏪 Presencialmente: En los peajes atendidos por personal de ITP S.p.A. En los Centros de Servicio ITP S.p.A. (direcciones y horarios en www.itpspa.it ) 💳 Transferencia bancaria: IBAN: IT05B0503401006000000013830 BIC: PPIT22XXX Indicar siempre el Número de referencia RMPP (3452684339) | J84: MANCATO P._Files_/c994b877.ARCHIVO.141455.pdf | K84: MANCATO P._Images/c994b877.RECIBO DE PAGO.171745.png | L84: MANCATO PAGAMENTO | M84: 10. OCTUBRE | N84: 45940
A85: fd81cc16 | B85: PAGADO | C85: 25/10/2025 | D85: 4300698406 | E85: 0 | F85: F025 | G85: 30.2 | H85: G017 | I85: 💳 Dónde y cómo pagar 🌐 En línea: www.tirrenica.it → sección de pago Necesario indicar Número de Mancato Pagamento y matrícula FM842HY 🏪 Presencialmente: En todos los puntos Mooney (Bar, Tabacchi, Edicole) En oficinas de Autostrade Tirrenica P.A. 💳 Transferencia bancaria: IBAN: IT39E0306902887100000002973 Indicar en la causa la matrícula del vehículo y el Número de Mancato Pagamento | J85: MANCATO P._Files_/fd81cc16.ARCHIVO.141945.pdf | K85: MANCATO P._Images/fd81cc16.RECIBO DE PAGO.211537.png | L85: MANCATO PAGAMENTO | M85: 10. OCTUBRE | N85: 45940
A86: 43668890 | B86: PAGADO | C86: 26/10/2025 | D86: 3079682757 | E86: 0 | F86: F025 | G86: 58 | H86: G017 | I86: 💳 Dónde y cómo pagar 🌐 En línea: www.autostrade.it → sección de pago App Autostrade per l’Italia 🏪 Presencialmente: Puntos Mooney (Bar, Tabacchi, Edicole) 🔗 Más información y otras modalidades de pago: Sección Servicios al Cliente del sitio web: www.autostrade.it | J86: MANCATO P._Files_/43668890.ARCHIVO.142540.pdf | K86: MANCATO P._Images/43668890.RECIBO DE PAGO.213400.png | L86: MANCATO PAGAMENTO | M86: 10. OCTUBRE | N86: 45941
A87: 892c5ae4 | B87: PAGADO | C87: 26/10/2025 | D87: 3079665174 | E87: 0 | F87: F025 | G87: 14.8 | H87: G017 | I87: 💳 Dónde y cómo pagar 🌐 En línea: www.autostrade.it App Muovy / Autostrade 🏪 Presencialmente: Puntos Mooney (Bar, Tabacchi, Edicole) 🔗 Más información y otras modalidades de pago: Sección Muovy del sitio web: www.autostrade.it | J87: MANCATO P._Files_/892c5ae4.ARCHIVO.142943.pdf | K87: MANCATO P._Images/892c5ae4.RECIBO DE PAGO.213029.png | L87: MANCATO PAGAMENTO | M87: 10. OCTUBRE | N87: 45941
... A100: cdc73c57 | B100: PAGADO | C100: 25/10/2025 | D100: 6157078822 | E100: 0 | F100: F022 | G100: 9.8 | H100: G033 | I100: 🌐 Enlace oficial para pagar online: 🔗 https://www.salt.it/paga-online/ También puedes pagar: 🏦 En una oficina postal italiana (conto corrente postale n. 14381438) 📄 Indicando en la causale: 👉 “Mancato Pagamento n° 6157078822” + la targa ND600Z3 | J100: MANCATO P._Files_/cdc73c57.ARCHIVO.110143.pdf | K100: MANCATO P._Images/cdc73c57.RECIBO DE PAGO.170117.png | L100: MANCATO PAGAMENTO | M100: 10. OCTUBRE | N100: 45940
A101: c218d5e8 | B101: PAGADO | C101: 04/11/2025 | D101: 4079114684 | E101: 0 | F101: F014 | G101: 11.4 | H101: G036 | I101: EMERSON LO PAGÓ CON TELEPASS |💳 Formas de pago: En el sitio web www.autostrade.it Aplicación “Autostrade per l’Italia” Puntos Mooney (Bar, Tabacchi, Edicole) ❓ Motivo del documento: No se efectuó el pago del peaje en la autopista en el tramo Milano Sud → Reggio Emilia. 🏛️ Emitido por: Autostrade per l’Italia 📍 Ubicación: Peaje autopista tramo Milano Sud – Reggio Emilia | J101: MANCATO P._Files_/c218d5e8.ARCHIVO.143935.pdf | L101: MANCATO PAGAMENTO | M101: 10. OCTUBRE | N101: 45950
A102: 95926ac8 | B102: PAGADO | C102: 01/11/2025 | D102: 3225678477 | E102: 0 | F102: F029 | G102: 15.6 | H102: G028 | I102: 💳 Formas de pago: Online en www.satapweb.it (también con Satispay) Oficina postal, c/c 18162107, indicando matrícula y número de mancato pagamento En las estaciones de peaje de la red Satap Tronco A4 ❓ Motivo del documento: No se efectuó el pago del peaje en la autopista RONDISSONE → ARLUNO, pista 22, clase de vehículo B. 🏛️ Emitido por: Satap S.p.A., Dirección y Coordinamiento ASTM 📍 Ubicación: 10144 Torino (TO), Italia | J102: MANCATO P._Files_/95926ac8.ARCHIVO.144719.pdf | K102: MANCATO P._Images/95926ac8.RECIBO DE PAGO.092646.jpg | L102: MANCATO PAGAMENTO | M102: 10. OCTUBRE | N102: 45947
A103: 45112840 | B103: PAGADO | C103: 01/11/2025 | D103: 3452700382 | E103: 0 | F103: F029 | G103: 13.8 | H103: G028 | I103: 💳 Formas de pago: Online en www.itpspa.it (también con Satispay) En estaciones de peaje gestionadas por ITP S.p.A. Transferencia bancaria IBAN: IT 05 B 05034 01006 000000013830 (indicar matrícula y número de mancato pagamento) ❓ Motivo del documento: No se efectuó el pago del peaje en la autopista Milano Ovest → Villanova Barrier, pista 26, clase de vehículo B. Causal: “Sprovvisto di denaro” (sin dinero). 🏛️ Emitido por: ITP S.p.A., Ivrea Torino Piacenza S.p.A, Tronco 2 📍 Ubicación: Corso Vittorio Emanuele II, 178, 10138 Torino (TO), Italia | J103: MANCATO P._Files_/45112840.ARCHIVO.145136.pdf | K103: MANCATO P._Images/45112840.RECIBO DE PAGO.092524.jpg | L103: MANCATO PAGAMENTO | M103: 10. OCTUBRE | N103: 45947
A104: 90dfd9d2 | B104: PAGADO | C104: 01/11/2025 | D104: 4453680797 | E104: 0 | F104: F029 | G104: 1.5 | H104: G028 | I104: 💳 Formas de pago: Online en www.itpspa.it (sección “Mancato Pagamento/Pagamento Online”), también con Satispay Transitando en las pistas manuales de peaje gestionadas por ITP S.p.A. Transferencia bancaria IBAN: IT 60 05034 01006 0000 00013829 (indicar matrícula y número de referencia RMPP) Centro servicios ITP S.p.A. de Settimo Torinese ❓ Motivo del documento: No se efectuó el pago del peaje en la autopista Direzione Sud → Bruere Barriera, pista 19, clase de vehículo B. Causal: “Sprovvisto di denaro” (sin dinero). 🏛️ Emitido por: ITP S.p.A., Ivrea Torino Piacenza S.p.A 📍 Ubicación: Corso Vittorio Emanuele II, 178, 10138 Torino (TO), Italia | J104: MANCATO P._Files_/90dfd9d2.ARCHIVO.145538.pdf | K104: MANCATO P._Images/90dfd9d2.RECIBO DE PAGO.092432.jpg | L104: MANCATO PAGAMENTO | M104: 10. OCTUBRE | N104: 45947
A105: 4e2e7fe3 | B105: PAGADO | C105: 01/11/2025 | D105: 4453680847 | E105: 0 | F105: F029 | G105: 1.5 | H105: G028 | I105: 💳 Formas de pago: Online en www.itpspa.it (sección “Mancato Pagamento/Pagamento Online”), también con Satispay Transitando en las pistas manuales de peaje gestionadas por ITP S.p.A. Transferencia bancaria IBAN: IT 60 … (indicar matrícula y número de referencia RMPP) Centro de servicios ITP S.p.A. de Settimo Torinese ❓ Motivo del documento: No se efectuó el pago del peaje en la autopista Direzione Nord → Falchera Barriera, pista 18, clase de vehículo B. Causal: “Sprovvisto di denaro” (sin dinero). 🏛️ Emitido por: ITP S.p.A., Ivrea Torino Piacenza S.p.A, Tronco 1 📍 Ubicación: Corso Vittorio Emanuele II, 178, 10138 Torino (TO), Italia | J105: MANCATO P._Files_/4e2e7fe3.ARCHIVO.150016.pdf | K105: MANCATO P._Images/4e2e7fe3.RECIBO DE PAGO.092337.png | L105: MANCATO PAGAMENTO | M105: 10. OCTUBRE | N105: 45947
A106: 9ded0156 | B106: PAGADO | C106: 01/11/2025 | D106: 4453680490 | E106: 0 | F106: F029 | G106: 2 | H106: G028 | I106: 💳 Formas de pago: Online en www.itpspa.it (sección “Mancato Pagamento/Pagamento Online”), también con Satispay Transitando en las pistas manuales de peaje gestionadas por ITP S.p.A. Transferencia bancaria IBAN: IT 05 B 05034 01006 00000013829 (indicar matrícula y número de referencia RMPP) Centro de servicios ITP S.p.A. de Settimo Torinese ❓ Motivo del documento: No se efectuó el pago del peaje en la autopista Direzione Nord → Trofarello Barriera, pista 01, clase de vehículo B. Causal: “Sprovvisto di denaro” (sin dinero). 🏛️ Emitido por: ITP S.p.A., Ivrea Torino Piacenza S.p.A, Tronco 1 📍 Ubicación: Corso Vittorio Emanuele II, 178, 10138 Torino (TO), Italia | J106: MANCATO P._Files_/9ded0156.ARCHIVO.150348.pdf | K106: MANCATO P._Images/9ded0156.RECIBO DE PAGO.090248.png | L106: MANCATO PAGAMENTO | M106: 10. OCTUBRE | N106: 45947
A107: 2899c218 | B107: PAGADO | C107: 01/11/2025 | D107: 4453680573 | E107: 0 | F107: F029 | G107: 1.5 | H107: G028 | I107: 🌐 Enlace para pagar: www.itpspa.it 💳 Formas de pago: Presso gli sportelli bancari (IBAN IT60 I 05034 01006 000000013829, SWIFT BAPPIT21A76) Centro Servicios Punto Blu ITP Online en www.itpspa.it (sección “Mancato Pagamento/Pagamento Online”), también con Satispay Después de 15 días, se añade € 2,58 por gastos de recaudación ❓ Motivo del documento: El peaje no fue abonado (letra "R" en modalidad de pago) debido a: Falta de tarjeta o tarjeta no habilitada Viacard con crédito insuficiente Tarjeta dañada o no leída Ruta: Tronco 1, salida/pista específica según transito registrado. 🏛️ Emitido por: ITP S.p.A., Ivrea Torino Piacenza S.p.A, Tronco 1 📍 Ubicación: Corso Vittorio Emanuele II, 178, 10138 Torino (TO), Italia | J107: MANCATO P._Files_/2899c218.ARCHIVO.151716.pdf | K107: MANCATO P._Images/2899c218.RECIBO DE PAGO.085827.png | L107: MANCATO PAGAMENTO | M107: 10. OCTUBRE | N107: 45947
A108: a451a3d0 | B108: PAGADO | C108: 04/11/2025 | D108: 3148885787 | E108: 0 | F108: F001 | G108: 2.9 | H108: G017 | I108: 🌐 Enlace para pagar: www.serravalle.it 💳 Formas de pago: Online en www.serravalle.it En las “Punti Corriscia” en las barreras de peaje gestionadas por Milano Serravalle SpA Oficinas de la sociedad Uffici Postali con indicación de matrícula en la causale del pago Después de 15 días, se añade € 2,58 por gastos de recaudación ❓ Motivo del documento: No se efectuó el pago del peaje en la autopista Milano Ovest → Gropello, pista 62, clase de vehículo A. 🏛️ Emitido por: Milano Serravalle Milano Tangenziali SpA 📍 Ubicación: Via del Bosco Rinnovato 4/A, 20057 Assago (MI), Italia | J108: MANCATO P._Files_/a451a3d0.ARCHIVO.151613.pdf | K108: MANCATO P._Images/a451a3d0.RECIBO DE PAGO.140551.png | L108: MANCATO PAGAMENTO | M108: 10. OCTUBRE | N108: 45950
A109: d3a33e68 | B109: PAGADO | C109: 10/11/2025 | D109: 77250156059 | E109: 0 | F109: F001 | G109: 6.64 | H109: 451ba90f | I109: 🌐 Enlace para pagar en línea: 👉 www.serravalle.it (en la página principal, hacer clic en “PAGA ORA”) | J109: MANCATO P._Files_/d3a33e68.ARCHIVO.081314.pdf | K109: MANCATO P._Images/d3a33e68.RECIBO DE PAGO.152408.png | L109: SOLLECITO | M109: 10. OCTUBRE | N109: 45956
A110: f7739ff8 | B110: PAGADO | C110: 03/11/2025 | D110: 003-566-001-258 | E110: 0 | F110: F002 | G110: 51 | H110: 451ba90f | I110: 🌐 Enlace de pago www.ticket.park-depot.it 🏢 Emisor ParkDepot SRL/GmbH 📍 Sede Bolzano, Italia ⚠️ Motivo Infracción de estacionamiento no pagada 🧾 Consecuencia Envío a agencia de cobro en 14 días si no se paga | J110: MANCATO P._Files_/f7739ff8.ARCHIVO.082810.pdf | K110: MANCATO P._Images/f7739ff8.RECIBO DE PAGO.142404.jpg | L110: SOLLECITO | M110: 10. OCTUBRE | N110: 45949
A111: 2999a91e | B111: PAGADO | C111: 03/11/2025 | D111: 003-566-001-287 | E111: 0 | F111: F006 | G111: 51 | H111: 451ba90f | I111: 🌐 Enlace para pagar online: 👉 www.ticket.park-depot.it | 📲 También puedes escanear el QR code que aparece en la carta. 📄 Motivo del documento Este documento es un “Ultimo Avvertimento” (Último aviso) emitido por ParkDepot. Indica que la multa o penalización contractual por una infracción de estacionamiento del 13/11/2024 (vehículo con placa EM504JT) aún no ha sido pagada, pese a varios recordatorios previos. ⚠️ Si el pago no se realiza dentro de 14 días, el crédito será entregado a una agencia de recuperación de deudas (recupero crediti), lo que ocasionará gastos adicionales y posibles medidas legales. | J111: MANCATO P._Files_/2999a91e.ARCHIVO.083216.pdf | K111: MANCATO P._Images/2999a91e.RECIBO DE PAGO.142440.jpg | L111: SOLLECITO | M111: 10. OCTUBRE | N111: 45949
A112: 4bf1ef28 | B112: PAGADO | C112: 03/11/2025 | D112: 003-566-001-298 | E112: 0 | F112: F006 | G112: 51 | H112: 451ba90f | I112: 🌐 Enlace de pago online: 👉 www.ticket.park-depot.it (Se puede también escanear el QR del documento) 📄 Motivo del documento: 💢 "Ultimo Avvertimento - Trasgressione al parcheggio del 14.11.2024" Significa que el vehículo con la matrícula EM504JT no respetó las condiciones de estacionamiento (por ejemplo, tiempo límite o registro no realizado) y no se ha pagado la penalidad contractual anterior, pese a varios avisos. | J112: MANCATO P._Files_/4bf1ef28.ARCHIVO.083936.pdf | K112: MANCATO P._Images/4bf1ef28.RECIBO DE PAGO.142513.jpg | L112: SOLLECITO | M112: 10. OCTUBRE | N112: 45949
A113: 2095069 | B113: PAGADO | C113: 03/11/2025 | D113: 003-566-001-268 | E113: 0 | F113: F006 | G113: 51 | H113: 451ba90f | I113: 🌐 Enlace para pagar online: 👉 www.ticket.park-depot.it (O también se puede pagar escaneando el QR code en el documento) 📄 Motivo del documento: 💢 “Ultimo Avvertimento - Trasgressione al parcheggio del 12.11.2024” ➡️ Esto significa que el vehículo con la matrícula EM504JT cometió una infracción relacionada con el estacionamiento (por ejemplo, exceder el tiempo permitido o no registrar la estancia). A pesar de varios recordatorios anteriores, la penalidad contractual no ha sido pagada. Este documento es el último aviso antes del envío del caso a cobranza. | J113: MANCATO P._Files_/7636feb6.ARCHIVO.175347.pdf | K113: MANCATO P._Images/2095069.RECIBO DE PAGO.142539.jpg | L113: SOLLECITO | M113: 10. OCTUBRE | N113: 45949
A114: 18deadf6 | B114: PAGADO | C114: 05/11/2025 | D114: 4453707095 | E114: 0 | F114: F014 | G114: 13.2 | H114: G036 | I114: 🌐 Enlace para pagar: 👉 https://www.itpspa.it | J114: MANCATO P._Files_/18deadf6.ARCHIVO.074247.pdf | K114: MANCATO P._Images/18deadf6.RECIBO DE PAGO.151806.png | L114: MANCATO PAGAMENTO | M114: 10. OCTUBRE | N114: 45951
A115: d1d4879c | B115: PAGADO | C115: 04/11/2025 | D115: 4453689699 | E115: 0 | F115: F025 | G115: 1.9 | H115: G034 | I115: 🌐 Enlace para pagar: 👉 https://www.itpspa.it → Ir a la sección “Mancato Pagamento / Pagamento Online” 🏧 Alternativamente puedes pagar: En las pistas manuales de peaje (ITP S.p.A.) durante un tránsito futuro. O mediante transferencia bancaria: 💳 IBAN: IT60 I 05034 01006 0000 00013829 SWIFT/BIC: BAPPIT21A76 Causale: indicar la TARGA (FM342HY) y el N° Mancato Pagamento (4453689699). 📄 Motivo del mancato pagamento: ➡️ “Sprovvisto di denaro” — es decir, no se disponía de dinero al momento del peaje, por lo que no se pagó el importe completo del tránsito. ⚠️ Consecuencias si no se paga: Después de 15 días, recargo de €2,58. Si el pago no se realiza, el caso puede ser enviado a la Polizia Stradale, generando una multa entre €87 y €345 y la pérdida de 2 puntos en la licencia. 🏢 Entidad emisora: IVREA TORINO PIACENZA S.p.A. (ITP S.p.A.) 📍 Dirección: Corso Vittorio Emanuele II, 178 – 10138 Torino, Italia 📧 Email: dpo@ivreatorinopiacenzaspa.it 🌐 Web: www.itpspa.it | J115: MANCATO P._Files_/d1d4879c.ARCHIVO.074827.pdf | K115: MANCATO P._Images/d1d4879c.RECIBO DE PAGO.141243.png | L115: MANCATO PAGAMENTO | M115: 10. OCTUBRE | N115: 45950
A116: ce8dacbb | B116: PAGADO | C116: 04/11/2025 | D116: 3094546243 | E116: 0 | F116: F025 | G116: 6.9 | H116: G034 | I116: 🌐 Dónde pagar: 👉 Sitio oficial: https://www.autostradadeifiori.it Ir a la sección “Informativa RMPP / Mancato Pagamento” 🏧 Alternativamente puedes pagar: En cualquier estación manual de la red Autostrada dei Fiori, o Por transferencia postal (versamento su c/c postale): 🏦 Número de cuenta: 001016582288 Titular: “Autostrada dei Fiori S.p.A.” Causale (concepto): Indica el N° Mancato Pagamento (3094546243) y la targa del vehículo (FM342HY) 📄 Motivo del mancato pagamento: ➡️ El documento indica que el peaje no fue pagado en su totalidad o en parte (“IL PEDAGGIO NON È STATO CORRISPOSTO IN TUTTO O IN PARTE”). No hay una causa específica (como “sin dinero” o “tarjeta dañada”), por lo que se asume que el pago no se completó en la cabina de peaje. | J116: MANCATO P._Files_/ce8dacbb.ARCHIVO.075529.pdf | K116: MANCATO P._Images/ce8dacbb.RECIBO DE PAGO.145946.png | L116: MANCATO PAGAMENTO | M116: 10. OCTUBRE | N116: 45950
A117: 647d62c4 | B117: PAGADO | C117: 01/11/2025 | D117: 6275944079 | E117: 0 | F117: F025 | G117: 24.2 | H117: G034 | I117: 🌐 Dónde pagar: 👉 Sitio web oficial: https://www.concessionideltirreno.it/paga-online-a12 (Sección para pagar online los Mancato Pagamento A12) 🏧 Alternativamente puedes pagar por cuenta postal: 🏦 Número de cuenta: 1069842787 Titular: “Concessioni del Tirreno S.p.A. – Tratta A12 RMPP” Causale: indicar la TARGA del vehículo (FM342HY) y el N° Mancato Pagamento (6275944079) 📄 Motivo del mancato pagamento: ➡️ “Il pedaggio non è stato corrisposto in tutto o in parte” 👉 Esto significa que el peaje no fue pagado parcial o totalmente en la salida (probablemente la máquina no aceptó pago o no se completó el proceso). ⚠️ Consecuencias si no se paga: Después de 15 días, el importe se incrementa por gastos de gestión. Si no se paga, el caso puede ser enviado a la Polizia Stradale, con: Multa entre €87,00 y €344,00, Y pérdida de 2 puntos en la licencia del conductor. | J117: MANCATO P._Files_/647d62c4.ARCHIVO.080126.pdf | K117: MANCATO P._Images/647d62c4.RECIBO DE PAGO.092159.jpg | L117: MANCATO PAGAMENTO | M117: 10. OCTUBRE | N117: 45947
A118: e5a353ed | B118: PAGADO | C118: 02/11/2025 | D118: 6157082667 | E118: 0 | F118: F025 | G118: 16.7 | H118: G034 | I118: 💳 Formas de pago En línea: 👉 www.salt.it/paga-online/ (usa el número de mancato pagamento y la matrícula del auto) Por correo postal: C/C postale n°: 14381438 Titular: SALT p.A. Causal: “MANCATO PAGAMENTO 6157082667 – TARGA FM342HY” | J118: MANCATO P._Files_/e5a353ed.ARCHIVO.080712.pdf | K118: MANCATO P._Images/e5a353ed.RECIBO DE PAGO.092333.jpg | L118: MANCATO PAGAMENTO | M118: 10. OCTUBRE | N118: 45948
A119: b91b8aa1 | B119: PAGADO | C119: 04/11/2025 | D119: 4079118545 | E119: 0 | F119: F025 | G119: 8.3 | H119: G034 | I119: Emerson lo pagó con TELEPASS|🌐 Enlace para pagar: www.autostrade.it También mediante la App Autostrade per l’Italia O en Punti Mooney (bares, estancos, quioscos) 📄 Motivo del documento: No se pagó el peaje (total o parcialmente) al salir de la autopista. Es un aviso de deuda pendiente por tránsito en la red de Autostrade per l’Italia. 🏢 Entidad emisora: Autostrade per l’Italia S.p.A. Tramo: Villanova B. → Casale Monferrato Sud 🌍 Web oficial: www.autostrade.it | J119: MANCATO P._Files_/b91b8aa1.ARCHIVO.081225.pdf | L119: MANCATO PAGAMENTO | M119: 10. OCTUBRE | N119: 45950
A120: 4fd5a404 | B120: PAGADO | C120: 05/11/2025 | D120: 3148887734 | E120: 0 | F120: F025 | G120: 1.5 | H120: G034 | I120: 🌐 Enlace para pagar: www.serravalle.it Pago online con tarjeta de crédito, o en Punti Corlesia en las barreras de Milano Serravalle SpA, oficinas de la sociedad, operadas manualmente o mediante giro postal. C/C postal: 40999203, a nombre de Milano Serravalle SpA Causal: indicar la matrícula y el número de mancato pagamento 📄 ¿Por qué te envían este documento? Porque no se pagó el peaje total o parcialmente al pasar por la autopista. Es un aviso de deuda pendiente por tránsito en la red de Milano Serravalle SpA. 🏢 Entidad emisora: Milano Serravalle Milano Tangenziali SpA Sede legal: Via del Bosco Rinnovato 4/A, 20057 Assago (MI) 🌍 Web: www.serravalle.it 📧 Email: info@serravalle.it ☎️ Teléfono: 02-575941 ℹ️ Extras / Observaciones: Si no se paga dentro de los 15 días, se aplican recargos y gastos adicionales. Pueden usar sistemas de video vigilancia para identificar al conductor y cobrar la deuda. El tratamiento de datos se realiza según el Reglamento UE 2016/679 (GDPR). | J120: MANCATO P._Files_/4fd5a404.ARCHIVO.081708.pdf | K120: MANCATO P._Images/4fd5a404.RECIBO DE PAGO.145933.png | L120: MANCATO PAGAMENTO | M120: 10. OCTUBRE | N120: 45951
A121: 30ed65cb | B121: PAGADO | C121: 05/11/2025 | D121: 4079159671 | E121: 0 | F121: F025 | G121: 7.9 | H121: G034 | I121: Emerson lo pagó con telepass|🌐 Enlace para pagar: www.autostrade.it App Autostrade per l’Italia Punti Mooney (bares, estancos, quioscos) 📄 ¿Por qué te envían este documento? Porque no se pagó el peaje total o parcialmente al pasar por la autopista. Es un aviso de deuda pendiente por tránsito en la red de Autostrade per l’Italia. 🏢 Entidad emisora: Autostrade per l’Italia S.p.A. Web oficial: www.autostrade.it ℹ️ Extras / Observaciones: Si no se paga dentro de los 15 días, se aplican recargos por gestión. El impago puede ser comunicado a la Polizia Stradale, generando una sanción administrativa según el artículo 176 del Codice della Strada y decurtación de 2 puntos del carné de conducir. Los datos personales se gestionan conforme al Reglamento UE 2016/679 (GDPR). | J121: MANCATO P._Files_/30ed65cb.ARCHIVO.082125.pdf | L121: MANCATO PAGAMENTO | M121: 10. OCTUBRE | N121: 45951
A122: fa6f243b | B122: PAGADO | C122: 04/11/2025 | D122: 3452704798 | E122: 0 | F122: F025 | G122: 4.9 | H122: G034 | I122: 🌐 Enlace para pagar: www.itpspa.it Pago en centros de servicio ITP S.p.A., ventanillas manuales de la autopista o bancos con SWIFT BAPPIT22XXX. Indicar número de mancato pagamento y targa del vehículo en la causal. 📄 ¿Por qué te envían este documento? Porque no se pagó el peaje total o parcialmente al pasar por Tronto 2 de la autopista ITP S.p.A. Es un aviso de deuda pendiente para el cobro del peaje. 🏢 Entidad emisora: ITP S.p.A. – Tronto 2 Dirección: Corso Vittorio Emanuele II, 178 – 10138 Torino 🌍 Web: www.itpspa.it | J122: MANCATO P._Files_/fa6f243b.ARCHIVO.082622.pdf | K122: MANCATO P._Images/fa6f243b.RECIBO DE PAGO.150509.png | L122: MANCATO PAGAMENTO | M122: 10. OCTUBRE | N122: 45950
